Workbook

Sheet Assumptions
A1: Key Financial Assumptions (Forecast)
A3: Assumption | B3: Value
A4: Base Growth Rate | B4: 0.16
A5: Tax Rate | B5: 0.22
A6: Discount Rate | B6: 0.1
A7: Inflation Rate | B7: 0.03
A8: Sales Target Units | B8: 6200

Sheet Revenue
A1: Revenue Projections by Product
A3: Product Line | B3: Base Units | C3: Unit Price | D3: Q1 Revenue | E3: Q2 Revenue | F3: Q3 Revenue | G3: Q4 Revenue | H3: Total Year
A4: Enterprise Software | B4: 1500 | C4: 450 | D4: =B4*C4/4 | E4: =D4*(1+Assumptions!B4) | F4: =E4*(1+Assumptions!B4) | G4: =F4*(1+Assumptions!B4) | H4: =SUM(D4:G4)
A5: Cloud Subscription | B5: 4200 | C5: 120 | D5: =B5*C5/4 | E5: =D5*(1+Assumptions!B4) | F5: =E5*(1+Assumptions!B4) | G5: =F5*(1+Assumptions!B4) | H5: =SUM(D5:G5)
A6: Consulting Services | B6: 800 | C6: 200 | D6: =B6*C6/4 | E6: =D6*(1+Assumptions!B4) | F6: =E6*(1+Assumptions!B4) | G6: =F6*(1+Assumptions!B4) | H6: =SUM(D6:G6)
A7: Hardware Appliances | B7: 400 | C7: 850 | D7: =B7*C7/4 | E7: =D7*(1+Assumptions!B4) | F7: =E7*(1+Assumptions!B4) | G7: =F7*(1+Assumptions!B4) | H7: =SUM(D7:G7)
A8: Total Revenue | D8: =SUM(D4:D7) | E8: =SUM(E4:E7) | F8: =SUM(F4:F7) | G8: =SUM(G4:G7) | H8: =SUM(H4:H7)

Sheet Costs
A1: Operating & Cost Breakdown
A3: Cost Category | B3: Type | C3: Q1 Costs | D3: Q2 Costs | E3: Q3 Costs | F3: Q4 Costs | G3: Annual Total
A4: Direct Labor / COGS | B4: COGS | C4: =Revenue!D8*0.35 | D4: =Revenue!E8*0.35 | E4: =Revenue!F8*0.35 | F4: =Revenue!G8*0.35 | G4: =SUM(C4:F4)
A5: Research & Development | B5: OPEX | C5: 120000 | D5: =C5*(1+Assumptions!B7) | E5: =D5*(1+Assumptions!B7) | F5: =E5*(1+Assumptions!B7) | G5: =SUM(C5:F5)
A6: Sales & Marketing | B6: OPEX | C6: =Revenue!D8*0.15 | D6: =Revenue!E8*0.15 | E6: =Revenue!F8*0.15 | F6: =Revenue!G8*0.15 | G6: =SUM(C6:F6)
A7: General & Administrative | B7: OPEX | C7: 85000 | D7: 85000 | E7: 85000 | F7: 85000 | G7: =SUM(C7:F7)
A8: Total Expenses | C8: =SUM(C4:C7) | D8: =SUM(D4:D7) | E8: =SUM(E4:E7) | F8: =SUM(F4:F7) | G8: =SUM(G4:G7)

Sheet Income Statement
A1: Executive Income Statement (Laporan Laba Rugi)
A3: Metric / Account | B3: Q1 | C3: Q2 | D3: Q3 | E3: Q4 | F3: Full Year
A4: Gross Revenue | B4: =Revenue!D8 | C4: =Revenue!E8 | D4: =Revenue!F8 | E4: =Revenue!G8 | F4: =Revenue!H8
A5: Total Expenses | B5: =Costs!C8 | C5: =Costs!D8 | D5: =Costs!F8 | E5: =Costs!F8 | F5: =Costs!G8
A6: Operating Income (EBIT) | B6: =B4-B5 | C6: =C4-C5 | D6: =D4-D5 | E6: =E4-E5 | F6: =SUM(B6:E6)
A7: Income Tax | B7: =B6*Assumptions!B5 | C7: =C6*Assumptions!B5 | D7: =D6*Assumptions!B5 | E7: =E6*Assumptions!B5 | F7: =SUM(B7:E7)
A8: Net Income | B8: =B6-B7 | C8: =C6-C7 | D8: =D6-D7 | E8: =E6-E7 | F8: =F6-F7
A9: AI Cloud Infrastructure Fee | B9: 20000 | C9: 25000 | D9: 30000 | E9: 35000 | F9: 110000
A10: R&D Innovation Grant | B10: 50000 | C10: 50000 | D10: 50000 | E10: 50000 | F10: 200000

Sheet Balance Sheet
A1: Executive Balance Sheet (Neraca)
A3: Balance Sheet Account | B3: Q1 | C3: Q2 | D3: Q3 | E3: Q4 | F3: Year End
A4: Cash & Cash Equivalents | B4: 180000 | C4: 142000 | D4: 168000 | E4: 195000 | F4: =E4
A5: Accounts Receivable | B5: =Revenue!D8*0.14 | C5: =Revenue!E8*0.14 | D5: =Revenue!F8*0.14 | E5: =Revenue!G8*0.14 | F5: =E5
A6: Inventories | B6: 85000 | C6: 88000 | D6: 92000 | E6: 95000 | F6: =E6
A7: Total Current Assets | B7: =SUM(B4:B6) | C7: =SUM(C4:C6) | D7: =SUM(D4:D6) | E7: =SUM(E4:E6) | F7: =E7
A8: Property, Plant & Equipment (Net) | B8: 540000 | C8: 440000 | D8: 430000 | E8: 420000 | F8: =E8
A9: Intangible Assets | B9: 60000 | C9: 60000 | D9: 58000 | E9: 58000 | F9: =E9
A10: Total Assets | B10: =B7+B8+B9 | C10: =C7+C8+C9 | D10: =D7+D8+D9 | E10: =E7+E8+E9 | F10: =E10
A11: Accounts Payable | B11: =Costs!C8*0.12 | C11: =Costs!D8*0.12 | D11: =Costs!E8*0.12 | E11: =Costs!F8*0.12 | F11: =E11
A12: Short-Term Debt | B12: 45000 | C12: 40000 | D12: 35000 | E12: 30000 | F12: =E12
A13: Total Current Liabilities | B13: =SUM(B11:B12) | C13: =SUM(C11:C12) | D13: =SUM(D11:D12) | E13: =SUM(E11:E12) | F13: =E13
A14: Long-Term Debt | B14: 220000 | C14: 210000 | D14: 200000 | E14: 190000 | F14: =E14
A15: Total Liabilities | B15: =B13+B14 | C15: =C13+C14 | D15: =D13+D14 | E15: =E13+E14 | F15: =E15
A16: Common Stock | B16: 200000 | C16: 200000 | D16: 200000 | E16: 200000 | F16: =E16
A17: Retained Earnings | B17: =B10-B15-B16 | C17: =C10-C15-C16 | D17: =D10-D15-D16 | E17: =E10-E15-E16 | F17: =E17
A18: Total Shareholders' Equity | B18: =B16+B17 | C18: =C16+C17 | D18: =D16+D17 | E18: =E16+E17 | F18: =E18
A19: Total Liabilities & Equity | B19: =B15+B18 | C19: =C15+C18 | D19: =D15+D18 | E19: =E15+E18 | F19: =E19

Sheet Cash Flow
A1: Executive Cash Flow Statement (Laporan Arus Kas)
A3: Cash Flow Account | B3: Q1 | C3: Q2 | D3: Q3 | E3: Q4 | F3: Full Year
A4: Net Income | B4: ='Income Statement'!B8 | C4: ='Income Statement'!C8 | D4: ='Income Statement'!D8 | E4: ='Income Statement'!E8 | F4: ='Income Statement'!F8
A5: Depreciation & Amortization | B5: 10000 | C5: 10000 | D5: 10000 | E5: 10000 | F5: =SUM(B5:E5)
A6: Change in Working Capital | B6: -6000 | C6: -5000 | D6: -4000 | E6: 3000 | F6: =SUM(B6:E6)
A7: Net Cash from Operating Activities | B7: =SUM(B4:B6) | C7: =SUM(C4:C6) | D7: =SUM(D4:D6) | E7: =SUM(E4:E6) | F7: =SUM(F4:F6)
A8: Capital Expenditures (CapEx) | B8: -40000 | C8: -35000 | D8: -15000 | E8: -12000 | F8: =SUM(B8:E8)
A9: Net Cash from Investing Activities | B9: =B8 | C9: =C8 | D9: =D8 | E9: =E8 | F9: =SUM(B9:E9)
A10: Repayment of Debt | B10: -5000 | C10: -5000 | D10: -5000 | E10: -5000 | F10: =SUM(B10:E10)
A11: Dividends Paid | B11: -15000 | C11: -8000 | D11: -8000 | E11: -12000 | F11: =SUM(B11:E11)
A12: Net Cash from Financing Activities | B12: =SUM(B10:B11) | C12: =SUM(C10:C11) | D12: =SUM(D10:D11) | E12: =SUM(E10:E11) | F12: =SUM(F10:F11)
A13: Net Increase / Decrease in Cash | B13: =B7+B9+B12 | C13: =C7+C9+C12 | D13: =D7+D9+D12 | E13: =E7+E9+E12 | F13: =SUM(B13:E13)
A14: Beginning Cash Balance | B14: 100000 | C14: =B15 | D14: =C15 | E14: =D15 | F14: 100000
A15: Ending Cash Balance | B15: =B13+B14 | C15: =C13+C14 | D15: =D13+D14 | E15: =E13+E14 | F15: =E15
