Workbook

Sheet Assumptions
A1: Key Financial Assumptions
A3: Assumption | B3: Value
A4: Base Growth Rate | B4: 0.08
A5: Tax Rate | B5: 0.22
A6: Discount Rate | B6: 0.1
A7: Inflation Rate | B7: 0.03
A8: Sales Target Units | B8: 5000

Sheet Revenue
A1: Revenue Projections by Product
A3: Product Line | B3: Base Units | C3: Unit Price | D3: Q1 Revenue | E3: Q2 Revenue | F3: Q3 Revenue | G3: Q4 Revenue | H3: Total Year
A4: Enterprise Software | B4: 1200 | C4: 450 | D4: =B4*C4/4 | E4: =D4*(1+Assumptions!B4) | F4: =E4*(1+Assumptions!B4) | G4: =F4*(1+Assumptions!B4) | H4: =SUM(D4:G4)
A5: Cloud Subscription | B5: 3500 | C5: 120 | D5: =B5*C5/4 | E5: =D5*(1+Assumptions!B4) | F5: =E5*(1+Assumptions!B4) | G5: =F5*(1+Assumptions!B4) | H5: =SUM(D5:G5)
A6: Consulting Services | B6: 800 | C6: 200 | D6: =B6*C6/4 | E6: =D6*(1+Assumptions!B4) | F6: 43500 | G6: =F6*(1+Assumptions!B4) | H6: =SUM(D6:G6)
A7: Hardware Appliances | B7: 400 | C7: 850 | D7: =B7*C7/4 | E7: =D7*(1+Assumptions!B4) | F7: =E7*(1+Assumptions!B4) | G7: =F7*(1+Assumptions!B4) | H7: =SUM(D7:G7)
A8: Total Revenue | D8: =SUM(D4:D7) | E8: =SUM(E4:E7) | F8: =SUM(F4:F7) | G8: =SUM(G4:G7) | H8: =SUM(H4:H7)

Sheet Costs
A1: Operating & Cost Breakdown
A3: Cost Category | B3: Type | C3: Q1 Costs | D3: Q2 Costs | E3: Q3 Costs | F3: Q4 Costs | G3: Annual Total
A4: Direct Labor / COGS | B4: COGS | C4: =Revenue!D8*0.35 | D4: =Revenue!E8*0.35 | E4: =Revenue!F8*0.35 | F4: =Revenue!G8*0.35 | G4: =SUM(C4:F4)
A5: Research & Development | B5: OPEX | C5: 120000 | D5: =C5*(1+Assumptions!B7) | E5: =D5*(1+Assumptions!B7) | F5: =E5*(1+Assumptions!B7) | G5: =SUM(C5:F5)
A6: Sales & Marketing | B6: OPEX | C6: =Revenue!D8*0.15 | D6: =Revenue!E8*0.15 | E6: =Revenue!F8*0.15 | F6: =Revenue!G8*0.15 | G6: =SUM(C6:F6)
A7: General & Administrative | B7: OPEX | C7: 85000 | D7: 85000 | E7: 85000 | F7: 85000 | G7: =SUM(C7:F7)
A8: Total Expenses | C8: =SUM(C4:C7) | D8: =SUM(D4:D7) | E8: =SUM(E4:E7) | F8: =SUM(F4:F7) | G8: =SUM(G4:G7)

Sheet Income Statement
A1: Executive Income Statement
A3: Metric | B3: Q1 | C3: Q2 | D3: Q3 | E3: Q4 | F3: Full Year
A4: Gross Revenue | B4: =Revenue!D8 | C4: =Revenue!E8 | D4: =Revenue!F8 | E4: =Revenue!G8 | F4: =Revenue!H8
A5: Total Expenses | B5: =Costs!C8 | C5: =Costs!D8 | D5: =Costs!F8 | E5: =Costs!F8 | F5: =Costs!G8
A6: Operating Income (EBIT) | B6: =B4-B5 | C6: =C4-C5 | D6: =D4-D5 | E6: =E4-E5 | F6: =SUM(B6:E6)
A7: Income Tax (22%) | B7: =B6*Assumptions!B5 | C7: =C6*Assumptions!B5 | D7: =D6*Assumptions!B5 | E7: =E6*Assumptions!B5 | F7: =SUM(B7:E7)
A8: Net Income | B8: =B6-B7 | C8: =C6-C7 | D8: =D6-D7 | E8: =E6-E7 | F8: =F6-F7
