Workbook
Name __123Graph_A: #REF!
Name __123Graph_A: #REF!
Name __123Graph_A: #REF!
Name __123Graph_B: #REF!
Name __123Graph_B: #REF!
Name __123Graph_B: #REF!
Name __123Graph_C: #REF!
Name __123Graph_C: #REF!
Name __123Graph_C: #REF!
Name __123Graph_D: #REF!
Name __123Graph_D: #REF!
Name __123Graph_D: #REF!
Name __123Graph_E: #REF!
Name __123Graph_E: #REF!
Name __123Graph_E: #REF!
Name __123Graph_F: #REF!
Name __123Graph_F: #REF!
Name __123Graph_F: #REF!
Name __123Graph_X: #REF!
Name __123Graph_X: #REF!
Name __123Graph_X: #REF!
Name _1: #REF!
Name _1: #REF!
Name _10: #REF!
Name _10: #REF!
Name _10: #REF!
Name _11: #REF!
Name _11: #REF!
Name _11: #REF!
Name _12: #REF!
Name _12: #REF!
Name _12: #REF!
Name _13: #REF!
Name _13: #REF!
Name _14: #REF!
Name _14: #REF!
Name _15: #REF!
Name _15: #REF!
Name _15: #REF!
Name _16: #REF!
Name _16: #REF!
Name _16: #REF!
Name _17: #REF!
Name _17: #REF!
Name _17: #REF!
Name _18: #REF!
Name _18: #REF!
Name _18: #REF!
Name _19: #REF!
Name _19: #REF!
Name _19: #REF!
Name _1A: #REF!
Name _1A: #REF!
Name _2: #REF!
Name _2: #REF!
Name _20: #REF!
Name _20: #REF!
Name _21: #REF!
Name _21: #REF!
Name _22: #REF!

Sheet Financials
B1: Income Statement | C1: Period 1 | D1: Period 2 | E1: Period 3 | F1: Period 4 | G1: Period 5 | H1: Period 6 | I1: Period 7 | J1: Period 8 | K1: Period 9 | L1: Period 10 | M1: Period 11 | N1: Period 12 | O1: Period 13 | P1: Period 14 | Q1: Period 15 | R1: Period 16 | S1: Period 17 | T1: Period 18 | U1: Period 19 | V1: Period 20 | W1: Period 21 | X1: Period 22 | Y1: Period 23 | Z1: Period 24 | AA1: Period 25 | AB1: Period 26 | AC1: Period 27 | AD1: Period 28 | AE1: Period 29 | AF1: Period 30 | AG1: Period 31 | AH1: Period 32 | AI1: Period 33 | AJ1: Period 34 | AK1: Period 35 | AL1: Period 36 | AM1: Period 37 | AN1: Period 38 | AO1: Period 39 | AP1: Period 40
C2: Values | D2: Values | E2: Values | F2: Values | G2: Values | H2: Values | I2: Values | J2: Values | K2: Values | L2: Values | M2: Values | N2: Values | O2: Values | P2: Values | Q2: Values | R2: Values | S2: Values | T2: Values | U2: Values | V2: Values | W2: Values | X2: Values | Y2: Values | Z2: Values | AA2: Values | AB2: Values | AC2: Values | AD2: Values | AE2: Values | AF2: Values | AG2: Values | AH2: Values | AI2: Values | AJ2: Values | AK2: Values | AL2: Values | AM2: Values | AN2: Values | AO2: Values | AP2: Values | AR2: 0 | AT2: 0 | AV2: 0 | AX2: 0 | AZ2: 0 | BB2: 0 | BD2: 0 | BF2: 0 | BH2: 0 | BJ2: 0 | BL2: 0 | BN2: 0 | BP2: 0 | BR2: 0 | BT2: 0 | BV2: 0 | BX2: 0 | BZ2: 0 | CB2: 0 | CD2: 0 | CF2: 0 | CH2: 0 | CJ2: 0 | CL2: 0 | CN2: 0 | CP2: 0 | CR2: 0 | CT2: 0 | CV2: 0 | CX2: 0 | CZ2: 0 | DB2: 0 | DD2: 0 | DF2: 0 | DH2: 0 | DJ2: 0 | DL2: 0 | DN2: 0 | DP2: 0 | DR2: 0 | DT2: 0 | DV2: 0 | DX2: 0 | DZ2: 0 | EB2: 0
A3: 0 | B3: =+#REF! -> #REF! | C3: 15339.238 | D3: 217503.04 | E3: 19056.423 | F3: 407728.31 | G3: 856519.08 | H3: 909823.4 | I3: 961018.41 | J3: 1008313.4 | K3: 1057973 | L3: 1057973 | M3: 1057973 | N3: 1057973 | O3: 1057973 | P3: 0 | Q3: 0 | AP3: 0 | AR3: 0 | AT3: 0 | AV3: 0 | AX3: 0 | AZ3: 0 | BB3: 0 | BD3: 0 | BF3: 0 | BH3: 0 | BJ3: 0 | BL3: 0 | BN3: 0 | BP3: 0 | BR3: 0 | BT3: 0 | BV3: 0 | BX3: 0 | BZ3: 0 | CB3: 0 | CD3: 0 | CF3: 0 | CH3: 0 | CJ3: 0 | CL3: 0 | CN3: 0 | CP3: 0 | CR3: 0 | CT3: 0 | CV3: 0 | CX3: 0 | CZ3: 0 | DB3: 0 | DD3: 0 | DF3: 0 | DH3: 0 | DJ3: 0 | DL3: 0 | DN3: 0 | DP3: 0 | DR3: 0 | DT3: 0 | DV3: 0 | DX3: 0 | DZ3: 0 | EB3: 0 | ED3: 0
B4: =+#REF! -> #REF! | C4: =IF(ISNUMBER(Historical!E105),Historical!E105, ) -> 100000 | D4: =IF(ISNUMBER(Historical!G105),Historical!G105, ) -> 110000 | E4: =IF(ISNUMBER(Historical!I105),Historical!I105, ) -> 120000 | F4: =IF(ISNUMBER(Projection!$H$7),IF(MONTH(Projection!H7)<>12,IF(ISNUMBER(Projection!L74),Projection!L74, ),IF(ISNUMBER(Historical!K105),Historical!K105, )), ) -> 132000 | G4: =IF(ISNUMBER(Projection!$H$7),IF(MONTH(Projection!$H$7)<>12,IF(ISNUMBER(Projection!N74),Projection!N74, ),IF(ISNUMBER(Projection!L74),Projection!L74, )), ) -> 157300 | H4: =IF(ISNUMBER(Projection!$H$7),IF(MONTH(Projection!$H$7)<>12,IF(ISNUMBER(Projection!P74),Projection!P74, ),IF(ISNUMBER(Projection!N74),Projection!N74, )), ) -> 173030 | I4: =IF(ISNUMBER(Projection!$H$7),IF(MONTH(Projection!$H$7)<>12,IF(ISNUMBER(Projection!R74),Projection!R74, ),IF(ISNUMBER(Projection!P74),Projection!P74, )), ) -> 190333 | J4: =IF(ISNUMBER(Projection!$H$7),IF(MONTH(Projection!$H$7)<>12,IF(ISNUMBER(Projection!T74),Projection!T74, ),IF(ISNUMBER(Projection!R74),Projection!R74, )), ) -> 209366.3 | K4: =IF(ISNUMBER(Projection!$H$7),IF(MONTH(Projection!$H$7)<>12,IF(ISNUMBER(Projection!Z74),Projection!Z74, ),IF(ISNUMBER(Projection!T74),Projection!T74, )), ) -> 209366.3 | L4: =IF(ISNUMBER(Projection!$H$7),IF(MONTH(Projection!$H$7)<>12,IF(ISNUMBER(Projection!AB74),Projection!AB74, ),IF(ISNUMBER(Projection!Z74),Projection!Z74, )), ) -> 209366.3 | M4: =IF(ISNUMBER(Projection!$H$7),IF(MONTH(Projection!$H$7)<>12,IF(ISNUMBER(Projection!AD74),Projection!AD74, ),IF(ISNUMBER(Projection!AB74),Projection!AB74, )), ) -> 209366.3 | N4: =IF(ISNUMBER(Projection!$H$7),IF(MONTH(Projection!$H$7)<>12,IF(ISNUMBER(Projection!AF74),Projection!AF74, ),IF(ISNUMBER(Projection!AD74),Projection!AD74, )), ) -> 209366.3 | O4: =IF(ISNUMBER(Projection!$H$7),IF(MONTH(Projection!$H$7)<>12,IF(ISNUMBER(Projection!AH74),Projection!AH74, ),IF(ISNUMBER(Projection!AF74),Projection!AF74, )), ) -> 209366.3 | R4: 0 | S4: 0 | T4: 0 | U4: 0 | V4: 0 | W4: 0 | X4: 0 | Y4: 0 | Z4: 0 | AA4: 0 | AB4: 0 | AC4: 0 | AD4: 0 | AE4: 0 | AF4: 0 | AG4: 0 | AH4: 0 | AI4: 0 | AJ4: 0 | AK4: 0 | AL4: 0 | AM4: 0 | AN4: 0 | AO4: 0 | AP4: 0 | AR4: 0 | AT4: 0 | AV4: 0 | AX4: 0 | AZ4: 0 | BB4: 0 | BD4: 0 | BF4: 0 | BH4: 0 | BJ4: 0 | BL4: 0 | BN4: 0 | BP4: 0 | BR4: 0 | BT4: 0 | BV4: 0 | BX4: 0 | BZ4: 0 | CB4: 0 | CD4: 0 | CF4: 0 | CH4: 0 | CJ4: 0 | CL4: 0 | CN4: 0 | CP4: 0 | CR4: 0 | CT4: 0 | CV4: 0 | CX4: 0 | CZ4: 0 | DB4: 0 | DD4: 0 | DF4: 0 | DH4: 0 | DJ4: 0 | DL4: 0 | DN4: 0 | DP4: 0 | DR4: 0 | DT4: 0 | DV4: 0 | DX4: 0 | DZ4: 0 | EB4: 0 | ED4: 0
B5: =+#REF! -> #REF!
B6: =+#REF! -> #REF!
B7: =+#REF! -> #REF!
B8: =+#REF! -> #REF!
B9: =+#REF! -> #REF!
B10: =+#REF! -> #REF!
B11: =+#REF! -> #REF!
B12: =+#REF! -> #REF!
B13: =+#REF! -> #REF!
B14: =+#REF! -> #REF!
B15: =+#REF! -> #REF!
B16: =+#REF! -> #REF!
... B18: =+#REF! -> #REF!
B19: =+#REF! -> #REF! | C19: 5524.5094 | D19: 207297.76 | E19: 4434.7247 | F19: 366041.15 | G19: 775480.23 | H19: 823925.26 | I19: 870663.86 | J19: 914153.37 | K19: 959817.35 | L19: 0 | M19: 0 | N19: 0 | O19: 0 | P19: 0
B20: =+#REF! -> #REF! | C20: =IF(ISNUMBER(Historical!E106),Historical!E106, ) -> 80000 | D20: =IF(ISNUMBER(Historical!G106),Historical!G106, ) -> 81000 | E20: =IF(ISNUMBER(Historical!I106),Historical!I106, ) -> 82000 | F20: =IF(ISNUMBER(Projection!H7),IF(MONTH(Projection!H7)<>12,IF(ISNUMBER(Projection!L75),Projection!L75, ),IF(ISNUMBER(Historical!K106),Historical!K106, )), ) -> 95040 | G20: =IF(ISNUMBER(Projection!H7),IF(MONTH(Projection!$H$7)<>12,IF(ISNUMBER(Projection!N75),Projection!N75, ),IF(ISNUMBER(Projection!L75),Projection!L75, )), ) -> 113256 | H20: =IF(ISNUMBER(Projection!H7),IF(MONTH(Projection!$H$7)<>12,IF(ISNUMBER(Projection!P75),Projection!P75, ),IF(ISNUMBER(Projection!N75),Projection!N75, )), ) -> 124581.6 | I20: =IF(ISNUMBER(Projection!$H$7),IF(MONTH(Projection!$H$7)<>12,IF(ISNUMBER(Projection!R75),Projection!R75, ),IF(ISNUMBER(Projection!P75),Projection!P75, )), ) -> 137039.76 | J20: =IF(ISNUMBER(Projection!H7),IF(MONTH(Projection!$H$7)<>12,IF(ISNUMBER(Projection!T75),Projection!T75, ),IF(ISNUMBER(Projection!R75),Projection!R75, )), ) -> 150743.74 | K20: =IF(ISNUMBER(Projection!H7),IF(MONTH(Projection!$H$7)<>12,IF(ISNUMBER(Projection!Z75),Projection!Z75, ),IF(ISNUMBER(Projection!T75),Projection!T75, )), ) -> 189937.11 | L20: =IF(ISNUMBER(Projection!$H$7),IF(MONTH(Projection!$H$7)<>12,IF(ISNUMBER(Projection!AB75),Projection!AB75, ),IF(ISNUMBER(Projection!Z75),Projection!Z75, )), ) -> 189937.11 | M20: =IF(ISNUMBER(Projection!$H$7),IF(MONTH(Projection!$H$7)<>12,IF(ISNUMBER(Projection!AD75),Projection!AD75, ),IF(ISNUMBER(Projection!AB75),Projection!AB75, )), ) -> 189937.11 | N20: =IF(ISNUMBER(Projection!$H$7),IF(MONTH(Projection!$H$7)<>12,IF(ISNUMBER(Projection!AF75),Projection!AF75, ),IF(ISNUMBER(Projection!AD75),Projection!AD75, )), ) -> 189937.11 | O20: =IF(ISNUMBER(Projection!$H$7),IF(MONTH(Projection!$H$7)<>12,IF(ISNUMBER(Projection!AH75),Projection!AH75, ),IF(ISNUMBER(Projection!AF75),Projection!AF75, )), ) -> 189937.11 | P20: 0 | Q20: 0 | R20: 0 | S20: 0 | T20: 0 | U20: 0 | V20: 0 | W20: 0 | X20: 0 | Y20: 0 | Z20: 0 | AA20: 0 | AB20: 0 | AC20: 0 | AD20: 0 | AE20: 0 | AF20: 0 | AG20: 0 | AH20: 0 | AI20: 0 | AJ20: 0 | AK20: 0 | AL20: 0 | AM20: 0 | AN20: 0 | AO20: 0 | AP20: 0
B21: =+#REF! -> #REF! | C21: =IF(ISNUMBER(Historical!E110),Historical!E110, )*Projection!$I$129 -> 0 | D21: =IF(ISNUMBER(Historical!G110),Historical!G110, )*Projection!$I$129 -> 0 | E21: =IF(ISNUMBER(Historical!I110),Historical!I110, )*Projection!$I$129 -> 0 | F21: =IF(ISNUMBER(Projection!H7),IF(MONTH(Projection!H7)<>12,IF(ISNUMBER(Projection!L79),Projection!L79, ),IF(ISNUMBER(Historical!K110),Historical!K110, )), )*Projection!$I$129 -> 0 | G21: =IF(ISNUMBER(Projection!$H$7),IF(MONTH(Projection!$H$7)<>12,IF(ISNUMBER(Projection!N137),Projection!N137, ),IF(ISNUMBER(Projection!L137),Projection!L137, )), ) -> 0 | H21: =IF(ISNUMBER(Projection!$H$7),IF(MONTH(Projection!$H$7)<>12,IF(ISNUMBER(Projection!P137),Projection!P137, ),IF(ISNUMBER(Projection!N137),Projection!N137, )), ) -> 0 | I21: =IF(ISNUMBER(Projection!$H$7),IF(MONTH(Projection!$H$7)<>12,IF(ISNUMBER(Projection!R137),Projection!R137, ),IF(ISNUMBER(Projection!P137),Projection!P137, )), ) -> 0 | J21: =IF(ISNUMBER(Projection!$H$7),IF(MONTH(Projection!$H$7)<>12,IF(ISNUMBER(Projection!T137),Projection!T137, ),IF(ISNUMBER(Projection!R137),Projection!R137, )), ) -> 0 | K21: =IF(ISNUMBER(Projection!$H$7),IF(MONTH(Projection!$H$7)<>12,IF(ISNUMBER(Projection!Z137),Projection!Z137, ),IF(ISNUMBER(Projection!T137),Projection!T137, )), ) -> 0 | L21: =IF(ISNUMBER(Projection!$H$7),IF(MONTH(Projection!$H$7)<>12,IF(ISNUMBER(Projection!AB137),Projection!AB137, ),IF(ISNUMBER(Projection!Z137),Projection!Z137, )), ) -> 0 | M21: =IF(ISNUMBER(Projection!$H$7),IF(MONTH(Projection!$H$7)<>12,IF(ISNUMBER(Projection!AD137),Projection!AD137, ),IF(ISNUMBER(Projection!AB137),Projection!AB137, )), ) -> 0 | N21: =IF(ISNUMBER(Projection!$H$7),IF(MONTH(Projection!$H$7)<>12,IF(ISNUMBER(Projection!AF137),Projection!AF137, ),IF(ISNUMBER(Projection!AD137),Projection!AD137, )), ) -> 0 | O21: =IF(ISNUMBER(Projection!$H$7),IF(MONTH(Projection!$H$7)<>12,IF(ISNUMBER(Projection!AH137),Projection!AH137, ),IF(ISNUMBER(Projection!AF137),Projection!AF137, )), ) -> 0
B22: =+#REF! -> #REF!
B23: =+#REF! -> #REF!
B24: =+#REF! -> #REF!
B25: =+#REF! -> #REF!
A26: 0 | B26: =+#REF! -> #REF!
B27: =+#REF! -> #REF!
B28: =+#REF! -> #REF!
B29: =+#REF! -> #REF!
B30: =+#REF! -> #REF!
B31: =+#REF! -> #REF!
B32: =+#REF! -> #REF!
A33: 0 | B33: =+#REF! -> #REF!
B34: =+#REF! -> #REF!
B35: =+#REF! -> #REF! | C35: =C3-C19 -> 9814.7286 | D35: =D3-D19 -> 10205.272 | E35: =E3-E19 -> 14621.699 | F35: =F3-F19 -> 41687.164 | G35: =G3-G19 -> 81038.855 | H35: =H3-H19 -> 85898.138 | I35: =I3-I19 -> 90354.549 | J35: =J3-J19 -> 94159.984 | ... AP35: =AP3-AP19 -> 0
B36: =+#REF! -> #REF! | C36: 59742.618 | D36: 6119.191 | E36: 5670.4059 | F36: 8134.2513 | G36: 14892.779 | H36: 16150.423 | I36: 17427.497 | J36: 18691.182 | K36: 20042.504 | L36: 1994.1003 | M36: 1994.1003 | N36: 1994.1003 | O36: 1994.1003
A37: 0 | B37: =+#REF! -> #REF! | C37: =IF(ISNUMBER(Historical!E108),Historical!E108, ) -> 5000 | D37: =IF(ISNUMBER(Historical!G108),Historical!G108, ) -> 5100 | E37: =IF(ISNUMBER(Historical!I108),Historical!I108, ) -> 5200 | F37: =IF(ISNUMBER(Projection!H7),IF(MONTH(Projection!H7)<>12,IF(ISNUMBER(Projection!L77),Projection!L77, ),IF(ISNUMBER(Historical!K108),Historical!K108, )), ) -> 6600 | G37: =IF(ISNUMBER(Projection!H7),IF(MONTH(Projection!$H$7)<>12,IF(ISNUMBER(Projection!N77),Projection!N77, ),IF(ISNUMBER(Projection!L77),Projection!L77, )), ) -> 7865 | H37: =IF(ISNUMBER(Projection!H7),IF(MONTH(Projection!$H$7)<>12,IF(ISNUMBER(Projection!P77),Projection!P77, ),IF(ISNUMBER(Projection!N77),Projection!N77, )), ) -> 8651.5 | I37: =IF(ISNUMBER(Projection!H7),IF(MONTH(Projection!$H$7)<>12,IF(ISNUMBER(Projection!R77),Projection!R77, ),IF(ISNUMBER(Projection!P77),Projection!P77, )), ) -> 9516.65 | J37: =IF(ISNUMBER(Projection!H7),IF(MONTH(Projection!$H$7)<>12,IF(ISNUMBER(Projection!T77),Projection!T77, ),IF(ISNUMBER(Projection!R77),Projection!R77, )), ) -> 10468.315 | K37: =IF(ISNUMBER(Projection!H7),IF(MONTH(Projection!$H$7)<>12,IF(ISNUMBER(Projection!Z77),Projection!Z77, ),IF(ISNUMBER(Projection!T77),Projection!T77, )), ) -> 3650.9408 | L37: =IF(ISNUMBER(Projection!H7),IF(MONTH(Projection!$H$7)<>12,IF(ISNUMBER(Projection!AB77),Projection!AB77, ),IF(ISNUMBER(Projection!Z77),Projection!Z77, )), ) -> 3650.9408 | M37: =IF(ISNUMBER(Projection!$H$7),IF(MONTH(Projection!$H$7)<>12,IF(ISNUMBER(Projection!AD77),Projection!AD77, ),IF(ISNUMBER(Projection!AB77),Projection!AB77, )), ) -> 3650.9408 | N37: =IF(ISNUMBER(Projection!$H$7),IF(MONTH(Projection!$H$7)<>12,IF(ISNUMBER(Projection!AF77),Projection!AF77, ),IF(ISNUMBER(Projection!AD77),Projection!AD77, )), ) -> 3650.9408 | O37: =IF(ISNUMBER(Projection!$H$7),IF(MONTH(Projection!$H$7)<>12,IF(ISNUMBER(Projection!AH77),Projection!AH77, ),IF(ISNUMBER(Projection!AF77),Projection!AF77, )), ) -> 3650.9408 | P37: 0 | Q37: 0 | R37: 0 | S37: 0 | T37: 0 | U37: 0 | V37: 0 | W37: 0 | X37: 0 | Y37: 0 | Z37: 0 | AA37: 0 | AB37: 0 | AC37: 0 | AD37: 0 | AE37: 0 | AF37: 0 | AG37: 0 | AH37: 0 | AI37: 0 | AJ37: 0 | AK37: 0 | AL37: 0 | AM37: 0 | AN37: 0 | AO37: 0 | AP37: 0
B38: =+#REF! -> #REF! | C38: =IF(ISNUMBER(Historical!E111),Historical!E111, ) -> 100 | D38: =IF(ISNUMBER(Historical!G111),Historical!G111, ) -> 110 | E38: =IF(ISNUMBER(Historical!I111),Historical!I111, ) -> 120 | F38: =IF(ISNUMBER(Projection!H7),IF(MONTH(Projection!H7)<>12,IF(ISNUMBER(Projection!L80),Projection!L80, ),IF(ISNUMBER(Historical!K111),Historical!K111, )), ) -> 260 | G38: =IF(ISNUMBER(Projection!H7),IF(MONTH(Projection!$H$7)<>12,IF(ISNUMBER(Projection!N80),Projection!N80, ),IF(ISNUMBER(Projection!L80),Projection!L80, )), ) -> 260 | H38: =IF(ISNUMBER(Projection!H7),IF(MONTH(Projection!$H$7)<>12,IF(ISNUMBER(Projection!P80),Projection!P80, ),IF(ISNUMBER(Projection!N80),Projection!N80, )), ) -> 260 | I38: =IF(ISNUMBER(Projection!H7),IF(MONTH(Projection!$H$7)<>12,IF(ISNUMBER(Projection!R80),Projection!R80, ),IF(ISNUMBER(Projection!P80),Projection!P80, )), ) -> 260 | J38: =IF(ISNUMBER(Projection!H7),IF(MONTH(Projection!$H$7)<>12,IF(ISNUMBER(Projection!T80),Projection!T80, ),IF(ISNUMBER(Projection!R80),Projection!R80, )), ) -> 260 | K38: =IF(ISNUMBER(Projection!H7),IF(MONTH(Projection!$H$7)<>12,IF(ISNUMBER(Projection!Z80),Projection!Z80, ),IF(ISNUMBER(Projection!T80),Projection!T80, )), ) -> 260 | L38: =IF(ISNUMBER(Projection!H7),IF(MONTH(Projection!$H$7)<>12,IF(ISNUMBER(Projection!AB80),Projection!AB80, ),IF(ISNUMBER(Projection!Z80),Projection!Z80, )), ) -> 260 | M38: =IF(ISNUMBER(Projection!$H$7),IF(MONTH(Projection!$H$7)<>12,IF(ISNUMBER(Projection!AD80),Projection!AD80, ),IF(ISNUMBER(Projection!AB80),Projection!AB80, )), ) -> 260 | N38: =IF(ISNUMBER(Projection!$H$7),IF(MONTH(Projection!$H$7)<>12,IF(ISNUMBER(Projection!AF80),Projection!AF80, ),IF(ISNUMBER(Projection!AD80),Projection!AD80, )), ) -> 260 | O38: =IF(ISNUMBER(Projection!$H$7),IF(MONTH(Projection!$H$7)<>12,IF(ISNUMBER(Projection!AH80),Projection!AH80, ),IF(ISNUMBER(Projection!AF80),Projection!AF80, )), ) -> 260
B39: =+#REF! -> #REF! | C39: =IF(ISNUMBER(Historical!E110),Historical!E110, )*Projection!$I$131 -> 2000 | D39: =IF(ISNUMBER(Historical!G110),Historical!G110, )*Projection!$I$131 -> 2100 | E39: =IF(ISNUMBER(Historical!I110),Historical!I110, )*Projection!$I$131 -> 2200 | F39: =IF(ISNUMBER(Projection!H7),IF(MONTH(Projection!H7)<>12,IF(ISNUMBER(Projection!L79),Projection!L79, ),IF(ISNUMBER(Historical!K110),Historical!K110, )), )*Projection!$I$131 -> 4602 | G39: =IF(ISNUMBER(Projection!$H$7),IF(MONTH(Projection!$H$7)<>12,IF(ISNUMBER(Projection!N139),Projection!N139, ),IF(ISNUMBER(Projection!L139),Projection!L139, )), ) -> 6902 | H39: =IF(ISNUMBER(Projection!$H$7),IF(MONTH(Projection!$H$7)<>12,IF(ISNUMBER(Projection!P139),Projection!P139, ),IF(ISNUMBER(Projection!N139),Projection!N139, )), ) -> 6902 | I39: =IF(ISNUMBER(Projection!$H$7),IF(MONTH(Projection!$H$7)<>12,IF(ISNUMBER(Projection!R139),Projection!R139, ),IF(ISNUMBER(Projection!P139),Projection!P139, )), ) -> 6902 | J39: =IF(ISNUMBER(Projection!$H$7),IF(MONTH(Projection!$H$7)<>12,IF(ISNUMBER(Projection!T139),Projection!T139, ),IF(ISNUMBER(Projection!R139),Projection!R139, )), ) -> 6902 | K39: =IF(ISNUMBER(Projection!$H$7),IF(MONTH(Projection!$H$7)<>12,IF(ISNUMBER(Projection!Z139),Projection!Z139, ),IF(ISNUMBER(Projection!T139),Projection!T139, )), ) -> 4602 | L39: =IF(ISNUMBER(Projection!$H$7),IF(MONTH(Projection!$H$7)<>12,IF(ISNUMBER(Projection!AB139),Projection!AB139, ),IF(ISNUMBER(Projection!Z139),Projection!Z139, )), ) -> 4602 | M39: =IF(ISNUMBER(Projection!$H$7),IF(MONTH(Projection!$H$7)<>12,IF(ISNUMBER(Projection!AD139),Projection!AD139, ),IF(ISNUMBER(Projection!AB139),Projection!AB139, )), ) -> 4602 | N39: =IF(ISNUMBER(Projection!$H$7),IF(MONTH(Projection!$H$7)<>12,IF(ISNUMBER(Projection!AF139),Projection!AF139, ),IF(ISNUMBER(Projection!AD139),Projection!AD139, )), ) -> 4602 | O39: =IF(ISNUMBER(Projection!$H$7),IF(MONTH(Projection!$H$7)<>12,IF(ISNUMBER(Projection!AH139),Projection!AH139, ),IF(ISNUMBER(Projection!AF139),Projection!AF139, )), ) -> 4602
B40: =+#REF! -> #REF!
B41: =+#REF! -> #REF!
B42: =+#REF! -> #REF!
B43: =+#REF! -> #REF!
B44: =+#REF! -> #REF!
B45: =+#REF! -> #REF!
B46: =+#REF! -> #REF!
B47: =+#REF! -> #REF!
B48: =+#REF! -> #REF!
B49: =+#REF! -> #REF!
B50: =+#REF! -> #REF!
B51: =+#REF! -> #REF!
B52: =+#REF! -> #REF! | C52: -2919 | D52: -61053 | E52: 151 | F52: -1689 | G52: -3548.0997 | H52: -3768.911 | I52: -3980.9845 | J52: -4176.9021 | K52: -4382.6156 | L52: 0 | M52: 0 | N52: 0 | O52: 0
B53: =+#REF! -> #REF! | C53: =IF(ISNUMBER(Historical!E115),Historical!E115, ) -> 10 | D53: =IF(ISNUMBER(Historical!G115),Historical!G115, ) -> -11 | E53: =IF(ISNUMBER(Historical!I115),Historical!I115, ) -> 12 | F53: =IF(ISNUMBER(Projection!H7),IF(MONTH(Projection!H7)<>12,IF(ISNUMBER(Projection!L84),Projection!L84, ),IF(ISNUMBER(Historical!K115),Historical!K115, )), ) -> -23 | G53: =IF(ISNUMBER(Projection!H7),IF(MONTH(Projection!$H$7)<>12,IF(ISNUMBER(Projection!N84),Projection!N84, ),IF(ISNUMBER(Projection!L84),Projection!L84, )), ) -> -786.5 | H53: =IF(ISNUMBER(Projection!H7),IF(MONTH(Projection!$H$7)<>12,IF(ISNUMBER(Projection!P84),Projection!P84, ),IF(ISNUMBER(Projection!N84),Projection!N84, )), ) -> -865.15 | I53: =IF(ISNUMBER(Projection!H7),IF(MONTH(Projection!$H$7)<>12,IF(ISNUMBER(Projection!R84),Projection!R84, ),IF(ISNUMBER(Projection!P84),Projection!P84, )), ) -> -951.665 | J53: =IF(ISNUMBER(Projection!H7),IF(MONTH(Projection!$H$7)<>12,IF(ISNUMBER(Projection!T84),Projection!T84, ),IF(ISNUMBER(Projection!R84),Projection!R84, )), ) -> -1046.8315 | K53: =IF(ISNUMBER(Projection!H7),IF(MONTH(Projection!$H$7)<>12,IF(ISNUMBER(Projection!Z84),Projection!Z84, ),IF(ISNUMBER(Projection!T84),Projection!T84, )), ) -> -889.09858 | L53: =IF(ISNUMBER(Projection!H7),IF(MONTH(Projection!$H$7)<>12,IF(ISNUMBER(Projection!AB84),Projection!AB84, ),IF(ISNUMBER(Projection!Z84),Projection!Z84, )), ) -> -889.09858 | M53: =IF(ISNUMBER(Projection!$H$7),IF(MONTH(Projection!$H$7)<>12,IF(ISNUMBER(Projection!AD84),Projection!AD84, ),IF(ISNUMBER(Projection!AB84),Projection!AB84, )), ) -> -889.09858 | N53: =IF(ISNUMBER(Projection!$H$7),IF(MONTH(Projection!$H$7)<>12,IF(ISNUMBER(Projection!AF84),Projection!AF84, ),IF(ISNUMBER(Projection!AD84),Projection!AD84, )), ) -> -889.09858 | O53: =IF(ISNUMBER(Projection!$H$7),IF(MONTH(Projection!$H$7)<>12,IF(ISNUMBER(Projection!AH84),Projection!AH84, ),IF(ISNUMBER(Projection!AF84),Projection!AF84, )), ) -> -889.09858 | Q53: 0 | R53: 0 | S53: 0 | T53: 0 | U53: 0 | V53: 0 | W53: 0 | X53: 0 | Y53: 0 | Z53: 0 | AA53: 0 | AB53: 0 | AC53: 0 | AD53: 0 | AE53: 0 | AF53: 0 | AG53: 0 | AH53: 0 | AI53: 0 | AJ53: 0 | AK53: 0 | AL53: 0 | AM53: 0 | AN53: 0 | AO53: 0 | AP53: 0
B54: =+#REF! -> #REF!
B55: =+#REF! -> #REF!
B56: =+#REF! -> #REF!
B57: =+#REF! -> #REF!
B58: =+#REF! -> #REF!
B59: =+#REF! -> #REF! | C59: =IF(ISNUMBER(Historical!E116),Historical!E116, ) -> 10 | D59: =IF(ISNUMBER(Historical!G116),Historical!G116, ) -> -11 | E59: =IF(ISNUMBER(Historical!I116),Historical!I116, ) -> 12 | F59: =IF(ISNUMBER(Projection!H7),IF(MONTH(Projection!H7)<>12,IF(ISNUMBER(Projection!L85),Projection!L85, ),IF(ISNUMBER(Historical!K116),Historical!K116, )), ) -> -13 | G59: =IF(ISNUMBER(Projection!H7),IF(MONTH(Projection!$H$7)<>12,IF(ISNUMBER(Projection!N85),Projection!N85, ),IF(ISNUMBER(Projection!L85),Projection!L85, )), ) -> 0 | H59: =IF(ISNUMBER(Projection!H7),IF(MONTH(Projection!$H$7)<>12,IF(ISNUMBER(Projection!P85),Projection!P85, ),IF(ISNUMBER(Projection!N85),Projection!N85, )), ) -> 0 | I59: =IF(ISNUMBER(Projection!H7),IF(MONTH(Projection!$H$7)<>12,IF(ISNUMBER(Projection!R85),Projection!R85, ),IF(ISNUMBER(Projection!P85),Projection!P85, )), ) -> 0 | J59: =IF(ISNUMBER(Projection!H7),IF(MONTH(Projection!$H$7)<>12,IF(ISNUMBER(Projection!T85),Projection!T85, ),IF(ISNUMBER(Projection!R85),Projection!R85, )), ) -> 0 | K59: =IF(ISNUMBER(Projection!H7),IF(MONTH(Projection!$H$7)<>12,IF(ISNUMBER(Projection!Z85),Projection!Z85, ),IF(ISNUMBER(Projection!T85),Projection!T85, )), ) -> 0 | L59: =IF(ISNUMBER(Projection!H7),IF(MONTH(Projection!$H$7)<>12,IF(ISNUMBER(Projection!AB85),Projection!AB85, ),IF(ISNUMBER(Projection!Z85),Projection!Z85, )), ) -> 0 | M59: =IF(ISNUMBER(Projection!$H$7),IF(MONTH(Projection!$H$7)<>12,IF(ISNUMBER(Projection!AD85),Projection!AD85, ),IF(ISNUMBER(Projection!AB85),Projection!AB85, )), ) -> 0 | N59: =IF(ISNUMBER(Projection!$H$7),IF(MONTH(Projection!$H$7)<>12,IF(ISNUMBER(Projection!AF85),Projection!AF85, ),IF(ISNUMBER(Projection!AD85),Projection!AD85, )), ) -> 0 | O59: =IF(ISNUMBER(Projection!$H$7),IF(MONTH(Projection!$H$7)<>12,IF(ISNUMBER(Projection!AH85),Projection!AH85, ),IF(ISNUMBER(Projection!AF85),Projection!AF85, )), ) -> 0
B60: =+#REF! -> #REF! | C60: =IF(ISNUMBER(Historical!E114),Historical!E114, ) -> 10 | D60: =IF(ISNUMBER(Historical!G114),Historical!G114, ) -> -11 | E60: =IF(ISNUMBER(Historical!I114),Historical!I114, ) -> 12 | F60: =IF(ISNUMBER(Projection!H7),IF(MONTH(Projection!H7)<>12,IF(ISNUMBER(Projection!L83),Projection!L83, ),IF(ISNUMBER(Historical!K114),Historical!K114, )), ) -> -13 | G60: =IF(ISNUMBER(Projection!H7),IF(MONTH(Projection!$H$7)<>12,IF(ISNUMBER(Projection!N83),Projection!N83, ),IF(ISNUMBER(Projection!L83),Projection!L83, )), ) -> 0 | H60: =IF(ISNUMBER(Projection!H7),IF(MONTH(Projection!$H$7)<>12,IF(ISNUMBER(Projection!P83),Projection!P83, ),IF(ISNUMBER(Projection!N83),Projection!N83, )), ) -> 0 | I60: =IF(ISNUMBER(Projection!H7),IF(MONTH(Projection!$H$7)<>12,IF(ISNUMBER(Projection!R83),Projection!R83, ),IF(ISNUMBER(Projection!P83),Projection!P83, )), ) -> 0 | J60: =IF(ISNUMBER(Projection!H7),IF(MONTH(Projection!$H$7)<>12,IF(ISNUMBER(Projection!T83),Projection!T83, ),IF(ISNUMBER(Projection!R83),Projection!R83, )), ) -> 0 | K60: =IF(ISNUMBER(Projection!H7),IF(MONTH(Projection!$H$7)<>12,IF(ISNUMBER(Projection!Z83),Projection!Z83, ),IF(ISNUMBER(Projection!T83),Projection!T83, )), ) -> 0 | L60: =IF(ISNUMBER(Projection!H7),IF(MONTH(Projection!$H$7)<>12,IF(ISNUMBER(Projection!AB83),Projection!AB83, ),IF(ISNUMBER(Projection!Z83),Projection!Z83, )), ) -> 0 | M60: =IF(ISNUMBER(Projection!$H$7),IF(MONTH(Projection!$H$7)<>12,IF(ISNUMBER(Projection!AD83),Projection!AD83, ),IF(ISNUMBER(Projection!AB83),Projection!AB83, )), ) -> 0 | N60: =IF(ISNUMBER(Projection!$H$7),IF(MONTH(Projection!$H$7)<>12,IF(ISNUMBER(Projection!AF83),Projection!AF83, ),IF(ISNUMBER(Projection!AD83),Projection!AD83, )), ) -> 0 | O60: =IF(ISNUMBER(Projection!$H$7),IF(MONTH(Projection!$H$7)<>12,IF(ISNUMBER(Projection!AH83),Projection!AH83, ),IF(ISNUMBER(Projection!AF83),Projection!AF83, )), ) -> 0
A61: 0 | B61: =+#REF! -> #REF!
B62: =+#REF! -> #REF!
B63: =+#REF! -> #REF!
B64: =+#REF! -> #REF!
B65: =+#REF! -> #REF!
B66: =+#REF! -> #REF!
B67: =+#REF! -> #REF!
B68: =+#REF! -> #REF! | C68: =C35-C36-C52 -> -47008.889 | D68: =D35-D36-D52 -> 65139.081 | E68: =E35-E36-E52 -> 8800.2926 | F68: =F35-F36-F52 -> 35241.913 | G68: =G35-G36-G52 -> 69694.175 | H68: =H35-H36-H52 -> 73516.627 | I68: =I35-I36-I52 -> 76908.037 | J68: =J35-J36-J52 -> 79645.703 | ... AP68: =AP35-AP36-AP52 -> 0
B69: =+#REF! -> #REF! | C69: 5247.2668 | D69: 10.881856 | E69: 7563.7297 | F69: 10185.847 | G69: 8218.2618 | H69: 6565.4022 | I69: 4482.3832 | J69: 2396.0849 | K69: 1110.7136 | L69: -18.838723 | M69: 0.00031945861 | N69: 0.00031945861 | O69: 0.00031945861
B70: =+#REF! -> #REF! | C70: =IF(ISNUMBER(Historical!E118),Historical!E118, ) -> 1200 | D70: =IF(ISNUMBER(Historical!G118),Historical!G118, ) -> 1300 | E70: =IF(ISNUMBER(Historical!I118),Historical!I118, ) -> 1500 | F70: =IF(ISNUMBER(Projection!H7),IF(MONTH(Projection!H7)<>12,IF(ISNUMBER(Projection!L87),Projection!L87, ),IF(ISNUMBER(Historical!K118),Historical!K118, )), ) -> 6674.359 | G70: =IF(ISNUMBER(Projection!H7),IF(MONTH(Projection!$H$7)<>12,IF(ISNUMBER(Projection!N87),Projection!N87, ),IF(ISNUMBER(Projection!L87),Projection!L87, )), ) -> 10795.893 | H70: =IF(ISNUMBER(Projection!H7),IF(MONTH(Projection!$H$7)<>12,IF(ISNUMBER(Projection!P87),Projection!P87, ),IF(ISNUMBER(Projection!N87),Projection!N87, )), ) -> 8815.9983 | I70: =IF(ISNUMBER(Projection!H7),IF(MONTH(Projection!$H$7)<>12,IF(ISNUMBER(Projection!R87),Projection!R87, ),IF(ISNUMBER(Projection!P87),Projection!P87, )), ) -> 6863.7429 | J70: =IF(ISNUMBER(Projection!H7),IF(MONTH(Projection!$H$7)<>12,IF(ISNUMBER(Projection!T87),Projection!T87, ),IF(ISNUMBER(Projection!R87),Projection!R87, )), ) -> 4561.5337 | K70: =IF(ISNUMBER(Projection!H7),IF(MONTH(Projection!$H$7)<>12,IF(ISNUMBER(Projection!Z87),Projection!Z87, ),IF(ISNUMBER(Projection!T87),Projection!T87, )), ) -> 4338.44 | L70: =IF(ISNUMBER(Projection!H7),IF(MONTH(Projection!$H$7)<>12,IF(ISNUMBER(Projection!AB87),Projection!AB87, ),IF(ISNUMBER(Projection!Z87),Projection!Z87, )), ) -> 4338.44 | M70: =IF(ISNUMBER(Projection!$H$7),IF(MONTH(Projection!$H$7)<>12,IF(ISNUMBER(Projection!AD87),Projection!AD87, ),IF(ISNUMBER(Projection!AB87),Projection!AB87, )), ) -> 4338.44 | N70: =IF(ISNUMBER(Projection!$H$7),IF(MONTH(Projection!$H$7)<>12,IF(ISNUMBER(Projection!AF87),Projection!AF87, ),IF(ISNUMBER(Projection!AD87),Projection!AD87, )), ) -> 4338.44 | O70: =IF(ISNUMBER(Projection!$H$7),IF(MONTH(Projection!$H$7)<>12,IF(ISNUMBER(Projection!AH87),Projection!AH87, ),IF(ISNUMBER(Projection!AF87),Projection!AF87, )), ) -> 4338.44 | P70: 0 | Q70: 0 | R70: 0 | S70: 0 | T70: 0 | U70: 0 | V70: 0 | W70: 0 | X70: 0 | Y70: 0 | Z70: 0 | AA70: 0 | AB70: 0 | AC70: 0 | AD70: 0 | AE70: 0 | AF70: 0 | AG70: 0 | AH70: 0 | AI70: 0 | AJ70: 0 | AK70: 0 | AL70: 0 | AM70: 0 | AN70: 0 | AO70: 0 | AP70: 0
B71: =+#REF! -> #REF!
A72: 0 | B72: =+#REF! -> #REF!
B73: =+#REF! -> #REF!
B74: =+#REF! -> #REF!
B75: =+#REF! -> #REF!
B76: =+#REF! -> #REF!
A77: 0 | B77: =+#REF! -> #REF!
B78: =+#REF! -> #REF!
A79: 0 | B79: =+#REF! -> #REF!
B80: =+#REF! -> #REF!
B81: =+#REF! -> #REF!
B82: =+#REF! -> #REF!
B83: =+#REF! -> #REF!
A84: 0 | B84: =+#REF! -> #REF!
B85: =+#REF! -> #REF! | C85: =C68-C69 -> -52256.156 | D85: =D68-D69 -> 65128.2 | E85: =E68-E69 -> 1236.5629 | F85: =F68-F69 -> 25056.066 | G85: =G68-G69 -> 61475.913 | H85: =H68-H69 -> 66951.224 | I85: =I68-I69 -> 72425.654 | J85: =J68-J69 -> 77249.618 | ... AP85: =AP68-AP69 -> 0
B86: =+#REF! -> #REF! | C86: -819.7865 | D86: 4769.0629 | E86: 350.396 | F86: 0 | G86: 15368.978 | H86: 16737.806 | I86: 18106.413 | J86: 19312.405 | K86: 20346.272 | L86: 263999.44 | M86: 263994.73 | N86: 263994.73 | O86: 263994.73
B87: =+#REF! -> #REF! | C87: =IF(ISNUMBER(Historical!E120),Historical!E120, ) -> 3500 | D87: =IF(ISNUMBER(Historical!G120),Historical!G120, ) -> 6000 | E87: =IF(ISNUMBER(Historical!I120),Historical!I120, ) -> 9000 | F87: =IF(ISNUMBER(Projection!H7),IF(MONTH(Projection!H7)<>12,IF(ISNUMBER(Projection!L89),Projection!L89, ),IF(ISNUMBER(Historical!K120),Historical!K120, )), ) -> 9000 | G87: =IF(ISNUMBER(Projection!H7),IF(MONTH(Projection!$H$7)<>12,IF(ISNUMBER(Projection!N89),Projection!N89, ),IF(ISNUMBER(Projection!L89),Projection!L89, )), ) -> 6652.6624 | H87: =IF(ISNUMBER(Projection!H7),IF(MONTH(Projection!$H$7)<>12,IF(ISNUMBER(Projection!P89),Projection!P89, ),IF(ISNUMBER(Projection!N89),Projection!N89, )), ) -> 8639.4181 | I87: =IF(ISNUMBER(Projection!H7),IF(MONTH(Projection!$H$7)<>12,IF(ISNUMBER(Projection!R89),Projection!R89, ),IF(ISNUMBER(Projection!P89),Projection!P89, )), ) -> 10745.879 | J87: =IF(ISNUMBER(Projection!H7),IF(MONTH(Projection!$H$7)<>12,IF(ISNUMBER(Projection!T89),Projection!T89, ),IF(ISNUMBER(Projection!R89),Projection!R89, )), ) -> 13117.141 | K87: =IF(ISNUMBER(Projection!H7),IF(MONTH(Projection!$H$7)<>12,IF(ISNUMBER(Projection!Z89),Projection!Z89, ),IF(ISNUMBER(Projection!T89),Projection!T89, )), ) -> 2613.4187 | L87: =IF(ISNUMBER(Projection!H7),IF(MONTH(Projection!$H$7)<>12,IF(ISNUMBER(Projection!AB89),Projection!AB89, ),IF(ISNUMBER(Projection!Z89),Projection!Z89, )), ) -> 2613.4187 | M87: =IF(ISNUMBER(Projection!$H$7),IF(MONTH(Projection!$H$7)<>12,IF(ISNUMBER(Projection!AD89),Projection!AD89, ),IF(ISNUMBER(Projection!AB89),Projection!AB89, )), ) -> 2613.4187 | N87: =IF(ISNUMBER(Projection!$H$7),IF(MONTH(Projection!$H$7)<>12,IF(ISNUMBER(Projection!AF89),Projection!AF89, ),IF(ISNUMBER(Projection!AD89),Projection!AD89, )), ) -> 2613.4187 | O87: =IF(ISNUMBER(Projection!$H$7),IF(MONTH(Projection!$H$7)<>12,IF(ISNUMBER(Projection!AH89),Projection!AH89, ),IF(ISNUMBER(Projection!AF89),Projection!AF89, )), ) -> 2613.4187 | P87: 0 | Q87: 0 | R87: 0 | S87: 0 | T87: 0 | U87: 0 | V87: 0 | W87: 0 | X87: 0 | Y87: 0 | Z87: 0 | AA87: 0 | AB87: 0 | AC87: 0 | AD87: 0 | AE87: 0 | AF87: 0 | AG87: 0 | AH87: 0 | AI87: 0 | AJ87: 0 | AK87: 0 | AL87: 0 | AM87: 0 | AN87: 0 | AO87: 0 | AP87: 0
B88: =+#REF! -> #REF!
B89: =+#REF! -> #REF!
B90: =+#REF! -> #REF!
B91: =+#REF! -> #REF!
B92: =+#REF! -> #REF!
B93: =+#REF! -> #REF!
B94: =+#REF! -> #REF!
B95: =+#REF! -> #REF!
B96: =+#REF! -> #REF!
B97: =+#REF! -> #REF!
B98: =+#REF! -> #REF!
B99: =+#REF! -> #REF!
... B101: =+#REF! -> #REF!
B102: =+#REF! -> #REF! | C102: 0 | D102: 0 | E102: 0 | F102: 0 | G102: 0 | H102: 0 | I102: 0 | J102: 0 | K102: 0 | L102: 0 | M102: 0
...

Sheet Historical
B2: Debtor / Group Name: | E2: Date : | H2: Proposed Unit :
B3: Generic Niaga / Generic Group | E3: 45598 | H3: Divisi Corporate Banking 2
B5: Status of Financial Statement
B6: Period of Financial Statement | E6: Status | G6: Public Accountant Firm | I6: Classification | K6: Opini | O6: --- | P6: --- | Q6: --- | BG6: Status-Opini | BI6: Kantor akuntan
B7: =+E13 -> 44561 | E7: Audited | G7: KAP | K7: Unqualified | O7: Audited | P7: A | Q7: Wajar tanpa pengecualian | BF7: =B7 -> 44561 | BG7: Audited - Unqualified | BI7: KAP
B8: =+G13 -> 44926 | E8: Audited | G8: KAP | K8: Unqualified | O8: Home Statement | P8: B | Q8: Wajar dengan pengecualian | BF8: =B8 -> 44926 | BG8: Audited - Unqualified | BI8: KAP
B9: =+I13 -> 45291 | E9: Audited | G9: KAP | K9: Unqualified | P9: C | Q9: Tidak wajar | BF9: =B9 -> 45291 | BG9: Audited - Unqualified | BI9: KAP
B10: =+K13 -> 45473 | E10: Home Statement | G10: N / A | K10: =IF(NOT(ISERROR(FIND("-",BG10))),RIGHT(BG10,LEN(BG10)-FIND("-",BG10)),"") | P10: D | Q10: Tidak memberikan pendapat | BF10: =B10 -> 45473 | BG10: Home Statement | BI10: N/A
B11: BALANCE SHEET STATEMENT | P11: Non Rekanan | BG11: Neraca
B12: Financial Statement Unit | E12: HISTORICAL | BG12: Satuan laporan keuangan | BJ12: HISTORIS
B13: =BD13&" "&BE13 -> IDR Million | E13: 44561 | F13: =+MONTH(E13)*30 -> 360 | G13: 44926 | H13: =+MONTH(G13)*30 -> 360 | I13: 45291 | J13: =+MONTH(I13)*30 -> 360 | K13: 45473 | L13: =+MONTH(K13)*30 -> 180 | BD13: IDR | BE13: Million | BG13: Rp. Juta | BJ13: =IF(ISNUMBER(VALUE(LEFT(BJ14,1))),DATE(RIGHT(TEXT(BJ14,"a"),4),LEFT(RIGHT(TEXT(BJ14,"a"),7),2),IF(LEN(TEXT(BJ14,"a"))=10,LEFT(TEXT(BJ14,"a"),2),LEFT(TEXT(BJ14,"a"),1))), ) -> #VALUE! | BK13: =+MONTH(BJ13)*30 -> #VALUE! | BL13: =IF(ISNUMBER(VALUE(LEFT(BL14,1))),DATE(RIGHT(TEXT(BL14,"a"),4),LEFT(RIGHT(TEXT(BL14,"a"),7),2),IF(LEN(TEXT(BL14,"a"))=10,LEFT(TEXT(BL14,"a"),2),LEFT(TEXT(BL14,"a"),1))), ) -> #VALUE! | BM13: =+MONTH(BL13)*30 -> #VALUE! | BN13: =IF(ISNUMBER(VALUE(LEFT(BN14,1))),DATE(RIGHT(TEXT(BN14,"a"),4),LEFT(RIGHT(TEXT(BN14,"a"),7),2),IF(LEN(TEXT(BN14,"a"))=10,LEFT(TEXT(BN14,"a"),2),LEFT(TEXT(BN14,"a"),1))), ) -> #VALUE! | BO13: =+MONTH(BN13)*30 -> #VALUE! | BP13: =IF(ISNUMBER(VALUE(LEFT(BP14,1))),DATE(RIGHT(TEXT(BP14,"a"),4),LEFT(RIGHT(TEXT(BP14,"a"),7),2),IF(LEN(TEXT(BP14,"a"))=10,LEFT(TEXT(BP14,"a"),2),LEFT(TEXT(BP14,"a"),1))), ) -> #VALUE! | BQ13: =+MONTH(BP13)*30 -> #VALUE!
E14: 42004 | G14: 42369 | I14: 42735 | K14: 45473 | BJ14: 42004 | BL14: 42369 | BN14: 42735 | BP14: 43100
E15: Amount | F15: % | G15: Amount | H15: % | I15: Amount | J15: % | K15: Amount | L15: % | BJ15: JUMLAH | BK15: % | BL15: JUMLAH | BM15: % | BN15: JUMLAH | BO15: % | BP15: JUMLAH | BQ15: %
B16: 1 | C16: Cash and Cash Equivalents | E16: 100 | F16: =IF(E$73=0,0,E16/E$73*100) -> 0.081168831 | G16: 101 | H16: =IF(G$73=0,0,G16/G$73*100) -> 0.081904067 | I16: 102 | J16: =IF(I$73=0,0,I16/I$73*100) -> 0.082637932 | K16: 103 | L16: =IF(K$73=0,0,K16/K$73*100) -> 0.083370432 | U16: 0 | W16: 0 | Y16: 0 | AA16: 0 | BG16: 1 | BH16: Kas dan Setara | BJ16: 1195.4833 | BK16: =IF(BJ$299=0,0,BJ16/BJ$299*100) -> 84.09149 | BL16: 506.07126 | BM16: =IF(BL$299=0,0,BL16/BL$299*100) -> 2.2592023 | BN16: 2370.9002 | BO16: =IF(BN$299=0,0,BN16/BN$299*100) -> 8.1735057 | BP16: 149989.07 | BQ16: =IF(BP$299=0,0,BP16/BP$299*100) -> 38.905636
B17: =B16+1 -> 2 | C17: Restricted Cash | E17: 200 | F17: =IF(E$73=0,0,E17/E$73*100) -> 0.16233766 | G17: 201 | H17: =IF(G$73=0,0,G17/G$73*100) -> 0.1629972 | I17: 202 | J17: =IF(I$73=0,0,I17/I$73*100) -> 0.16365551 | K17: 203 | L17: =IF(K$73=0,0,K17/K$73*100) -> 0.1643126
B18: =+B17+1 -> 3 | C18: Short Term Investments | E18: 300 | F18: =IF(E$73=0,0,E18/E$73*100) -> 0.24350649 | G18: 301 | H18: =IF(G$73=0,0,G18/G$73*100) -> 0.24409034 | I18: 302 | J18: =IF(I$73=0,0,I18/I$73*100) -> 0.24467309 | K18: 303 | L18: =IF(K$73=0,0,K18/K$73*100) -> 0.24525477 | BG18: 2 | BH18: Deposit Likuid Jangka Pendek | BJ18: 0 | BK18: =IF(BJ$299=0,0,BJ18/BJ$299*100) -> 0 | BL18: 0 | BM18: =IF(BL$299=0,0,BL18/BL$299*100) -> 0 | BN18: 0 | BO18: =IF(BN$299=0,0,BN18/BN$299*100) -> 0 | BP18: 0 | BQ18: =IF(BP$299=0,0,BP18/BP$299*100) -> 0
B19: =+B18+1 -> 4 | C19: Account Receivables | E19: 400 | F19: =IF(E$73=0,0,E19/E$73*100) -> 0.32467532 | G19: 401 | H19: =IF(G$73=0,0,G19/G$73*100) -> 0.32518347 | I19: 402 | J19: =IF(I$73=0,0,I19/I$73*100) -> 0.32569067 | K19: 403 | L19: =IF(K$73=0,0,K19/K$73*100) -> 0.32619693 | BU19: 3 | BV19: Surat Berharga | BX19: 0 | BY19: =IF(BJ$299=0,0,BX19/BJ$299*100) -> 0 | BZ19: 0 | CA19: =IF(BL$299=0,0,BZ19/BL$299*100) -> 0 | CB19: 0 | CC19: =IF(BN$299=0,0,CB19/BN$299*100) -> 0 | CD19: 0 | CE19: =IF(BP$299=0,0,CD19/BP$299*100) -> 0
B20: =+B19+1 -> 5 | C20: Inventories | E20: 500 | F20: =IF(E$73=0,0,E20/E$73*100) -> 0.40584416 | G20: 501 | H20: =IF(G$73=0,0,G20/G$73*100) -> 0.40627661 | I20: 502 | J20: =IF(I$73=0,0,I20/I$73*100) -> 0.40670826 | K20: 503 | L20: =IF(K$73=0,0,K20/K$73*100) -> 0.4071391 | BG20: 4 | BJ20: 0 | BK20: =IF(BJ$299=0,0,BJ20/BJ$299*100) -> 0 | BL20: 0 | BM20: =IF(BL$299=0,0,BL20/BL$299*100) -> 0 | BN20: 0 | BO20: =IF(BN$299=0,0,BN20/BN$299*100) -> 0 | BP20: 0 | BQ20: =IF(BP$299=0,0,BP20/BP$299*100) -> 0
B21: =+B20+1 -> 6 | C21: Prepaid Taxes | E21: 600 | F21: =IF(E$73=0,0,E21/E$73*100) -> 0.48701299 | G21: 601 | H21: =IF(G$73=0,0,G21/G$73*100) -> 0.48736974 | I21: 602 | J21: =IF(I$73=0,0,I21/I$73*100) -> 0.48772584 | K21: 603 | L21: =IF(K$73=0,0,K21/K$73*100) -> 0.48808127 | BG21: 5 | BJ21: 0 | BK21: =IF(BJ$299=0,0,BJ21/BJ$299*100) -> 0 | BL21: 0 | BM21: =IF(BL$299=0,0,BL21/BL$299*100) -> 0 | BN21: 0 | BO21: =IF(BN$299=0,0,BN21/BN$299*100) -> 0 | BP21: 0 | BQ21: =IF(BP$299=0,0,BP21/BP$299*100) -> 0
B22: =+B21+1 -> 7 | C22: Prepaid Expenses | E22: 700 | F22: =IF(E$73=0,0,E22/E$73*100) -> 0.56818182 | G22: 701 | H22: =IF(G$73=0,0,G22/G$73*100) -> 0.56846288 | I22: 702 | J22: =IF(I$73=0,0,I22/I$73*100) -> 0.56874342 | K22: 703 | L22: =IF(K$73=0,0,K22/K$73*100) -> 0.56902343 | BG22: 6 | BJ22: 0 | BK22: =IF(BJ$299=0,0,BJ22/BJ$299*100) -> 0 | BL22: 0 | BM22: =IF(BL$299=0,0,BL22/BL$299*100) -> 0 | BN22: 0 | BO22: =IF(BN$299=0,0,BN22/BN$299*100) -> 0 | BP22: 0 | BQ22: =IF(BP$299=0,0,BP22/BP$299*100) -> 0
B23: =+B22+1 -> 8 | C23: Advance Payments | E23: 800 | F23: =IF(E$73=0,0,E23/E$73*100) -> 0.64935065 | G23: 801 | H23: =IF(G$73=0,0,G23/G$73*100) -> 0.64955602 | I23: 802 | J23: =IF(I$73=0,0,I23/I$73*100) -> 0.649761 | K23: 803 | L23: =IF(K$73=0,0,K23/K$73*100) -> 0.6499656 | BG23: 7 | BJ23: 0 | BK23: =IF(BJ$299=0,0,BJ23/BJ$299*100) -> 0 | BL23: 0 | BM23: =IF(BL$299=0,0,BL23/BL$299*100) -> 0 | BN23: 0 | BO23: =IF(BN$299=0,0,BN23/BN$299*100) -> 0 | BP23: 0 | BQ23: =IF(BP$299=0,0,BP23/BP$299*100) -> 0
B24: =+B23+1 -> 9 | C24: Other Current Assets | E24: 900 | F24: =IF(E$73=0,0,E24/E$73*100) -> 0.73051948 | G24: 901 | H24: =IF(G$73=0,0,G24/G$73*100) -> 0.73064915 | I24: 902 | J24: =IF(I$73=0,0,I24/I$73*100) -> 0.73077858 | K24: 903 | L24: =IF(K$73=0,0,K24/K$73*100) -> 0.73090777 | BG24: 8 | BJ24: 0 | BK24: =IF(BJ$299=0,0,BJ24/BJ$299*100) -> 0 | BL24: 0 | BM24: =IF(BL$299=0,0,BL24/BL$299*100) -> 0 | BN24: 0 | BO24: =IF(BN$299=0,0,BN24/BN$299*100) -> 0 | BP24: 0 | BQ24: =IF(BP$299=0,0,BP24/BP$299*100) -> 0
B25: =+B24+1 -> 10 | C25: Total Current Assets | E25: =SUM(E16:E24) -> 4500 | F25: =IF(E$73=0,0,E25/E$73*100) -> 3.6525974 | G25: =SUM(G16:G24) -> 4509 | H25: =IF(G$73=0,0,G25/G$73*100) -> 3.6564895 | I25: =SUM(I16:I24) -> 4518 | J25: =IF(I$73=0,0,I25/I$73*100) -> 3.6603743 | K25: =SUM(K16:K24) -> 4527 | L25: =IF(K$73=0,0,K25/K$73*100) -> 3.6642519 | BG25: 9 | BJ25: 0 | BK25: =IF(BJ$299=0,0,BJ25/BJ$299*100) -> 0 | BL25: 0 | BM25: =IF(BL$299=0,0,BL25/BL$299*100) -> 0 | BN25: 0 | BO25: =IF(BN$299=0,0,BN25/BN$299*100) -> 0 | BP25: 0 | BQ25: =IF(BP$299=0,0,BP25/BP$299*100) -> 0
B26: =+B25+1 -> 11 | C26: Fixed Assets | E26: 110000 | F26: =IF(E$73=0,0,E26/E$73*100) -> 89.285714 | G26: 110100 | H26: =IF(G$73=0,0,G26/G$73*100) -> 89.283542 | I26: 110200 | J26: =IF(I$73=0,0,I26/I$73*100) -> 89.281374 | K26: 110300 | L26: =IF(K$73=0,0,K26/K$73*100) -> 89.27921 | BG26: 10 | BJ26: 0 | BK26: =IF(BJ$299=0,0,BJ26/BJ$299*100) -> 0 | BL26: 0 | BM26: =IF(BL$299=0,0,BL26/BL$299*100) -> 0 | BN26: 0 | BO26: =IF(BN$299=0,0,BN26/BN$299*100) -> 0 | BP26: 0 | BQ26: =IF(BP$299=0,0,BP26/BP$299*100) -> 0
B27: =+B26+1 -> 12 | C27: Investment in Associates | E27: 1200 | F27: =IF(E$73=0,0,E27/E$73*100) -> 0.97402597 | G27: 1201 | H27: =IF(G$73=0,0,G27/G$73*100) -> 0.97392856 | I27: 1202 | J27: =IF(I$73=0,0,I27/I$73*100) -> 0.97383132 | K27: 1203 | L27: =IF(K$73=0,0,K27/K$73*100) -> 0.97373427 | BG27: 11 | BJ27: 0 | BK27: =IF(BJ$299=0,0,BJ27/BJ$299*100) -> 0 | BL27: 0 | BM27: =IF(BL$299=0,0,BL27/BL$299*100) -> 0 | BN27: 0 | BO27: =IF(BN$299=0,0,BN27/BN$299*100) -> 0 | BP27: 0 | BQ27: =IF(BP$299=0,0,BP27/BP$299*100) -> 0
B28: =B27+1 -> 13 | C28: Investment in Joint Venture | E28: 1300 | F28: =IF(E$73=0,0,E28/E$73*100) -> 1.0551948 | G28: 1301 | H28: =IF(G$73=0,0,G28/G$73*100) -> 1.0550217 | I28: 1302 | J28: =IF(I$73=0,0,I28/I$73*100) -> 1.0548489 | K28: 1303 | L28: =IF(K$73=0,0,K28/K$73*100) -> 1.0546764
B29: =B28+1 -> 14 | C29: Intangible Assets | E29: 1400 | F29: =IF(E$73=0,0,E29/E$73*100) -> 1.1363636 | G29: 1401 | H29: =IF(G$73=0,0,G29/G$73*100) -> 1.1361148 | I29: 1402 | J29: =IF(I$73=0,0,I29/I$73*100) -> 1.1358665 | K29: 1403 | L29: =IF(K$73=0,0,K29/K$73*100) -> 1.1356186
B30: 15 | C30: Deferred Taxes | E30: 1500 | F30: =IF(E$73=0,0,E30/E$73*100) -> 1.2175325 | G30: 1501 | H30: =IF(G$73=0,0,G30/G$73*100) -> 1.217208 | I30: 1502 | J30: =IF(I$73=0,0,I30/I$73*100) -> 1.2168841 | K30: 1503 | L30: =IF(K$73=0,0,K30/K$73*100) -> 1.2165608 | BG30: 12 | BJ30: 0 | BK30: =IF(BJ$299=0,0,BJ30/BJ$299*100) -> 0 | BL30: 0 | BM30: =IF(BL$299=0,0,BL30/BL$299*100) -> 0 | BN30: 0 | BO30: =IF(BN$299=0,0,BN30/BN$299*100) -> 0 | BP30: 0 | BQ30: =IF(BP$299=0,0,BP30/BP$299*100) -> 0
B31: 16 | C31: Other Non-Current Assets | E31: 1600 | F31: =IF(E$73=0,0,E31/E$73*100) -> 1.2987013 | G31: 1601 | H31: =IF(G$73=0,0,G31/G$73*100) -> 1.2983011 | I31: 1602 | J31: =IF(I$73=0,0,I31/I$73*100) -> 1.2979016 | K31: 1603 | L31: =IF(K$73=0,0,K31/K$73*100) -> 1.2975029 | BG31: 13 | BJ31: 0 | BK31: =IF(BJ$299=0,0,BJ31/BJ$299*100) -> 0 | BL31: 0 | BM31: =IF(BL$299=0,0,BL31/BL$299*100) -> 0 | BN31: 0 | BO31: =IF(BN$299=0,0,BN31/BN$299*100) -> 0 | BP31: 0 | BQ31: =IF(BP$299=0,0,BP31/BP$299*100) -> 0
B32: 17 | C32: Investments | E32: 1700 | F32: =IF(E$73=0,0,E32/E$73*100) -> 1.3798701 | G32: 1701 | H32: =IF(G$73=0,0,G32/G$73*100) -> 1.3793942 | I32: 1702 | J32: =IF(I$73=0,0,I32/I$73*100) -> 1.3789192 | K32: 1703 | L32: =IF(K$73=0,0,K32/K$73*100) -> 1.3784451 | BG32: 14 | BJ32: 0 | BK32: =IF(BJ$299=0,0,BJ32/BJ$299*100) -> 0 | BL32: 0 | BM32: =IF(BL$299=0,0,BL32/BL$299*100) -> 0 | BN32: 0 | BO32: =IF(BN$299=0,0,BN32/BN$299*100) -> 0 | BP32: 0 | BQ32: =IF(BP$299=0,0,BP32/BP$299*100) -> 0
B33: =+B32+1 -> 18 | C33: Total Non-Current Assets | E33: =SUM(E26:E32) -> 118700 | F33: =IF(E$73=0,0,E33/E$73*100) -> 96.347403 | G33: =SUM(G26:G32) -> 118806 | H33: =IF(G$73=0,0,G33/G$73*100) -> 96.343511 | I33: =SUM(I26:I32) -> 118912 | J33: =IF(I$73=0,0,I33/I$73*100) -> 96.339626 | K33: =SUM(K26:K32) -> 119018 | L33: =IF(K$73=0,0,K33/K$73*100) -> 96.335748 | BG33: 15 | BJ33: 0 | BK33: =IF(BJ$299=0,0,BJ33/BJ$299*100) -> 0 | BL33: 0 | BM33: =IF(BL$299=0,0,BL33/BL$299*100) -> 0 | BN33: 0 | BO33: =IF(BN$299=0,0,BN33/BN$299*100) -> 0 | BP33: 0 | BQ33: =IF(BP$299=0,0,BP33/BP$299*100) -> 0
B34: =+B33+1 -> 19 | C34: TOTAL ASSETS | E34: =E25+E33 -> 123200 | F34: =IF(E$73=0,0,E34/E$73*100) -> 100 | G34: =G25+G33 -> 123315 | H34: =IF(G$73=0,0,G34/G$73*100) -> 100 | I34: =I25+I33 -> 123430 | J34: =IF(I$73=0,0,I34/I$73*100) -> 100 | K34: =K25+K33 -> 123545 | L34: =IF(K$73=0,0,K34/K$73*100) -> 100 | U34: 157881.1 | W34: 303530.54 | Y34: 310346.08 | AA34: 597520.23
B35: =+B34+1 -> 20 | C35: Short-Term Bank Loan - BNI | E35: 2000 | F35: =IF(E$73=0,0,E35/E$73*100) -> 1.6233766 | G35: 2001 | H35: =IF(G$73=0,0,G35/G$73*100) -> 1.6226736 | I35: 2002 | J35: =IF(I$73=0,0,I35/I$73*100) -> 1.621972 | K35: 2003 | L35: =IF(K$73=0,0,K35/K$73*100) -> 1.6212716 | BU35: 16 | BV35: Piutang Usaha | BX35: 682.12144 | BY35: =IF(L$253=0,0,BX35/L$253*100) -> 0 | BZ35: 5054.491 | CA35: =IF(N$299=0,0,BZ35/N$299*100) -> 0 | CB35: 6414.4736 | CC35: =IF(P$299=0,0,CB35/P$299*100) -> 0 | CD35: 136969.56 | CE35: =IF(R$299=0,0,CD35/R$299*100) -> 0
B36: =+B35+1 -> 21 | C36: Short-Term Bank Loan - Other Banks | E36: 2100 | F36: =IF(E$73=0,0,E36/E$73*100) -> 1.7045455 | G36: 2101 | H36: =IF(G$73=0,0,G36/G$73*100) -> 1.7037668 | I36: 2102 | J36: =IF(I$73=0,0,I36/I$73*100) -> 1.7029895 | K36: 2103 | L36: =IF(K$73=0,0,K36/K$73*100) -> 1.7022138 | BU36: 17 | BV36: Piutang Usaha - Pihak Berelasi | BX36: 0 | BY36: =IF(BJ$299=0,0,BX36/BJ$299*100) -> 0 | BZ36: 48 | CA36: =IF(BL$299=0,0,BZ36/BL$299*100) -> 0.21428151 | CB36: 5557.0367 | CC36: =IF(BN$299=0,0,CB36/BN$299*100) -> 19.15748 | CD36: 329.51233 | CE36: =IF(BP$299=0,0,CD36/BP$299*100) -> 0.085472139
B37: =+B36+1 -> 22 | C37: LC / TR - BNI | E37: 2200 | F37: =IF(E$73=0,0,E37/E$73*100) -> 1.7857143 | G37: 2201 | H37: =IF(G$73=0,0,G37/G$73*100) -> 1.7848599 | I37: 2202 | J37: =IF(I$73=0,0,I37/I$73*100) -> 1.7840071 | K37: 2203 | L37: =IF(K$73=0,0,K37/K$73*100) -> 1.7831559 | BU37: 18 | BV37: Piutang Usaha - Pihak Ketiga | BX37: 0 | BY37: =IF(BJ$299=0,0,BX37/BJ$299*100) -> 0 | BZ37: 0 | CA37: =IF(BL$299=0,0,BZ37/BL$299*100) -> 0 | CB37: 0 | CC37: =IF(BN$299=0,0,CB37/BN$299*100) -> 0 | CD37: 0 | CE37: =IF(BP$299=0,0,CD37/BP$299*100) -> 0
B38: =+B37+1 -> 23 | C38: LC / TR - Other Banks | E38: 2300 | F38: =IF(E$73=0,0,E38/E$73*100) -> 1.8668831 | G38: 2301 | H38: =IF(G$73=0,0,G38/G$73*100) -> 1.865953 | I38: 2302 | J38: =IF(I$73=0,0,I38/I$73*100) -> 1.8650247 | K38: 2303 | L38: =IF(K$73=0,0,K38/K$73*100) -> 1.8640981 | BU38: 19 | BX38: 0 | BY38: =IF(L$253=0,0,BX38/L$253*100) -> 0 | BZ38: 0 | CA38: =IF(N$299=0,0,BZ38/N$299*100) -> 0 | CB38: 0 | CC38: =IF(P$299=0,0,CB38/P$299*100) -> 0 | CD38: 0 | CE38: =IF(R$299=0,0,CD38/R$299*100) -> 0
B39: =+B38+1 -> 24 | C39: Account Payables | E39: 2400 | F39: =IF(E$73=0,0,E39/E$73*100) -> 1.9480519 | G39: 2401 | H39: =IF(G$73=0,0,G39/G$73*100) -> 1.9470462 | I39: 2402 | J39: =IF(I$73=0,0,I39/I$73*100) -> 1.9460423 | K39: 2403 | L39: =IF(K$73=0,0,K39/K$73*100) -> 1.9450403 | BU39: 20 | BX39: 0 | BY39: =IF(BJ$299=0,0,BX39/BJ$299*100) -> 0 | BZ39: 0 | CA39: =IF(BL$299=0,0,BZ39/BL$299*100) -> 0 | CB39: 0 | CC39: =IF(BN$299=0,0,CB39/BN$299*100) -> 0 | CD39: 0 | CE39: =IF(BP$299=0,0,CD39/BP$299*100) -> 0
B40: =+B39+1 -> 25 | C40: Tax Payables | E40: 2500 | F40: =IF(E$73=0,0,E40/E$73*100) -> 2.0292208 | G40: 2501 | H40: =IF(G$73=0,0,G40/G$73*100) -> 2.0281393 | I40: 2502 | J40: =IF(I$73=0,0,I40/I$73*100) -> 2.0270599 | K40: 2503 | L40: =IF(K$73=0,0,K40/K$73*100) -> 2.0259824 | BU40: 21 | BX40: 0 | BY40: =IF(BJ$299=0,0,BX40/BJ$299*100) -> 0 | BZ40: 0 | CA40: =IF(BL$299=0,0,BZ40/BL$299*100) -> 0 | CB40: 0 | CC40: =IF(BN$299=0,0,CB40/BN$299*100) -> 0 | CD40: 0 | CE40: =IF(BP$299=0,0,CD40/BP$299*100) -> 0
B41: =+B40+1 -> 26 | C41: Shareholder & Related Parties Loans- Short Term | E41: 2600 | F41: =IF(E$73=0,0,E41/E$73*100) -> 2.1103896 | G41: 2601 | H41: =IF(G$73=0,0,G41/G$73*100) -> 2.1092325 | I41: 2602 | J41: =IF(I$73=0,0,I41/I$73*100) -> 2.1080775 | K41: 2603 | L41: =IF(K$73=0,0,K41/K$73*100) -> 2.1069246 | BU41: 22 | BX41: 0 | BY41: =IF(BJ$299=0,0,BX41/BJ$299*100) -> 0 | BZ41: 0 | CA41: =IF(BL$299=0,0,BZ41/BL$299*100) -> 0 | CB41: 0 | CC41: =IF(BN$299=0,0,CB41/BN$299*100) -> 0 | CD41: 0 | CE41: =IF(BP$299=0,0,CD41/BP$299*100) -> 0
B42: =+B41+1 -> 27 | C42: Accrued Expenses | E42: 2700 | F42: =IF(E$73=0,0,E42/E$73*100) -> 2.1915584 | G42: 2701 | H42: =IF(G$73=0,0,G42/G$73*100) -> 2.1903256 | I42: 2702 | J42: =IF(I$73=0,0,I42/I$73*100) -> 2.189095 | K42: 2703 | L42: =IF(K$73=0,0,K42/K$73*100) -> 2.1878668 | BU42: 23 | BX42: 0 | BY42: =IF(BJ$299=0,0,BX42/BJ$299*100) -> 0 | BZ42: 0 | CA42: =IF(BL$299=0,0,BZ42/BL$299*100) -> 0 | CB42: 0 | CC42: =IF(BN$299=0,0,CB42/BN$299*100) -> 0 | CD42: 0 | CE42: =IF(BP$299=0,0,CD42/BP$299*100) -> 0
B43: =+B42+1 -> 28 | C43: Customer Advances | E43: 2800 | F43: =IF(E$73=0,0,E43/E$73*100) -> 2.2727273 | G43: 2801 | H43: =IF(G$73=0,0,G43/G$73*100) -> 2.2714187 | I43: 2802 | J43: =IF(I$73=0,0,I43/I$73*100) -> 2.2701126 | K43: 2803 | L43: =IF(K$73=0,0,K43/K$73*100) -> 2.2688089 | BU43: 24 | BX43: 0 | BY43: =IF(BJ$299=0,0,BX43/BJ$299*100) -> 0 | BZ43: 0 | CA43: =IF(BL$299=0,0,BZ43/BL$299*100) -> 0 | CB43: 0 | CC43: =IF(BN$299=0,0,CB43/BN$299*100) -> 0 | CD43: 0 | CE43: =IF(BP$299=0,0,CD43/BP$299*100) -> 0
B44: =+B43+1 -> 29 | C44: Deferred Liabilities | E44: 2900 | F44: =IF(E$73=0,0,E44/E$73*100) -> 2.3538961 | G44: 2901 | H44: =IF(G$73=0,0,G44/G$73*100) -> 2.3525119 | I44: 2902 | J44: =IF(I$73=0,0,I44/I$73*100) -> 2.3511302 | K44: 2903 | L44: =IF(K$73=0,0,K44/K$73*100) -> 2.3497511 | BU44: 25 | BX44: 0 | BY44: =IF(BJ$299=0,0,BX44/BJ$299*100) -> 0 | BZ44: 0 | CA44: =IF(BL$299=0,0,BZ44/BL$299*100) -> 0 | CB44: 0 | CC44: =IF(BN$299=0,0,CB44/BN$299*100) -> 0 | CD44: 0 | CE44: =IF(BP$299=0,0,CD44/BP$299*100) -> 0
B45: =+B44+1 -> 30 | C45: Other Current Liabilities | E45: 3000 | F45: =IF(E$73=0,0,E45/E$73*100) -> 2.4350649 | G45: 3001 | H45: =IF(G$73=0,0,G45/G$73*100) -> 2.433605 | I45: 3002 | J45: =IF(I$73=0,0,I45/I$73*100) -> 2.4321478 | K45: 3003 | L45: =IF(K$73=0,0,K45/K$73*100) -> 2.4306933
B46: =+B45+1 -> 31 | C46: Current Portion of Long - Term Bank Loans - BNI | E46: 3100 | F46: =IF(E$73=0,0,E46/E$73*100) -> 2.5162338 | G46: 3101 | H46: =IF(G$73=0,0,G46/G$73*100) -> 2.5146981 | I46: 3102 | J46: =IF(I$73=0,0,I46/I$73*100) -> 2.5131654 | K46: 3103 | L46: =IF(K$73=0,0,K46/K$73*100) -> 2.5116354 | BU46: 26 | BX46: 0 | BY46: =IF(BJ$299=0,0,BX46/BJ$299*100) -> 0 | BZ46: 0 | CA46: =IF(BL$299=0,0,BZ46/BL$299*100) -> 0 | CB46: 0 | CC46: =IF(BN$299=0,0,CB46/BN$299*100) -> 0 | CD46: 0 | CE46: =IF(BP$299=0,0,CD46/BP$299*100) -> 0
B47: =B46+1 -> 32 | C47: Current Portion of Long - Term Bank Loans - Other Banks | E47: 3200 | F47: =IF(E$73=0,0,E47/E$73*100) -> 2.5974026 | G47: 3201 | H47: =IF(G$73=0,0,G47/G$73*100) -> 2.5957913 | I47: 3202 | J47: =IF(I$73=0,0,I47/I$73*100) -> 2.5941829 | K47: 3203 | L47: =IF(K$73=0,0,K47/K$73*100) -> 2.5925776
B48: =B47+1 -> 33 | C48: Current Portion of Lease Liabilities | E48: 3300 | F48: =IF(E$73=0,0,E48/E$73*100) -> 2.6785714 | G48: 3301 | H48: =IF(G$73=0,0,G48/G$73*100) -> 2.6768844 | I48: 3302 | J48: =IF(I$73=0,0,I48/I$73*100) -> 2.6752005 | K48: 3303 | L48: =IF(K$73=0,0,K48/K$73*100) -> 2.6735198
B49: =B48+1 -> 34 | C49: Current Portion of Long-Term Debts inc. Bonds/MTN/Securities | E49: 3400 | F49: =IF(E$73=0,0,E49/E$73*100) -> 2.7597403 | G49: 3401 | H49: =IF(G$73=0,0,G49/G$73*100) -> 2.7579775 | I49: 3402 | J49: =IF(I$73=0,0,I49/I$73*100) -> 2.7562181 | K49: 3403 | L49: =IF(K$73=0,0,K49/K$73*100) -> 2.7544619 | BU49: 27 | BX49: 0 | BY49: =IF(BJ$299=0,0,BX49/BJ$299*100) -> 0 | BZ49: 0 | CA49: =IF(BL$299=0,0,BZ49/BL$299*100) -> 0 | CB49: 0 | CC49: =IF(BN$299=0,0,CB49/BN$299*100) -> 0 | CD49: 0 | CE49: =IF(BP$299=0,0,CD49/BP$299*100) -> 0
B50: =+B49+1 -> 35 | C50: Total Current Liabilities | E50: =SUM(E35:E49) -> 40500 | F50: =IF(E$73=0,0,E50/E$73*100) -> 32.873377 | G50: =SUM(G35:G49) -> 40515 | H50: =IF(G$73=0,0,G50/G$73*100) -> 32.854884 | I50: =SUM(I35:I49) -> 40530 | J50: =IF(I$73=0,0,I50/I$73*100) -> 32.836426 | K50: =SUM(K35:K49) -> 40545 | L50: =IF(K$73=0,0,K50/K$73*100) -> 32.818002 | BU50: 28 | BX50: 0 | BY50: =IF(BJ$299=0,0,BX50/BJ$299*100) -> 0 | BZ50: 0 | CA50: =IF(BL$299=0,0,BZ50/BL$299*100) -> 0 | CB50: 0 | CC50: =IF(BN$299=0,0,CB50/BN$299*100) -> 0 | CD50: 0 | CE50: =IF(BP$299=0,0,CD50/BP$299*100) -> 0
B51: =+B50+1 -> 36 | C51: Long-Term Bank Loans - BNI | E51: 3600 | F51: =IF(E$73=0,0,E51/E$73*100) -> 2.9220779 | G51: 3601 | H51: =IF(G$73=0,0,G51/G$73*100) -> 2.9201638 | I51: 3602 | J51: =IF(I$73=0,0,I51/I$73*100) -> 2.9182533 | K51: 3603 | L51: =IF(K$73=0,0,K51/K$73*100) -> 2.9163463 | BU51: 29 | BX51: 0 | BY51: =IF(BJ$299=0,0,BX51/BJ$299*100) -> 0 | BZ51: 0 | CA51: =IF(BL$299=0,0,BZ51/BL$299*100) -> 0 | CB51: 0 | CC51: =IF(BN$299=0,0,CB51/BN$299*100) -> 0 | CD51: 0 | CE51: =IF(BP$299=0,0,CD51/BP$299*100) -> 0
B52: =+B51+1 -> 37 | C52: Long-Term Bank Loans - Other Banks | E52: 3700 | F52: =IF(E$73=0,0,E52/E$73*100) -> 3.0032468 | G52: 3701 | H52: =IF(G$73=0,0,G52/G$73*100) -> 3.0012569 | I52: 3702 | J52: =IF(I$73=0,0,I52/I$73*100) -> 2.9992708 | K52: 3703 | L52: =IF(K$73=0,0,K52/K$73*100) -> 2.9972884 | BU52: 30 | BV52: Penyisihan: Piutang Ragu-Ragu (-) | BX52: 0 | BY52: =IF(BJ$299=0,0,BX52/BJ$299*100) -> 0 | BZ52: 0 | CA52: =IF(BL$299=0,0,BZ52/BL$299*100) -> 0 | CB52: 0 | CC52: =IF(BN$299=0,0,CB52/BN$299*100) -> 0 | CD52: 0 | CE52: =IF(BP$299=0,0,CD52/BP$299*100) -> 0
B53: =+B52+1 -> 38 | C53: Lease Liabilities | E53: 3800 | F53: =IF(E$73=0,0,E53/E$73*100) -> 3.0844156 | G53: 3801 | H53: =IF(G$73=0,0,G53/G$73*100) -> 3.0823501 | I53: 3802 | J53: =IF(I$73=0,0,I53/I$73*100) -> 3.0802884 | K53: 3803 | L53: =IF(K$73=0,0,K53/K$73*100) -> 3.0782306
B54: =+B53+1 -> 39 | C54: Long-Term Debts - Bonds/MTN/Securities | E54: 3900 | F54: =IF(E$73=0,0,E54/E$73*100) -> 3.1655844 | G54: 3901 | H54: =IF(G$73=0,0,G54/G$73*100) -> 3.1634432 | I54: 3902 | J54: =IF(I$73=0,0,I54/I$73*100) -> 3.161306 | K54: 3903 | L54: =IF(K$73=0,0,K54/K$73*100) -> 3.1591728
B55: =+B54+1 -> 40 | C55: Employee Benefit Liabilities | E55: 4000 | F55: =IF(E$73=0,0,E55/E$73*100) -> 3.2467532 | G55: 4001 | H55: =IF(G$73=0,0,G55/G$73*100) -> 3.2445363 | I55: 4002 | J55: =IF(I$73=0,0,I55/I$73*100) -> 3.2423236 | K55: 4003 | L55: =IF(K$73=0,0,K55/K$73*100) -> 3.2401149 | BU55: 31 | BV55: Persediaan | BX55: 49.781119 | BY55: =IF(BJ$299=0,0,BX55/BJ$299*100) -> 3.5016537 | BZ55: 0 | CA55: =IF(BL$299=0,0,BZ55/BL$299*100) -> 0 | CB55: 4533.5447 | CC55: =IF(BN$299=0,0,CB55/BN$299*100) -> 15.629065 | CD55: 7184.5594 | CE55: =IF(BP$299=0,0,CD55/BP$299*100) -> 1.8636015
B56: =+B55+1 -> 41 | C56: Long Term Tax Payables | E56: 4100 | F56: =IF(E$73=0,0,E56/E$73*100) -> 3.3279221 | G56: 4101 | H56: =IF(G$73=0,0,G56/G$73*100) -> 3.3256295 | I56: 4102 | J56: =IF(I$73=0,0,I56/I$73*100) -> 3.3233412 | K56: 4103 | L56: =IF(K$73=0,0,K56/K$73*100) -> 3.3210571 | BG56: 32 | BH56: Bahan Baku | BJ56: 0 | BK56: =IF(BJ$299=0,0,BJ56/BJ$299*100) -> 0 | BL56: 0 | BM56: =IF(BL$299=0,0,BL56/BL$299*100) -> 0 | BN56: 0 | BO56: =IF(BN$299=0,0,BN56/BN$299*100) -> 0 | BP56: 0 | BQ56: =IF(BP$299=0,0,BP56/BP$299*100) -> 0
B57: =+B56+1 -> 42 | C57: Shareholders & Related Parties Loan- Long Term | E57: 4200 | F57: =IF(E$73=0,0,E57/E$73*100) -> 3.4090909 | G57: 4201 | H57: =IF(G$73=0,0,G57/G$73*100) -> 3.4067226 | I57: 4202 | J57: =IF(I$73=0,0,I57/I$73*100) -> 3.4043587 | K57: 4203 | L57: =IF(K$73=0,0,K57/K$73*100) -> 3.4019993 | BG57: 33 | BH57: Persediaan Dalam Proses | BJ57: 0 | BK57: =IF(BJ$299=0,0,BJ57/BJ$299*100) -> 0 | BL57: 0 | BM57: =IF(BL$299=0,0,BL57/BL$299*100) -> 0 | BN57: 0 | BO57: =IF(BN$299=0,0,BN57/BN$299*100) -> 0 | BP57: 0 | BQ57: =IF(BP$299=0,0,BP57/BP$299*100) -> 0
B58: =B57+1 -> 43 | C58: Other Non-Current Liabilities | E58: 4300 | F58: =IF(E$73=0,0,E58/E$73*100) -> 3.4902597 | G58: 4301 | H58: =IF(G$73=0,0,G58/G$73*100) -> 3.4878158 | I58: 4302 | J58: =IF(I$73=0,0,I58/I$73*100) -> 3.4853763 | K58: 4303 | L58: =IF(K$73=0,0,K58/K$73*100) -> 3.4829414 | BG58: 34 | BH58: Persediaan Untuk Dijual | BJ58: 0 | BK58: =IF(BJ$299=0,0,BJ58/BJ$299*100) -> 0 | BL58: 0 | BM58: =IF(BL$299=0,0,BL58/BL$299*100) -> 0 | BN58: 0 | BO58: =IF(BN$299=0,0,BN58/BN$299*100) -> 0 | BP58: 0 | BQ58: =IF(BP$299=0,0,BP58/BP$299*100) -> 0
B59: =+B58+1 -> 44 | C59: Total Non-Current Liabilities | E59: =SUM(E51:E58) -> 31600 | F59: =IF(E$73=0,0,E59/E$73*100) -> 25.649351 | G59: =SUM(G51:G58) -> 31608 | H59: =IF(G$73=0,0,G59/G$73*100) -> 25.631918 | I59: =SUM(I51:I58) -> 31616 | J59: =IF(I$73=0,0,I59/I$73*100) -> 25.614518 | K59: =SUM(K51:K58) -> 31624 | L59: =IF(K$73=0,0,K59/K$73*100) -> 25.597151 | BG59: 35 | BH59: Barang Dalam Perjalanan | BJ59: 0 | BK59: =IF(BJ$299=0,0,BJ59/BJ$299*100) -> 0 | BL59: 0 | BM59: =IF(BL$299=0,0,BL59/BL$299*100) -> 0 | BN59: 0 | BO59: =IF(BN$299=0,0,BN59/BN$299*100) -> 0 | BP59: 0 | BQ59: =IF(BP$299=0,0,BP59/BP$299*100) -> 0
B60: =+B59+1 -> 45 | C60: Total Liabilities | E60: =E50+E59 -> 72100 | F60: =IF(E$73=0,0,E60/E$73*100) -> 58.522727 | G60: =G50+G59 -> 72123 | H60: =IF(G$73=0,0,G60/G$73*100) -> 58.486802 | I60: =I50+I59 -> 72146 | J60: =IF(I$73=0,0,I60/I$73*100) -> 58.450944 | K60: =K50+K59 -> 72169 | L60: =IF(K$73=0,0,K60/K$73*100) -> 58.415152 | BG60: 36 | BH60: Perlengkapan | BJ60: 0 | BK60: =IF(BJ$299=0,0,BJ60/BJ$299*100) -> 0 | BL60: 0 | BM60: =IF(BL$299=0,0,BL60/BL$299*100) -> 0 | BN60: 0 | BO60: =IF(BN$299=0,0,BN60/BN$299*100) -> 0 | BP60: 0 | BQ60: =IF(BP$299=0,0,BP60/BP$299*100) -> 0
B61: =+B60+1 -> 46 | C61: Preference Shares | E61: 4600 | F61: =IF(E$73=0,0,E61/E$73*100) -> 3.7337662 | G61: 4601 | H61: =IF(G$73=0,0,G61/G$73*100) -> 3.7310952 | I61: 4602 | J61: =IF(I$73=0,0,I61/I$73*100) -> 3.7284291 | K61: 4603 | L61: =IF(K$73=0,0,K61/K$73*100) -> 3.7257679 | BG61: 37 | BJ61: 0 | BK61: =IF(BJ$299=0,0,BJ61/BJ$299*100) -> 0 | BL61: 0 | BM61: =IF(BL$299=0,0,BL61/BL$299*100) -> 0 | BN61: 0 | BO61: =IF(BN$299=0,0,BN61/BN$299*100) -> 0 | BP61: 0 | BQ61: =IF(BP$299=0,0,BP61/BP$299*100) -> 0
B62: =+B61+1 -> 47 | C62: Common Shares | E62: 4700 | F62: =IF(E$73=0,0,E62/E$73*100) -> 3.8149351 | G62: 4701 | H62: =IF(G$73=0,0,G62/G$73*100) -> 3.8121883 | I62: 4702 | J62: =IF(I$73=0,0,I62/I$73*100) -> 3.8094466 | K62: 4703 | L62: =IF(K$73=0,0,K62/K$73*100) -> 3.8067101 | BG62: 38 | BJ62: 0 | BK62: =IF(BJ$299=0,0,BJ62/BJ$299*100) -> 0 | BL62: 0 | BM62: =IF(BL$299=0,0,BL62/BL$299*100) -> 0 | BN62: 0 | BO62: =IF(BN$299=0,0,BN62/BN$299*100) -> 0 | BP62: 0 | BQ62: =IF(BP$299=0,0,BP62/BP$299*100) -> 0
B63: =B62+1 -> 48 | C63: Treasury Shares | E63: 4800 | F63: =IF(E$73=0,0,E63/E$73*100) -> 3.8961039 | G63: 4801 | H63: =IF(G$73=0,0,G63/G$73*100) -> 3.8932814 | I63: 4802 | J63: =IF(I$73=0,0,I63/I$73*100) -> 3.8904642 | K63: 4803 | L63: =IF(K$73=0,0,K63/K$73*100) -> 3.8876523
B64: =B63+1 -> 49 | C64: Share Premium (Agio Share) | E64: 4900 | F64: =IF(E$73=0,0,E64/E$73*100) -> 3.9772727 | G64: 4901 | H64: =IF(G$73=0,0,G64/G$73*100) -> 3.9743746 | I64: 4902 | J64: =IF(I$73=0,0,I64/I$73*100) -> 3.9714818 | K64: 4903 | L64: =IF(K$73=0,0,K64/K$73*100) -> 3.9685944 | BG64: 39 | BJ64: 0 | BK64: =IF(BJ$299=0,0,BJ64/BJ$299*100) -> 0 | BL64: 0 | BM64: =IF(BL$299=0,0,BL64/BL$299*100) -> 0 | BN64: 0 | BO64: =IF(BN$299=0,0,BN64/BN$299*100) -> 0 | BP64: 0 | BQ64: =IF(BP$299=0,0,BP64/BP$299*100) -> 0
B65: =B64+1 -> 50 | C65: Additional Paid-In Capital | E65: 5000 | F65: =IF(E$73=0,0,E65/E$73*100) -> 4.0584416 | G65: 5001 | H65: =IF(G$73=0,0,G65/G$73*100) -> 4.0554677 | I65: 5002 | J65: =IF(I$73=0,0,I65/I$73*100) -> 4.0524994 | K65: 5003 | L65: =IF(K$73=0,0,K65/K$73*100) -> 4.0495366
B66: =B65+1 -> 51 | C66: Subordinated Shareholders & Related Parties Loan | E66: 5100 | F66: =IF(E$73=0,0,E66/E$73*100) -> 4.1396104 | G66: 5101 | H66: =IF(G$73=0,0,G66/G$73*100) -> 4.1365608 | I66: 5102 | J66: =IF(I$73=0,0,I66/I$73*100) -> 4.133517 | K66: 5103 | L66: =IF(K$73=0,0,K66/K$73*100) -> 4.1304788 | BG66: 40 | BJ66: 0 | BK66: =IF(BJ$299=0,0,BJ66/BJ$299*100) -> 0 | BL66: 0 | BM66: =IF(BL$299=0,0,BL66/BL$299*100) -> 0 | BN66: 0 | BO66: =IF(BN$299=0,0,BN66/BN$299*100) -> 0 | BP66: 0 | BQ66: =IF(BP$299=0,0,BP66/BP$299*100) -> 0
B67: =+B66+1 -> 52 | C67: Difference in Corporate Transactions | E67: 5200 | F67: =IF(E$73=0,0,E67/E$73*100) -> 4.2207792 | G67: 5201 | H67: =IF(G$73=0,0,G67/G$73*100) -> 4.217654 | I67: 5202 | J67: =IF(I$73=0,0,I67/I$73*100) -> 4.2145346 | K67: 5203 | L67: =IF(K$73=0,0,K67/K$73*100) -> 4.2114209 | BG67: 41 | BJ67: 0 | BK67: =IF(BJ$299=0,0,BJ67/BJ$299*100) -> 0 | BL67: 0 | BM67: =IF(BL$299=0,0,BL67/BL$299*100) -> 0 | BN67: 0 | BO67: =IF(BN$299=0,0,BN67/BN$299*100) -> 0 | BP67: 0 | BQ67: =IF(BP$299=0,0,BP67/BP$299*100) -> 0
B68: =B67+1 -> 53 | C68: Other Equity | E68: 5300 | F68: =IF(E$73=0,0,E68/E$73*100) -> 4.3019481 | G68: 5301 | H68: =IF(G$73=0,0,G68/G$73*100) -> 4.2987471 | I68: 5302 | J68: =IF(I$73=0,0,I68/I$73*100) -> 4.2955521 | K68: 5303 | L68: =IF(K$73=0,0,K68/K$73*100) -> 4.2923631 | BG68: 44 | BJ68: 0 | BK68: =IF(BJ$299=0,0,BJ68/BJ$299*100) -> 0 | BL68: 0 | BM68: =IF(BL$299=0,0,BL68/BL$299*100) -> 0 | BN68: 0 | BO68: =IF(BN$299=0,0,BN68/BN$299*100) -> 0 | BP68: 0 | BQ68: =IF(BP$299=0,0,BP68/BP$299*100) -> 0
B69: =B68+1 -> 54 | C69: Previous Retained Earnings | E69: 5400 | F69: =IF(E$73=0,0,E69/E$73*100) -> 4.3831169 | G69: =SUM(E69:E71) -> 11500 | H69: =IF(G$73=0,0,G69/G$73*100) -> 9.3257106 | I69: =SUM(G69:G71) -> 11584 | J69: =IF(I$73=0,0,I69/I$73*100) -> 9.3850766 | K69: =SUM(I69:I71) -> 11668 | L69: =IF(K$73=0,0,K69/K$73*100) -> 9.444332 | O69: -13439.545 | P69: 98313.591 | Q69: 99201.758 | BG69: 45 | BH69: Penyisihan: Untuk Persediaan Usang/Lambat Bergerak (-) | BJ69: 0 | BK69: =IF(BJ$299=0,0,BJ69/BJ$299*100) -> 0 | BL69: 0 | BM69: =IF(BL$299=0,0,BL69/BL$299*100) -> 0 | BN69: 0 | BO69: =IF(BN$299=0,0,BN69/BN$299*100) -> 0 | BP69: 0 | BQ69: =IF(BP$299=0,0,BP69/BP$299*100) -> 0
B70: =+B69+1 -> 55 | C70: Profit / (Loss) for The Year | E70: =E122 -> 7650 | F70: =IF(E$73=0,0,E70/E$73*100) -> 6.2094156 | G70: =G122 -> 13935 | H70: =IF(G$73=0,0,G70/G$73*100) -> 11.300328 | I70: =I122 -> 19400 | J70: =IF(I$73=0,0,I70/I$73*100) -> 15.717411 | K70: =K122 -> 19105 | L70: =IF(K$73=0,0,K70/K$73*100) -> 15.464001 | BG70: 46 | BH70: Aset Lancar Lainnya | BJ70: 0 | BK70: =IF(BJ$299=0,0,BJ70/BJ$299*100) -> 0 | BL70: 0 | BM70: =IF(BL$299=0,0,BL70/BL$299*100) -> 0 | BN70: 0 | BO70: =IF(BN$299=0,0,BN70/BN$299*100) -> 0 | BP70: 1303.0846 | BQ70: =IF(BP$299=0,0,BP70/BP$299*100) -> 0.33800685
B71: =B70+1 -> 56 | C71: Profit/(Loss) Adjustments | E71: -1550 | F71: =IF(E$73=0,0,E71/E$73*100) -> -1.2581169 | G71: -13851 | H71: =IF(G$73=0,0,G71/G$73*100) -> -11.23221 | I71: -19316 | J71: =IF(I$73=0,0,I71/I$73*100) -> -15.649356 | K71: -19021 | L71: =IF(K$73=0,0,K71/K$73*100) -> -15.39601 | BU71: 47 | BV71: Pajak Dibayar Dimuka | BX71: 0 | BY71: =IF(BJ$299=0,0,BX71/BJ$299*100) -> 0 | BZ71: 97.060412 | CA71: =IF(BL$299=0,0,BZ71/BL$299*100) -> 0.4332969 | CB71: 370.22209 | CC71: =IF(BN$299=0,0,CB71/BN$299*100) -> 1.2763137 | CD71: 12239.685 | CE71: =IF(BP$299=0,0,CD71/BP$299*100) -> 3.1748495
B72: =B71+1 -> 57 | C72: Total Equity | E72: =SUM(E61:E71) -> 51100 | F72: =IF(E$73=0,0,E72/E$73*100) -> 41.477273 | G72: =SUM(G61:G71) -> 51192 | H72: =IF(G$73=0,0,G72/G$73*100) -> 41.513198 | I72: =SUM(I61:I71) -> 51284 | J72: =IF(I$73=0,0,I72/I$73*100) -> 41.549056 | K72: =SUM(K61:K71) -> 51376 | L72: =IF(K$73=0,0,K72/K$73*100) -> 41.584848 | BG72: 48 | BH72: Tagihan Piutang | BJ72: 374.85685 | BK72: =IF(BJ$299=0,0,BJ72/BJ$299*100) -> 26.367806 | BL72: 0 | BM72: =IF(BL$299=0,0,BL72/BL$299*100) -> 0 | BN72: 0 | BO72: =IF(BN$299=0,0,BN72/BN$299*100) -> 0 | BP72: 0 | BQ72: =IF(BP$299=0,0,BP72/BP$299*100) -> 0
B73: =+B72+1 -> 58 | C73: TOTAL LIABILITIES & EQUITY | E73: =E60+E72 -> 123200 | F73: =IF(E$73=0,0,E73/E$73*100) -> 100 | G73: =G60+G72 -> 123315 | H73: =IF(G$73=0,0,G73/G$73*100) -> 100 | I73: =I60+I72 -> 123430 | J73: =IF(I$73=0,0,I73/I$73*100) -> 100 | K73: =K60+K72 -> 123545 | L73: =IF(K$73=0,0,K73/K$73*100) -> 100 | U73: 157881 | W73: 303530 | Y73: 310346 | AA73: 597520 | BG73: 49 | BH73: Piutang Non Usaha | BJ73: 0 | BK73: =IF(BJ$299=0,0,BJ73/BJ$299*100) -> 0 | BL73: 0 | BM73: =IF(BL$299=0,0,BL73/BL$299*100) -> 0 | BN73: 0 | BO73: =IF(BN$299=0,0,BN73/BN$299*100) -> 0 | BP73: 0 | BQ73: =IF(BP$299=0,0,BP73/BP$299*100) -> 0
C74: Long-Term Debt Details: | BU74: 50 | BV74: Biaya Dibayar di Muka | BX74: 0 | BY74: =IF(BJ$299=0,0,BX74/BJ$299*100) -> 0 | BZ74: 0 | CA74: =IF(BL$299=0,0,BZ74/BL$299*100) -> 0 | CB74: 0 | CC74: =IF(BN$299=0,0,CB74/BN$299*100) -> 0 | CD74: 0 | CE74: =IF(BP$299=0,0,CD74/BP$299*100) -> 0
C75: Long-Term Bank Loans - BNI + Others Bank | BU75: 51 | BV75: Uang Muka Pembelian | BX75: 9.85 | BY75: =IF(BJ$299=0,0,BX75/BJ$299*100) -> 0.69285886 | BZ75: 11847.744 | CA75: =IF(BL$299=0,0,BZ75/BL$299*100) -> 52.890678 | CB75: 143.75 | CC75: =IF(BN$299=0,0,CB75/BN$299*100) -> 0.49556766 | CD75: 12.6667 | CE75: =IF(BP$299=0,0,CD75/BP$299*100) -> 0.0032856128
C76: Beginning balance | G76: =+E79 -> 13600 | I76: =+G79 -> 13604 | K76: =+I79 -> 13608 | BG76: 52 | BH76: Piutang pada Pihak Terkait - Bagian Lancar | BJ76: 0 | BK76: =IF(BJ$299=0,0,BJ76/BJ$299*100) -> 0 | BL76: 0 | BM76: =IF(BL$299=0,0,BL76/BL$299*100) -> 0 | BN76: 0 | BO76: =IF(BN$299=0,0,BN76/BN$299*100) -> 0 | BP76: 0 | BQ76: =IF(BP$299=0,0,BP76/BP$299*100) -> 0
C77: (+) Loan Disbursement | G77: =IF(+G79-G76+E46+E47 < 0, 0, +G79-G76+E46+E47) -> 6304 | I77: =IF(+I79-I76+G46+G47 < 0, 0, +I79-I76+G46+G47) -> 6306 | K77: =IF(+K79-K76+I46+I47 < 0, 0, +K79-K76+I46+I47) -> 6308 | BG77: 53 | BH77: Pengembalian Pajak Tangguhan - Bagian Lancar | BJ77: 0 | BK77: =IF(BJ$299=0,0,BJ77/BJ$299*100) -> 0 | BL77: 0 | BM77: =IF(BL$299=0,0,BL77/BL$299*100) -> 0 | BN77: 0 | BO77: =IF(BN$299=0,0,BN77/BN$299*100) -> 0 | BP77: 0 | BQ77: =IF(BP$299=0,0,BP77/BP$299*100) -> 0
C78: (-) Principal Repayments | G78: =IF(+G79-G76+E46+E47 < 0, +E46+E47-(+G79-G76+E46+E47), +E46+E47) -> 6300 | I78: =IF(+I79-I76+G46+G47 < 0, +G46+G47-(+I79-I76+G46+G47), +G46+G47) -> 6302 | K78: =IF(+K79-K76+I46+I47 < 0, +I46+I47-(+K79-K76+I46+I47), +I46+I47) -> 6304 | BG78: 54 | BH78: Pinjaman kepada Pihak Terkait | BJ78: 0 | BK78: =IF(BJ$299=0,0,BJ78/BJ$299*100) -> 0 | BL78: 0 | BM78: =IF(BL$299=0,0,BL78/BL$299*100) -> 0 | BN78: 0 | BO78: =IF(BN$299=0,0,BN78/BN$299*100) -> 0 | BP78: 0 | BQ78: =IF(BP$299=0,0,BP78/BP$299*100) -> 0
C79: Ending balance | E79: =E46+E47+E51+E52 -> 13600 | G79: =G46+G47+G51+G52 -> 13604 | I79: =I46+I47+I51+I52 -> 13608 | K79: =K46+K47+K51+K52 -> 13612 | BG79: 55 | BH79: Biaya Lebih dari Penagihan | BJ79: 0 | BK79: =IF(BJ$299=0,0,BJ79/BJ$299*100) -> 0 | BL79: 0 | BM79: =IF(BL$299=0,0,BL79/BL$299*100) -> 0 | BN79: 0 | BO79: =IF(BN$299=0,0,BN79/BN$299*100) -> 0 | BP79: 0 | BQ79: =IF(BP$299=0,0,BP79/BP$299*100) -> 0
C80: Long-Term Debts Incl. Bonds/MTN/Securities | BU80: 51 | BV80: Uang Muka Pembelian | BX80: 9.85 | BY80: =IF(BJ$299=0,0,BX80/BJ$299*100) -> 0.69285886 | BZ80: 11847.744 | CA80: =IF(BL$299=0,0,BZ80/BL$299*100) -> 52.890678 | CB80: 143.75 | CC80: =IF(BN$299=0,0,CB80/BN$299*100) -> 0.49556766 | CD80: 12.6667 | CE80: =IF(BP$299=0,0,CD80/BP$299*100) -> 0.0032856128
C81: Beginning Balance | G81: =+E84 -> 7300 | I81: =+G84 -> 7302 | K81: =+I84 -> 7304 | BG81: 52 | BH81: Piutang pada Pihak Terkait - Bagian Lancar | BJ81: 0 | BK81: =IF(BJ$299=0,0,BJ81/BJ$299*100) -> 0 | BL81: 0 | BM81: =IF(BL$299=0,0,BL81/BL$299*100) -> 0 | BN81: 0 | BO81: =IF(BN$299=0,0,BN81/BN$299*100) -> 0 | BP81: 0 | BQ81: =IF(BP$299=0,0,BP81/BP$299*100) -> 0
C82: (+) Debt Drawdown | G82: =IF(+G84-G81+E49 < 0, 0, +G84-G81+E49) -> 3402 | I82: =IF(+I84-I81+G49 < 0, 0, +I84-I81+G49) -> 3403 | K82: =IF(+K84-K81+I49 < 0, 0, +K84-K81+I49) -> 3404 | BG82: 53 | BH82: Pengembalian Pajak Tangguhan - Bagian Lancar | BJ82: 0 | BK82: =IF(BJ$299=0,0,BJ82/BJ$299*100) -> 0 | BL82: 0 | BM82: =IF(BL$299=0,0,BL82/BL$299*100) -> 0 | BN82: 0 | BO82: =IF(BN$299=0,0,BN82/BN$299*100) -> 0 | BP82: 0 | BQ82: =IF(BP$299=0,0,BP82/BP$299*100) -> 0
C83: (-) Principal Repayments | G83: =IF(+G84-G81+E49 < 0, +E49-(+G84-G81+E49), +E49) -> 3400 | I83: =IF(+I84-I81+G49 < 0, +G49-(+I84-I81+G49), +G49) -> 3401 | K83: =IF(+K84-K81+I49 < 0, +I49-(+K84-K81+I49), +I49) -> 3402 | BG83: 54 | BH83: Pinjaman kepada Pihak Terkait | BJ83: 0 | BK83: =IF(BJ$299=0,0,BJ83/BJ$299*100) -> 0 | BL83: 0 | BM83: =IF(BL$299=0,0,BL83/BL$299*100) -> 0 | BN83: 0 | BO83: =IF(BN$299=0,0,BN83/BN$299*100) -> 0 | BP83: 0 | BQ83: =IF(BP$299=0,0,BP83/BP$299*100) -> 0
C84: Ending Balance | E84: =E49+E54 -> 7300 | G84: =G49+G54 -> 7302 | I84: =I49+I54 -> 7304 | K84: =K49+K54 -> 7306 | BG84: 55 | BH84: Biaya Lebih dari Penagihan | BJ84: 0 | BK84: =IF(BJ$299=0,0,BJ84/BJ$299*100) -> 0 | BL84: 0 | BM84: =IF(BL$299=0,0,BL84/BL$299*100) -> 0 | BN84: 0 | BO84: =IF(BN$299=0,0,BN84/BN$299*100) -> 0 | BP84: 0 | BQ84: =IF(BP$299=0,0,BP84/BP$299*100) -> 0
C85: Lease Liabilities | BG85: 56 | BH85: Aset Derivaif - Bagian Lancar | BJ85: 0 | BK85: =IF(BJ$299=0,0,BJ85/BJ$299*100) -> 0 | BL85: 0 | BM85: =IF(BL$299=0,0,BL85/BL$299*100) -> 0 | BN85: 0 | BO85: =IF(BN$299=0,0,BN85/BN$299*100) -> 0 | BP85: 0 | BQ85: =IF(BP$299=0,0,BP85/BP$299*100) -> 0
C86: Beginning Balance | G86: =+E89 -> 7100 | I86: =+G89 -> 7102 | K86: =+I89 -> 7104 | BG86: 57 | BH86: Aset Lancar Non Operasional | BJ86: 0 | BK86: =IF(BJ$299=0,0,BJ86/BJ$299*100) -> 0 | BL86: 0 | BM86: =IF(BL$299=0,0,BL86/BL$299*100) -> 0 | BN86: 0 | BO86: =IF(BN$299=0,0,BN86/BN$299*100) -> 0 | BP86: 0 | BQ86: =IF(BP$299=0,0,BP86/BP$299*100) -> 0
C87: (+) Loan Disbursement | G87: =IF(+G89-G86+E48 < 0, 0, +G89-G86+E48) -> 3302 | I87: =IF(+I89-I86+G48 < 0, 0, +I89-I86+G48) -> 3303 | K87: =IF(+K89-K86+I48 < 0, 0, +K89-K86+I48) -> 3304 | BG87: 58 | BH87: Penyisihan untuk Penyesuaian (-) | BJ87: 0 | BK87: =IF(BJ$299=0,0,BJ87/BJ$299*100) -> 0 | BL87: 0 | BM87: =IF(BL$299=0,0,BL87/BL$299*100) -> 0 | BN87: 0 | BO87: =IF(BN$299=0,0,BN87/BN$299*100) -> 0 | BP87: 0 | BQ87: =IF(BP$299=0,0,BP87/BP$299*100) -> 0
C88: (-) Principal Repayments | G88: =IF(+G89-G86+E48 < 0, +E48-(+G89-G86+E48), +E48) -> 3300 | I88: =IF(+I89-I86+G48 < 0, +G48-(+I89-I86+G48), +G48) -> 3301 | K88: =IF(+K89-K86+I48 < 0, +I48-(+K89-K86+I48), +I48) -> 3302 | BG88: 59 | BJ88: 0 | BK88: =IF(BJ$299=0,0,BJ88/BJ$299*100) -> 0 | BL88: 0 | BM88: =IF(BL$299=0,0,BL88/BL$299*100) -> 0 | BN88: 0 | BO88: =IF(BN$299=0,0,BN88/BN$299*100) -> 0 | BP88: 0 | BQ88: =IF(BP$299=0,0,BP88/BP$299*100) -> 0
C89: Ending Balance | E89: =E48+E53 -> 7100 | G89: =+G48+G53 -> 7102 | I89: =+I48+I53 -> 7104 | K89: =+K48+K53 -> 7106 | BG89: 60 | BJ89: 0 | BK89: =IF(BJ$299=0,0,BJ89/BJ$299*100) -> 0 | BL89: 0 | BM89: =IF(BL$299=0,0,BL89/BL$299*100) -> 0 | BN89: 0 | BO89: =IF(BN$299=0,0,BN89/BN$299*100) -> 0 | BP89: 0 | BQ89: =IF(BP$299=0,0,BP89/BP$299*100) -> 0
C90: Financial Ratios Related to the Balance Sheet: | E90: =E13 -> 44561 | G90: =G13 -> 44926 | I90: =I13 -> 45291 | K90: =K13 -> 45473 | BG90: 61 | BH90: TOTAL ASSET LANCAR | BJ90: =SUM(BJ16:BJ89) -> 1570.3401 | BK90: =IF(BJ$299=0,0,BJ90/BJ$299*100) -> 110.4593 | BL90: =SUM(BL16:BL89) -> 506.07126 | BM90: =IF(BL$299=0,0,BL90/BL$299*100) -> 2.2592023 | BN90: =SUM(BN16:BN89) -> 2370.9002 | BO90: =IF(BN$299=0,0,BN90/BN$299*100) -> 8.1735057 | BP90: =SUM(BP16:BP89) -> 151292.15 | BQ90: =IF(BP$299=0,0,BP90/BP$299*100) -> 39.243643
C91: Current Ratio (CR) | E91: =IF(E50=0,0,E25/E50) -> 0.11111111 | F91: times | G91: =IF(G50=0,0,G25/G50) -> 0.11129211 | H91: times | I91: =IF(I50=0,0,I25/I50) -> 0.11147298 | J91: times | K91: =IF(K50=0,0,K25/K50) -> 0.11165372 | L91: times
C92: Current Ratio (CR) excl CPLTD | E92: =IF((E50-SUM(E46:E49))=0,0,E25/(E50-SUM(E46:E49))) -> 0.16363636 | F92: times | G92: =IF((G50-SUM(G46:G49))=0,0,G25/(G50-SUM(G46:G49))) -> 0.16389808 | H92: times | I92: =IF((I50-SUM(I46:I49))=0,0,I25/(I50-SUM(I46:I49))) -> 0.16415958 | J92: times | K92: =IF((K50-SUM(K46:K49))=0,0,K25/(K50-SUM(K46:K49))) -> 0.16442088 | L92: times
C93: Debt to Equity Ratio (DER) | E93: =IF((E72)=0,0,(E60)/(E72)) -> 1.4109589 | F93: times | G93: =IF((G72)=0,0,(G60)/(G72)) -> 1.4088725 | H93: times | I93: =IF((I72)=0,0,(I60)/(I72)) -> 1.4067935 | J93: times | K93: =IF((K72)=0,0,(K60)/(K72)) -> 1.404722 | L93: times | BU93: =+BG90+1 -> 62 | BV93: Aset Tetap | BX93: 92517.448 | BY93: =IF(BJ$299=0,0,BX93/BJ$299*100) -> 6507.7699 | BZ93: 144759.88 | CA93: =IF(BL$299=0,0,BZ93/BL$299*100) -> 646.23676 | CB93: 149738.85 | CC93: =IF(BN$299=0,0,CB93/BN$299*100) -> 516.2138 | CD93: 100569.4 | CE93: =IF(BP$299=0,0,CD93/BP$299*100) -> 26.086676
C94: Days Account Receivable | E94: =IF(E105=0,0,(E19/E105)*F13) -> 1.44 | F94: days | G94: =IF(G105=0,0,(G19/G105)*H13) -> 1.3123636 | H94: days | I94: =IF(I105=0,0,(I19/I105)*J13) -> 1.206 | J94: days | K94: =IF(K105=0,0,(K19/K105)*L13) -> 0.558 | L94: days
C95: Days Inventory | E95: =IF(E106=0,0,(E20/E106)*F13) -> 2.25 | F95: days | G95: =IF(G106=0,0,(G20/G106)*H13) -> 2.2266667 | H95: days | I95: =IF(I106=0,0,(I20/I106)*J13) -> 2.2039024 | J95: days | K95: =IF(K106=0,0,(K20/K106)*L13) -> 1.006 | L95: days | BG95: 63 | BH95: Tanah | BJ95: 0 | BK95: =IF(BJ$299=0,0,BJ95/BJ$299*100) -> 0 | BL95: 0 | BM95: =IF(BL$299=0,0,BL95/BL$299*100) -> 0 | BN95: 0 | BO95: =IF(BN$299=0,0,BN95/BN$299*100) -> 0 | BP95: 0 | BQ95: =IF(BP$299=0,0,BP95/BP$299*100) -> 0
C96: Days Account Payable | E96: =IF(E106=0,0,(E39/E106)*F13) -> 10.8 | F96: days | G96: =IF(G106=0,0,(G39/G106)*H13) -> 10.671111 | H96: days | I96: =IF(I106=0,0,(I39/I106)*J13) -> 10.545366 | J96: days | K96: =IF(K106=0,0,(K39/K106)*L13) -> 4.806 | L96: days | BG96: 64 | BH96: Bangunan | BJ96: 0 | BK96: =IF(BJ$299=0,0,BJ96/BJ$299*100) -> 0 | BL96: 0 | BM96: =IF(BL$299=0,0,BL96/BL$299*100) -> 0 | BN96: 0 | BO96: =IF(BN$299=0,0,BN96/BN$299*100) -> 0 | BP96: 0 | BQ96: =IF(BP$299=0,0,BP96/BP$299*100) -> 0
C97: Cash to Cash Cycle | E97: =E94+E95-E96 -> -7.11 | F97: days | G97: =G94+G95-G96 -> -7.1320808 | H97: days | I97: =I94+I95-I96 -> -7.1354634 | J97: days | K97: =K94+K95-K96 -> -3.242 | L97: days
C98: Net Working Capital (NWC) | E98: =E25-E50 -> -36000 | F98: IDR Million | G98: =G25-G50 -> -36006 | H98: IDR Million | I98: =I25-I50 -> -36012 | J98: IDR Million | K98: =K25-K50 -> -36018 | L98: IDR Million | BG98: 65 | BH98: Perbaikan Prasarana | BJ98: 0 | BK98: =IF(BJ$299=0,0,BJ98/BJ$299*100) -> 0 | BL98: 0 | BM98: =IF(BL$299=0,0,BL98/BL$299*100) -> 0 | BN98: 0 | BO98: =IF(BN$299=0,0,BN98/BN$299*100) -> 0 | BP98: 0 | BQ98: =IF(BP$299=0,0,BP98/BP$299*100) -> 0
C99: Difference | E99: =E34-E73 -> 0 | G99: =G34-G73 -> 0 | I99: =I34-I73 -> 0 | K99: =K34-K73 -> 0 | BG99: 66 | BH99: Mesin & Peralatan | BJ99: 0 | BK99: =IF(BJ$299=0,0,BJ99/BJ$299*100) -> 0 | BL99: 0 | BM99: =IF(BL$299=0,0,BL99/BL$299*100) -> 0 | BN99: 0 | BO99: =IF(BN$299=0,0,BN99/BN$299*100) -> 0 | BP99: 0 | BQ99: =IF(BP$299=0,0,BP99/BP$299*100) -> 0
BG100: 67 | BH100: Kendaraan | BJ100: 0 | BK100: =IF(BJ$299=0,0,BJ100/BJ$299*100) -> 0 | BL100: 0 | BM100: =IF(BL$299=0,0,BL100/BL$299*100) -> 0 | BN100: 0 | BO100: =IF(BN$299=0,0,BN100/BN$299*100) -> 0 | BP100: 0 | BQ100: =IF(BP$299=0,0,BP100/BP$299*100) -> 0
B101: PROFIT & LOSS STATEMENT | BG101: 68 | BH101: Perabot & Inventaris | BJ101: 0 | BK101: =IF(BJ$299=0,0,BJ101/BJ$299*100) -> 0 | BL101: 0 | BM101: =IF(BL$299=0,0,BL101/BL$299*100) -> 0 | BN101: 0 | BO101: =IF(BN$299=0,0,BN101/BN$299*100) -> 0 | BP101: 0 | BQ101: =IF(BP$299=0,0,BP101/BP$299*100) -> 0
B102: =+B12 -> Financial Statement Unit | E102: HISTORICAL | BG102: 69 | BH102: Sewa Guna Usaha | BJ102: 0 | BK102: =IF(BJ$299=0,0,BJ102/BJ$299*100) -> 0 | BL102: 0 | BM102: =IF(BL$299=0,0,BL102/BL$299*100) -> 0 | BN102: 0 | BO102: =IF(BN$299=0,0,BN102/BN$299*100) -> 0 | BP102: 0 | BQ102: =IF(BP$299=0,0,BP102/BP$299*100) -> 0
...

Sheet Assumption
C3: ASSUMPTIONS OF FINANCIAL PROJECTIONS
R5: ---
R6: =DATE(YEAR(Historical!K13),MONTH(Historical!K13)+1,VLOOKUP(MONTH(Historical!K13)+1,$T$6:$U$20,2)) -> 45504 | T6: 1 | U6: 31
D7: 1 | E7: Assumptions of Sales | R7: =DATE(YEAR(R6),MONTH(R6)+1,VLOOKUP(MONTH(R6)+1,$T$6:$U$19,2)) -> 45535 | T7: 2 | U7: 28
F8: Realization: | G8: =+Historical!B13 -> IDR Million | H8: Growth (%) | R8: =DATE(YEAR(R7),MONTH(R7)+1,VLOOKUP(MONTH(R7)+1,$T$6:$U$19,2)) -> 45565 | T8: 3 | U8: 31
F9: =+Historical!E13 -> 44561 | G9: =+Historical!E105 -> 100000 | H9: N/A | R9: =DATE(YEAR(R8),MONTH(R8)+1,VLOOKUP(MONTH(R8)+1,$T$6:$U$19,2)) -> 45596 | T9: 4 | U9: 30
F10: =+Historical!G13 -> 44926 | G10: =+Historical!G105 -> 110000 | H10: =Historical!G129 -> 10 | R10: =DATE(YEAR(R9),MONTH(R9)+1,VLOOKUP(MONTH(R9)+1,$T$6:$U$19,2)) -> 45626 | T10: 5 | U10: 31
F11: =+Historical!I13 -> 45291 | G11: =+Historical!I105 -> 120000 | H11: =Historical!I129 -> 9.0909091 | R11: =DATE(YEAR(R10),MONTH(R10)+1,VLOOKUP(MONTH(R10)+1,$T$6:$U$19,2)) -> 45656 | T11: 6 | U11: 30
F12: =+Historical!K13 -> 45473 | G12: =Historical!K105 -> 130000 | H12: =Historical!K129 -> 116.66667 | R12: =DATE(YEAR(R11),MONTH(R11)+1,VLOOKUP(MONTH(R11)+1,$T$6:$U$19,2)) -> 45687 | T12: 7 | U12: 31
R13: =DATE(YEAR(R12),MONTH(R12)+1,VLOOKUP(MONTH(R12)+1,$T$6:$U$19,2)) -> 45716 | T13: 8 | U13: 31
F14: Assumptions of Projections Sales Growth: | R14: =DATE(YEAR(R13),MONTH(R13)+1,VLOOKUP(MONTH(R13)+1,$T$6:$U$19,2)) -> 45747 | T14: 9 | U14: 30
F15: =+IF(MONTH(F12)=12,DATE(YEAR(F12)+1,12,31),DATE(YEAR(F11)+1,12,31)) -> 45657 | G15: =IF(K15=F12,G12*(1+I15),G11*(1+I15)) -> 132000 | H15: Growth (%) | I15: =+(SUM(J23:J26)-G12)/G12 -> 0.1 | J15: from | K15: =+IF(MONTH(F12)=12,F12,F11) -> 45291 | R15: =DATE(YEAR(R14),MONTH(R14)+1,VLOOKUP(MONTH(R14)+1,$T$6:$U$19,2)) -> 45777 | T15: 10 | U15: 31
F17: =+IF(MONTH(F12)=12,"",IF(G15<G12,"Agar input asumsi Growth lainnya, karena posisi Sales di bulan Desember harus lebih besar dari posisi terakhir !!",""))
F19: Reason of assumptions : | R19: =DATE(YEAR(R15),MONTH(R15)+1,VLOOKUP(MONTH(R15)+1,$T$6:$U$19,2)) -> 45808 | T19: 11 | U19: 30
R20: =DATE(YEAR(R19),MONTH(R19)+1,VLOOKUP(MONTH(R19)+1,$T$6:$U$19,2)) -> 45838 | T20: 12 | U20: 31
F21: Description | G21: Volume | H21: Price/Unit | J21: Sales
H22: ="("&Historical!$B$13&")" -> (IDR Million) | J22: ="("&Historical!$B$13&")" -> (IDR Million)
F23: Product A | G23: 10000 | H23: 14.3 | J23: =+G23*H23 -> 143000
F24: Product B | G24: 0 | H24: 0 | J24: =+G24*H24 -> 0
F25: Product C | G25: 0 | H25: 0 | J25: =+G25*H25 -> 0
F26: Product D | G26: 0 | H26: 0 | J26: =+G26*H26 -> 0
R27: =DATE(YEAR(R20),MONTH(R20)+1,VLOOKUP(MONTH(R20)+1,$T$6:$U$19,2)) -> 45869
F28: =DATE(YEAR(F15)+1,12,31) -> 46022 | G28: =+G15*(1+I28) -> 157300 | H28: Growth (%) | I28: =+(SUM(J33:J36)-G15)/G15 -> 0.19166667 | J28: dari | K28: =+F15 -> 45657 | R28: =DATE(YEAR(R27),MONTH(R27)+1,VLOOKUP(MONTH(R27)+1,$T$6:$U$19,2)) -> 45900
F29: Reason of assumptions : | R29: =DATE(YEAR(R28),MONTH(R28)+1,VLOOKUP(MONTH(R28)+1,$T$6:$U$19,2)) -> 45930
R30: =DATE(YEAR(R29),MONTH(R29)+1,VLOOKUP(MONTH(R29)+1,$T$6:$U$19,2)) -> 45961
F31: Description | G31: Volume | H31: Price/Unit | J31: Sales
H32: ="("&Historical!$B$13&")" -> (IDR Million) | J32: ="("&Historical!$B$13&")" -> (IDR Million)
F33: Product A | G33: 11000 | H33: 14.3 | J33: =+G33*H33 -> 157300
F34: Product B | G34: 0 | H34: 0 | J34: =+G34*H34 -> 0
F35: Product C | G35: 0 | H35: 0 | J35: =+G35*H35 -> 0
F36: Product D | G36: 0 | H36: 0 | J36: =+G36*H36 -> 0
R37: =DATE(YEAR(R30),MONTH(R30)+1,VLOOKUP(MONTH(R30)+1,$T$6:$U$19,2)) -> 45991
F38: =DATE(YEAR(F28)+1,12,31) -> 46387 | G38: =+G28*(1+I38) -> 173030 | H38: Growth (%) | I38: =+(SUM(J43:J46)-G28)/G28 -> 0.1 | J38: dari | K38: =+F28 -> 46022 | R38: =DATE(YEAR(R37),MONTH(R37)+1,VLOOKUP(MONTH(R37)+1,$T$6:$U$19,2)) -> 46021
F39: Reason of assumptions : | R39: =DATE(YEAR(R38),MONTH(R38)+1,VLOOKUP(MONTH(R38)+1,$T$6:$U$19,2)) -> 46052
R40: =DATE(YEAR(R39),MONTH(R39)+1,VLOOKUP(MONTH(R39)+1,$T$6:$U$19,2)) -> 46081
F41: Description | G41: Volume | H41: Price/Unit | J41: Sales
H42: ="("&Historical!$B$13&")" -> (IDR Million) | J42: ="("&Historical!$B$13&")" -> (IDR Million)
F43: Product A | G43: 11000 | H43: 15.73 | J43: =+G43*H43 -> 173030
F44: Product B | G44: 0 | H44: 0 | J44: =+G44*H44 -> 0
F45: Product C | G45: 0 | H45: 0 | J45: =+G45*H45 -> 0
F46: Product D | G46: 0 | H46: 0 | J46: =+G46*H46 -> 0
R47: =DATE(YEAR(R40),MONTH(R40)+1,VLOOKUP(MONTH(R40)+1,$T$6:$U$19,2)) -> 46112
F48: =DATE(YEAR(F38)+1,12,31) -> 46752 | G48: =+G38*(1+I48) -> 190333 | H48: Growth (%) | I48: =+(SUM(J53:J56)-G38)/G38 -> 0.1 | J48: dari | K48: =+F38 -> 46387
F49: Reason of assumptions :
F51: Description | G51: Volume | H51: Price/Unit | J51: Sales
H52: ="("&Historical!$B$13&")" -> (IDR Million) | J52: ="("&Historical!$B$13&")" -> (IDR Million)
F53: Product A | G53: 12100 | H53: 15.73 | J53: =+G53*H53 -> 190333
F54: Product B | G54: 0 | H54: 0 | J54: =+G54*H54 -> 0
F55: Product C | G55: 0 | H55: 0 | J55: =+G55*H55 -> 0
F56: Product D | G56: 0 | H56: 0 | J56: =+G56*H56 -> 0
F58: =DATE(YEAR(F48)+1,12,31) -> 47118 | G58: =+G48*(1+I58) -> 209366.3 | H58: Growth (%) | I58: =+(SUM(J63:J66)-G48)/G48 -> 0.1 | J58: dari | K58: =+F48 -> 46752
F59: Reason of assumptions :
F61: Description | G61: Volume | H61: Price/Unit | J61: Sales
H62: ="("&Historical!$B$13&")" -> (IDR Million) | J62: ="("&Historical!$B$13&")" -> (IDR Million)
F63: Product A | G63: 13310 | H63: 15.73 | J63: =+G63*H63 -> 209366.3
F64: Product B | G64: 0 | H64: 0 | J64: =+G64*H64 -> 0
F65: Product C | G65: 0 | H65: 0 | J65: =+G65*H65 -> 0
F66: Product D | G66: 0 | H66: 0 | J66: =+G66*H66 -> 0
F68: =DATE(YEAR(F58)+1,12,31) -> 47483 | G68: =+G58*(1+I68) -> 209366.3 | H68: Growth (%) | I68: 0 | J68: dari | K68: =+F58 -> 47118
F69: Alasan asumsi :
F73: Proyeksi | G73: =+G8 -> IDR Million | H73: Growth (%)
F74: =DATE(YEAR(F68)+1,12,31) -> 47848 | G74: =+G68*(1+H74) -> 209366.3 | H74: 0
F75: =DATE(YEAR(F74)+1,12,31) -> 48213 | G75: =+G74*(1+H75) -> 209366.3 | H75: 0
F76: =DATE(YEAR(F75)+1,12,31) -> 48579 | G76: =+G75*(1+H76) -> 209366.3 | H76: 0
F77: =DATE(YEAR(F76)+1,12,31) -> 48944 | G77: =+G76*(1+H77) -> 209366.3 | H77: 0
F79: Alasan asumsi proyeksi penjualan untuk periode | H79: =+F74 -> 47848 | I79: s. d. | J79: =+F77 -> 48944 | K79: :
F82: Profile of Other (Income) / Expense compare to Sales :
F83: Realization: | G83: % | K83: Period (year) | L83: Unit | M83: Amount
F84: =+F9 -> 44561 | G84: =+IF(Historical!E13=0,"",Historical!F115/100) -> 0.0001 | I84: assumption taken | K84: =+K127 -> 2024 | L84: dlm %-tase | M84: -0.005
F85: =+F10 -> 44926 | G85: =+IF(Historical!G13=0,"",Historical!H115/100) -> -0.0001 | K85: =+K128 -> 2025 | L85: dlm %-tase | M85: -0.005
F86: =+F11 -> 45291 | G86: =+IF(Historical!I13=0,"",Historical!J115/100) -> 0.0001 | K86: =+K129 -> 2026 | L86: dlm %-tase | M86: -0.005
F87: =+F12 -> 45473 | G87: =+Historical!L115/100 -> -0.0001 | K87: =+K130 -> 2027 | L87: dlm %-tase | M87: -0.005
F88: Average | G88: =+AVERAGE(G84:G87) -> 0 | K88: =+K131 -> 2028 | L88: dlm %-tase | M88: -0.005 | AA88: Kebutuhan KMK | AF88: Kebutuhan LC
K89: =+K132 -> 2029 | L89: dlm %-tase | M89: -0.0042466174
K90: =+K89+1 -> 2030 | L90: dlm %-tase | M90: -0.0042466174
K91: =+K90+1 -> 2031 | L91: dlm %-tase | M91: -0.0042466174
K92: =+K91+1 -> 2032 | L92: dlm %-tase | M92: -0.0042466174
K93: =+K92+1 -> 2033 | L93: dlm %-tase | M93: -0.0042466174
AA94: 2018 | AF94: 2018
D95: 2 | E95: Sales Schedule Projection (Monthly) :
F96: Januari (%) | G96: 0.1
F97: Februari (%) | G97: 0.08 | AA97: =DATE(2018,1,31) -> 43131 | AB97: =+CF!I96 -> 2003 | AC97: =+AB97/13600 -> 0.14727941 | AE97: =DATE(2018,1,31) -> 43131 | AF97: =+CF!I99 -> 2203 | AG97: =+AF97/13600 -> 0.16198529
F98: Maret (%) | G98: 0.06 | AA98: =+AA97+28 -> 43159 | AB98: =+CF!J$96 -> 2003 | AC98: =+AB98/13600 -> 0.14727941 | AE98: =+AE97+28 -> 43159 | AF98: =+CF!J$99 -> 2203 | AG98: =+AF98/13600 -> 0.16198529
F99: April (%) | G99: 0.08 | AA99: =+AA98+31 -> 43190 | AB99: =+CF!K$96 -> 2003 | AC99: =+AB99/13600 -> 0.14727941 | AE99: =+AE98+31 -> 43190 | AF99: =+CF!K$99 -> 2203 | AG99: =+AF99/13600 -> 0.16198529
F100: Mei (%) | G100: 0.1 | AA100: =+AA99+30 -> 43220 | AB100: =+CF!L$96 -> 2003 | AC100: =+AB100/13600 -> 0.14727941 | AE100: =+AE99+30 -> 43220 | AF100: =+CF!L$99 -> 2203 | AG100: =+AF100/13600 -> 0.16198529
F101: Juni (%) | G101: 0.08 | AA101: =+AA100+31 -> 43251 | AB101: =+CF!M$96 -> 2003 | AC101: =+AB101/13600 -> 0.14727941 | AE101: =+AE100+31 -> 43251 | AF101: =+CF!M$99 -> 2203 | AG101: =+AF101/13600 -> 0.16198529
F102: Juli (%) | G102: 0.08 | AA102: =+AA101+30 -> 43281 | AB102: =+CF!N$96 -> 2003 | AC102: =+AB102/13600 -> 0.14727941 | AE102: =+AE101+30 -> 43281 | AF102: =+CF!N$99 -> 2203 | AG102: =+AF102/13600 -> 0.16198529
F103: Agustus (%) | G103: 0.1 | AA103: =+AA102+31 -> 43312 | AB103: =+CF!O$96 -> 49503.236 | AC103: =+AB103/13600 -> 3.6399438 | AE103: =+AE102+31 -> 43312 | AF103: =+CF!O$99 -> 1652.25 | AG103: =+AF103/13600 -> 0.12148897
F104: September (%) | G104: 0.08 | AA104: =+AA103+31 -> 43343 | AB104: =+CF!P$96 -> 52722.671 | AC104: =+AB104/13600 -> 3.876667 | AE104: =+AE103+31 -> 43343 | AF104: =+CF!P$99 -> 1101.5 | AG104: =+AF104/13600 -> 0.080992647
F105: Oktober (%) | G105: 0.06 | AA105: =+AA104+30 -> 43373 | AB105: =+CF!Q$96 -> 56748.794 | AC105: =+AB105/13600 -> 4.1727055 | AE105: =+AE104+30 -> 43373 | AF105: =+CF!Q$99 -> 550.75 | AG105: =+AF105/13600 -> 0.040496324
F106: Nopember (%) | G106: 0.08 | AA106: =+AA105+31 -> 43404 | AB106: =+CF!R$96 -> 60575.961 | AC106: =+AB106/13600 -> 4.4541148 | AE106: =+AE105+31 -> 43404 | AF106: =+CF!R$99 -> 0 | AG106: =+AF106/13600 -> 0
F107: Desember (%) | G107: 0.1 | I107: =+IF(G107<0,"Input kembali proporsi penjualan per-bulan, posisi Des min 0,00%","") | AA107: =+AA106+30 -> 43434 | AB107: =+CF!S$96 -> 63374.888 | AC107: =+AB107/13600 -> 4.6599182 | AE107: =+AE106+30 -> 43434 | AF107: =+CF!R$99 -> 0 | AG107: =+AF107/13600 -> 0
F108: Total | G108: =+SUM(G96:G107) -> 1 | AA108: =+AA107+31 -> 43465 | AB108: =+CF!T$96 -> 67798.131 | AC108: =+AB108/13600 -> 4.9851567 | AE108: =+AE107+31 -> 43465 | AF108: =+CF!S$99 -> 0 | AG108: =+AF108/13600 -> 0
E110: Purchase Schedule Projection (Monthly) :
F111: Januari (%) | G111: 0.08 | AB111: 2018 | AC111: =+AB111+1 -> 2019 | AD111: =+AC111+1 -> 2020 | AE111: =+AD111+1 -> 2021 | AF111: =+AE111+1 -> 2022
F112: Februari (%) | G112: 0.06
F113: Maret (%) | G113: 0.08 | AA113: CR | AB113: =+Projection!L100 -> 0.49057441 | AC113: =+Projection!N100 -> 0.67223334 | AD113: =+Projection!P100 -> 0.96644035 | AE113: =+Projection!R100 -> 1.7315876 | AF113: =+Projection!T100 -> 3.1083879
F114: April (%) | G114: 0.1
F115: Mei (%) | G115: 0.1
F116: Juni (%) | G116: 0.08
...

Sheet CF
I1: =+I96/13600 -> 0.14727941
I3: =+IF(G19=0,1,G19) -> 4 | V3: =+I3 -> 4 | AI3: =+V3 -> 4 | AV3: =+AI3 -> 4 | BI3: =+AV3 -> 4 | BV3: =+BI3 -> 4 | CI3: =+BV3 -> 4 | CV3: =+CI3 -> 4 | DI3: =+CV3 -> 4 | DV3: =+DI3 -> 4
I4: =+IF(I10=0,0,1) -> 0 | J4: =+IF(J10=0,0,1) -> 0 | K4: =+IF(K10=0,0,1) -> 0 | L4: =+IF(L10=0,0,1) -> 0 | M4: =+IF(M10=0,0,1) -> 0 | N4: =+IF(N10=0,0,1) -> 0 | O4: =+IF(O10=0,0,1) -> 1 | P4: =+IF(P10=0,0,1) -> 1 | ... T4: =+IF(T10=0,0,1) -> 1 | V4: =+IF(V10=0,0,1) -> 1 | W4: =+IF(W10=0,0,1) -> 1 | X4: =+IF(X10=0,0,1) -> 1 | Y4: =+IF(Y10=0,0,1) -> 1 | Z4: =+IF(Z10=0,0,1) -> 1 | AA4: =+IF(AA10=0,0,1) -> 1 | AB4: =+IF(AB10=0,0,1) -> 1 | AC4: =+IF(AC10=0,0,1) -> 1 | ... AG4: =+IF(AG10=0,0,1) -> 1 | AI4: =+IF(AI10=0,0,1) -> 1 | AJ4: =+IF(AJ10=0,0,1) -> 1 | AK4: =+IF(AK10=0,0,1) -> 1 | AL4: =+IF(AL10=0,0,1) -> 1 | AM4: =+IF(AM10=0,0,1) -> 1 | AN4: =+IF(AN10=0,0,1) -> 1 | AO4: =+IF(AO10=0,0,1) -> 1 | AP4: =+IF(AP10=0,0,1) -> 1 | ... AT4: =+IF(AT10=0,0,1) -> 1 | AV4: =+IF(AV10=0,0,1) -> 1 | AW4: =+IF(AW10=0,0,1) -> 1 | AX4: =+IF(AX10=0,0,1) -> 1 | AY4: =+IF(AY10=0,0,1) -> 1 | AZ4: =+IF(AZ10=0,0,1) -> 1 | BA4: =+IF(BA10=0,0,1) -> 1 | BB4: =+IF(BB10=0,0,1) -> 1 | BC4: =+IF(BC10=0,0,1) -> 1 | ... BG4: =+IF(BG10=0,0,1) -> 1 | BI4: =+IF(BI10=0,0,1) -> 1 | BJ4: =+IF(BJ10=0,0,1) -> 1 | BK4: =+IF(BK10=0,0,1) -> 1 | BL4: =+IF(BL10=0,0,1) -> 1 | BM4: =+IF(BM10=0,0,1) -> 1 | BN4: =+IF(BN10=0,0,1) -> 1 | BO4: =+IF(BO10=0,0,1) -> 1 | BP4: =+IF(BP10=0,0,1) -> 1 | ... BT4: =+IF(BT10=0,0,1) -> 1 | BV4: =+IF(BV10=0,0,1) -> 1 | BW4: =+IF(BW10=0,0,1) -> 1 | BX4: =+IF(BX10=0,0,1) -> 1 | BY4: =+IF(BY10=0,0,1) -> 1 | BZ4: =+IF(BZ10=0,0,1) -> 1 | CA4: =+IF(CA10=0,0,1) -> 1 | CB4: =+IF(CB10=0,0,1) -> 1 | CC4: =+IF(CC10=0,0,1) -> 1 | ... CG4: =+IF(CG10=0,0,1) -> 1 | CI4: =+IF(CI10=0,0,1) -> 1 | CJ4: =+IF(CJ10=0,0,1) -> 1 | CK4: =+IF(CK10=0,0,1) -> 1 | CL4: =+IF(CL10=0,0,1) -> 1 | CM4: =+IF(CM10=0,0,1) -> 1 | CN4: =+IF(CN10=0,0,1) -> 1 | CO4: =+IF(CO10=0,0,1) -> 1 | CP4: =+IF(CP10=0,0,1) -> 1 | ... CT4: =+IF(CT10=0,0,1) -> 1 | CV4: =+IF(CV10=0,0,1) -> 1 | CW4: =+IF(CW10=0,0,1) -> 1 | CX4: =+IF(CX10=0,0,1) -> 1 | CY4: =+IF(CY10=0,0,1) -> 1 | CZ4: =+IF(CZ10=0,0,1) -> 1 | DA4: =+IF(DA10=0,0,1) -> 1 | DB4: =+IF(DB10=0,0,1) -> 1 | DC4: =+IF(DC10=0,0,1) -> 1 | ... DG4: =+IF(DG10=0,0,1) -> 1 | DI4: =+IF(DI10=0,0,1) -> 1 | DJ4: =+IF(DJ10=0,0,1) -> 1 | DK4: =+IF(DK10=0,0,1) -> 1 | DL4: =+IF(DL10=0,0,1) -> 1 | DM4: =+IF(DM10=0,0,1) -> 1 | DN4: =+IF(DN10=0,0,1) -> 1 | DO4: =+IF(DO10=0,0,1) -> 1 | DP4: =+IF(DP10=0,0,1) -> 1 | ... DT4: =+IF(DT10=0,0,1) -> 1 | DV4: =+IF(DV10=0,0,1) -> 1 | DW4: =+IF(DW10=0,0,1) -> 1 | DX4: =+IF(DX10=0,0,1) -> 1 | DY4: =+IF(DY10=0,0,1) -> 1 | DZ4: =+IF(DZ10=0,0,1) -> 1 | EA4: =+IF(EA10=0,0,1) -> 1 | EB4: =+IF(EB10=0,0,1) -> 1 | EC4: =+IF(EC10=0,0,1) -> 1 | ... EG4: =+IF(EG10=0,0,1) -> 1
I5: =+I4 -> 0 | J5: =+SUM($I$4:J4) -> 0 | K5: =+SUM($I$4:K4) -> 0 | L5: =+SUM($I$4:L4) -> 0 | M5: =+SUM($I$4:M4) -> 0 | N5: =+SUM($I$4:N4) -> 0 | O5: =+SUM($I$4:O4) -> 1 | P5: =+SUM($I$4:P4) -> 2 | Q5: =+SUM($I$4:Q4) -> 3 | ... T5: =+SUM($I$4:T4) -> 6 | V5: =+V4 -> 1 | W5: =+V5+1 -> 2 | X5: =+W5+1 -> 3 | Y5: =+X5+1 -> 4 | Z5: =+Y5+1 -> 5 | AA5: =+Z5+1 -> 6 | AB5: =+AA5+1 -> 7 | AC5: =+AB5+1 -> 8 | AD5: =+AC5+1 -> 9 | ... AG5: =+AF5+1 -> 12 | AI5: =+AI4 -> 1 | AJ5: =+AI5+1 -> 2 | AK5: =+AJ5+1 -> 3 | AL5: =+AK5+1 -> 4 | AM5: =+AL5+1 -> 5 | AN5: =+AM5+1 -> 6 | AO5: =+AN5+1 -> 7 | AP5: =+AO5+1 -> 8 | AQ5: =+AP5+1 -> 9 | ... AT5: =+AS5+1 -> 12 | AV5: =+AV4 -> 1 | AW5: =+AV5+1 -> 2 | AX5: =+AW5+1 -> 3 | AY5: =+AX5+1 -> 4 | AZ5: =+AY5+1 -> 5 | BA5: =+AZ5+1 -> 6 | BB5: =+BA5+1 -> 7 | BC5: =+BB5+1 -> 8 | BD5: =+BC5+1 -> 9 | ... BG5: =+BF5+1 -> 12 | BI5: =+BI4 -> 1 | BJ5: =+BI5+1 -> 2 | BK5: =+BJ5+1 -> 3 | BL5: =+BK5+1 -> 4 | BM5: =+BL5+1 -> 5 | BN5: =+BM5+1 -> 6 | BO5: =+BN5+1 -> 7 | BP5: =+BO5+1 -> 8 | BQ5: =+BP5+1 -> 9 | ... BT5: =+BS5+1 -> 12 | BV5: =+BV4 -> 1 | BW5: =+BV5+1 -> 2 | BX5: =+BW5+1 -> 3 | BY5: =+BX5+1 -> 4 | BZ5: =+BY5+1 -> 5 | CA5: =+BZ5+1 -> 6 | CB5: =+CA5+1 -> 7 | CC5: =+CB5+1 -> 8 | CD5: =+CC5+1 -> 9 | ... CG5: =+CF5+1 -> 12 | CI5: =+CI4 -> 1 | CJ5: =+CI5+1 -> 2 | CK5: =+CJ5+1 -> 3 | CL5: =+CK5+1 -> 4 | CM5: =+CL5+1 -> 5 | CN5: =+CM5+1 -> 6 | CO5: =+CN5+1 -> 7 | CP5: =+CO5+1 -> 8 | CQ5: =+CP5+1 -> 9 | ... CT5: =+CS5+1 -> 12 | CV5: =+CV4 -> 1 | CW5: =+CV5+1 -> 2 | CX5: =+CW5+1 -> 3 | CY5: =+CX5+1 -> 4 | CZ5: =+CY5+1 -> 5 | DA5: =+CZ5+1 -> 6 | DB5: =+DA5+1 -> 7 | DC5: =+DB5+1 -> 8 | DD5: =+DC5+1 -> 9 | ... DG5: =+DF5+1 -> 12 | DI5: =+DI4 -> 1 | DJ5: =+DI5+1 -> 2 | DK5: =+DJ5+1 -> 3 | DL5: =+DK5+1 -> 4 | DM5: =+DL5+1 -> 5 | DN5: =+DM5+1 -> 6 | DO5: =+DN5+1 -> 7 | DP5: =+DO5+1 -> 8 | DQ5: =+DP5+1 -> 9 | ... DT5: =+DS5+1 -> 12 | DV5: =+DV4 -> 1 | DW5: =+DV5+1 -> 2 | DX5: =+DW5+1 -> 3 | DY5: =+DX5+1 -> 4 | DZ5: =+DY5+1 -> 5 | EA5: =+DZ5+1 -> 6 | EB5: =+EA5+1 -> 7 | EC5: =+EB5+1 -> 8 | ED5: =+EC5+1 -> 9 | ... EG5: =+EF5+1 -> 12
E6: =+Historical!B3 -> Generic Niaga / Generic Group | I6: C A S H F L O W P R O J E C T I O N | V6: P R O Y E K S I C A S H F L O W | AI6: P R O Y E K S I C A S H F L O W | AV6: P R O Y E K S I C A S H F L O W | BI6: P R O Y E K S I C A S H F L O W | BV6: P R O Y E K S I C A S H F L O W | CI6: P R O Y E K S I C A S H F L O W | CV6: P R O Y E K S I C A S H F L O W | DI6: P R O Y E K S I C A S H F L O W | DV6: P R O Y E K S I C A S H F L O W
E7: =+Historical!B13 -> IDR Million
F8: Date/Month/Year : | G8: Assumption | H8: Current Post | I8: =IF(MONTH(Historical!K13)=12,DATE(YEAR(Historical!K13),MONTH(Historical!K13)+1,31),DATE(YEAR(Historical!I13),MONTH(Historical!I13)+1,31)) -> 45322 | J8: =+IF(MOD(YEAR(I8),4)=0,I8+29,I8+28) -> 45351 | K8: =DATE(YEAR(J8),MONTH(J8)+1,31) -> 45382 | L8: =DATE(YEAR(K8),MONTH(K8)+1,30) -> 45412 | M8: =DATE(YEAR(L8),MONTH(L8)+1,31) -> 45443 | N8: =DATE(YEAR(M8),MONTH(M8)+1,30) -> 45473 | O8: =DATE(YEAR(N8),MONTH(N8)+1,31) -> 45504 | P8: =DATE(YEAR(O8),MONTH(O8)+1,31) -> 45535 | Q8: =DATE(YEAR(P8),MONTH(P8)+1,30) -> 45565 | R8: =DATE(YEAR(Q8),MONTH(Q8)+1,31) -> 45596 | S8: =DATE(YEAR(R8),MONTH(R8)+1,30) -> 45626 | T8: =DATE(YEAR(S8),MONTH(S8)+1,31) -> 45657 | U8: TOTAL | V8: =DATE(YEAR(T8),MONTH(T8)+1,31) -> 45688 | W8: =+IF(MOD(YEAR(V8),4)=0,V8+29,V8+28) -> 45716 | X8: =DATE(YEAR(W8),MONTH(W8)+1,31) -> 45747 | Y8: =DATE(YEAR(X8),MONTH(X8)+1,30) -> 45777 | Z8: =DATE(YEAR(Y8),MONTH(Y8)+1,31) -> 45808 | AA8: =DATE(YEAR(Z8),MONTH(Z8)+1,30) -> 45838 | AB8: =DATE(YEAR(AA8),MONTH(AA8)+1,31) -> 45869 | AC8: =DATE(YEAR(AB8),MONTH(AB8)+1,31) -> 45900 | AD8: =DATE(YEAR(AC8),MONTH(AC8)+1,30) -> 45930 | AE8: =DATE(YEAR(AD8),MONTH(AD8)+1,31) -> 45961 | AF8: =DATE(YEAR(AE8),MONTH(AE8)+1,30) -> 45991 | AG8: =DATE(YEAR(AF8),MONTH(AF8)+1,31) -> 46022 | AH8: TOTAL | AI8: =DATE(YEAR(AG8),MONTH(AG8)+1,31) -> 46053 | AJ8: =+IF(MOD(YEAR(AI8),4)=0,AI8+29,AI8+28) -> 46081 | AK8: =DATE(YEAR(AJ8),MONTH(AJ8)+1,31) -> 46112 | AL8: =DATE(YEAR(AK8),MONTH(AK8)+1,30) -> 46142 | AM8: =DATE(YEAR(AL8),MONTH(AL8)+1,31) -> 46173 | AN8: =DATE(YEAR(AM8),MONTH(AM8)+1,30) -> 46203 | AO8: =DATE(YEAR(AN8),MONTH(AN8)+1,31) -> 46234 | AP8: =DATE(YEAR(AO8),MONTH(AO8)+1,31) -> 46265 | AQ8: =DATE(YEAR(AP8),MONTH(AP8)+1,30) -> 46295 | AR8: =DATE(YEAR(AQ8),MONTH(AQ8)+1,31) -> 46326 | AS8: =DATE(YEAR(AR8),MONTH(AR8)+1,30) -> 46356 | AT8: =DATE(YEAR(AS8),MONTH(AS8)+1,31) -> 46387 | AU8: TOTAL | AV8: =DATE(YEAR(AT8),MONTH(AT8)+1,31) -> 46418 | AW8: =+IF(MOD(YEAR(AV8),4)=0,AV8+29,AV8+28) -> 46446 | AX8: =DATE(YEAR(AW8),MONTH(AW8)+1,31) -> 46477 | AY8: =DATE(YEAR(AX8),MONTH(AX8)+1,30) -> 46507 | AZ8: =DATE(YEAR(AY8),MONTH(AY8)+1,31) -> 46538 | BA8: =DATE(YEAR(AZ8),MONTH(AZ8)+1,30) -> 46568 | BB8: =DATE(YEAR(BA8),MONTH(BA8)+1,31) -> 46599 | BC8: =DATE(YEAR(BB8),MONTH(BB8)+1,31) -> 46630 | BD8: =DATE(YEAR(BC8),MONTH(BC8)+1,30) -> 46660 | BE8: =DATE(YEAR(BD8),MONTH(BD8)+1,31) -> 46691 | BF8: =DATE(YEAR(BE8),MONTH(BE8)+1,30) -> 46721 | BG8: =DATE(YEAR(BF8),MONTH(BF8)+1,31) -> 46752 | BH8: TOTAL | BI8: =DATE(YEAR(BG8),MONTH(BG8)+1,31) -> 46783 | BJ8: =+IF(MOD(YEAR(BI8),4)=0,BI8+29,BI8+28) -> 46812 | BK8: =DATE(YEAR(BJ8),MONTH(BJ8)+1,31) -> 46843 | BL8: =DATE(YEAR(BK8),MONTH(BK8)+1,30) -> 46873 | BM8: =DATE(YEAR(BL8),MONTH(BL8)+1,31) -> 46904 | BN8: =DATE(YEAR(BM8),MONTH(BM8)+1,30) -> 46934 | BO8: =DATE(YEAR(BN8),MONTH(BN8)+1,31) -> 46965 | BP8: =DATE(YEAR(BO8),MONTH(BO8)+1,31) -> 46996 | BQ8: =DATE(YEAR(BP8),MONTH(BP8)+1,30) -> 47026 | BR8: =DATE(YEAR(BQ8),MONTH(BQ8)+1,31) -> 47057 | BS8: =DATE(YEAR(BR8),MONTH(BR8)+1,30) -> 47087 | BT8: =DATE(YEAR(BS8),MONTH(BS8)+1,31) -> 47118 | BU8: TOTAL | BV8: =DATE(YEAR(BT8),MONTH(BT8)+1,31) -> 47149 | BW8: =+IF(MOD(YEAR(BV8),4)=0,BV8+29,BV8+28) -> 47177 | BX8: =DATE(YEAR(BW8),MONTH(BW8)+1,31) -> 47208 | BY8: =DATE(YEAR(BX8),MONTH(BX8)+1,30) -> 47238 | BZ8: =DATE(YEAR(BY8),MONTH(BY8)+1,31) -> 47269 | CA8: =DATE(YEAR(BZ8),MONTH(BZ8)+1,30) -> 47299 | CB8: =DATE(YEAR(CA8),MONTH(CA8)+1,31) -> 47330 | CC8: =DATE(YEAR(CB8),MONTH(CB8)+1,31) -> 47361 | CD8: =DATE(YEAR(CC8),MONTH(CC8)+1,30) -> 47391 | CE8: =DATE(YEAR(CD8),MONTH(CD8)+1,31) -> 47422 | CF8: =DATE(YEAR(CE8),MONTH(CE8)+1,30) -> 47452 | CG8: =DATE(YEAR(CF8),MONTH(CF8)+1,31) -> 47483 | CH8: TOTAL | CI8: =DATE(YEAR(CG8),MONTH(CG8)+1,31) -> 47514 | CJ8: =+IF(MOD(YEAR(CI8),4)=0,CI8+29,CI8+28) -> 47542 | CK8: =DATE(YEAR(CJ8),MONTH(CJ8)+1,31) -> 47573 | CL8: =DATE(YEAR(CK8),MONTH(CK8)+1,30) -> 47603 | CM8: =DATE(YEAR(CL8),MONTH(CL8)+1,31) -> 47634 | CN8: =DATE(YEAR(CM8),MONTH(CM8)+1,30) -> 47664 | CO8: =DATE(YEAR(CN8),MONTH(CN8)+1,31) -> 47695 | CP8: =DATE(YEAR(CO8),MONTH(CO8)+1,31) -> 47726 | CQ8: =DATE(YEAR(CP8),MONTH(CP8)+1,30) -> 47756 | CR8: =DATE(YEAR(CQ8),MONTH(CQ8)+1,31) -> 47787 | CS8: =DATE(YEAR(CR8),MONTH(CR8)+1,30) -> 47817 | CT8: =DATE(YEAR(CS8),MONTH(CS8)+1,31) -> 47848 | CU8: TOTAL | CV8: =DATE(YEAR(CT8),MONTH(CT8)+1,31) -> 47879 | CW8: =+IF(MOD(YEAR(CV8),4)=0,CV8+29,CV8+28) -> 47907 | CX8: =DATE(YEAR(CW8),MONTH(CW8)+1,31) -> 47938 | CY8: =DATE(YEAR(CX8),MONTH(CX8)+1,30) -> 47968 | CZ8: =DATE(YEAR(CY8),MONTH(CY8)+1,31) -> 47999 | DA8: =DATE(YEAR(CZ8),MONTH(CZ8)+1,30) -> 48029 | DB8: =DATE(YEAR(DA8),MONTH(DA8)+1,31) -> 48060 | DC8: =DATE(YEAR(DB8),MONTH(DB8)+1,31) -> 48091 | DD8: =DATE(YEAR(DC8),MONTH(DC8)+1,30) -> 48121 | DE8: =DATE(YEAR(DD8),MONTH(DD8)+1,31) -> 48152 | DF8: =DATE(YEAR(DE8),MONTH(DE8)+1,30) -> 48182 | DG8: =DATE(YEAR(DF8),MONTH(DF8)+1,31) -> 48213 | DH8: TOTAL | DI8: =DATE(YEAR(DG8),MONTH(DG8)+1,31) -> 48244 | DJ8: =+IF(MOD(YEAR(DI8),4)=0,DI8+29,DI8+28) -> 48273 | DK8: =DATE(YEAR(DJ8),MONTH(DJ8)+1,31) -> 48304 | DL8: =DATE(YEAR(DK8),MONTH(DK8)+1,30) -> 48334 | DM8: =DATE(YEAR(DL8),MONTH(DL8)+1,31) -> 48365 | DN8: =DATE(YEAR(DM8),MONTH(DM8)+1,30) -> 48395 | DO8: =DATE(YEAR(DN8),MONTH(DN8)+1,31) -> 48426 | DP8: =DATE(YEAR(DO8),MONTH(DO8)+1,31) -> 48457 | DQ8: =DATE(YEAR(DP8),MONTH(DP8)+1,30) -> 48487 | DR8: =DATE(YEAR(DQ8),MONTH(DQ8)+1,31) -> 48518 | DS8: =DATE(YEAR(DR8),MONTH(DR8)+1,30) -> 48548 | DT8: =DATE(YEAR(DS8),MONTH(DS8)+1,31) -> 48579 | DU8: TOTAL | DV8: =DATE(YEAR(DT8),MONTH(DT8)+1,31) -> 48610 | DW8: =+IF(MOD(YEAR(DV8),4)=0,DV8+29,DV8+28) -> 48638 | DX8: =DATE(YEAR(DW8),MONTH(DW8)+1,31) -> 48669 | DY8: =DATE(YEAR(DX8),MONTH(DX8)+1,30) -> 48699 | DZ8: =DATE(YEAR(DY8),MONTH(DY8)+1,31) -> 48730 | EA8: =DATE(YEAR(DZ8),MONTH(DZ8)+1,30) -> 48760 | EB8: =DATE(YEAR(EA8),MONTH(EA8)+1,31) -> 48791 | EC8: =DATE(YEAR(EB8),MONTH(EB8)+1,31) -> 48822 | ED8: =DATE(YEAR(EC8),MONTH(EC8)+1,30) -> 48852 | EE8: =DATE(YEAR(ED8),MONTH(ED8)+1,31) -> 48883 | EF8: =DATE(YEAR(EE8),MONTH(EE8)+1,30) -> 48913 | EG8: =DATE(YEAR(EF8),MONTH(EF8)+1,31) -> 48944 | EH8: TOTAL
D9: 1 | F9: BEGINNING CASH BALANCE | H9: =Historical!K16 -> 103 | I9: =Historical!K16 -> 103 | J9: =+I81 -> -15910.769 | K9: =+J81 -> -15924.538 | L9: =+K81 -> -15938.306 | M9: =L81 -> -15952.075 | N9: =M81 -> -15965.844 | O9: =N81 -> -15979.612 | P9: =O81 -> 500 | Q9: =P81 -> 500 | R9: =Q81 -> 500 | S9: =R81 -> 500 | T9: =S81 -> 500 | V9: =T81 -> 500 | W9: =V81 -> 500 | X9: =W81 -> 500 | Y9: =X81 -> 500 | Z9: =Y81 -> 500 | AA9: =Z81 -> 500 | AB9: =AA81 -> 500 | AC9: =AB81 -> 500 | AD9: =AC81 -> 500 | ... AG9: =AF81 -> 500 | AI9: =AG81 -> 500 | AJ9: =AI81 -> 500 | AK9: =AJ81 -> 500 | AL9: =AK81 -> 500 | AM9: =AL81 -> 500 | AN9: =AM81 -> 500 | AO9: =AN81 -> 500 | AP9: =AO81 -> 500 | AQ9: =AP81 -> 500 | ... AT9: =AS81 -> 500 | AV9: =AT81 -> 500 | AW9: =AV81 -> 500 | AX9: =AW81 -> 500 | AY9: =AX81 -> 500 | AZ9: =AY81 -> 500 | BA9: =AZ81 -> 500 | BB9: =BA81 -> 500 | BC9: =BB81 -> 500 | BD9: =BC81 -> 500 | ... BG9: =BF81 -> 500 | BI9: =BG81 -> 500 | BJ9: =BI81 -> 500 | BK9: =BJ81 -> 500 | BL9: =BK81 -> 500 | BM9: =BL81 -> 500 | BN9: =BM81 -> 1251.0489 | BO9: =BN81 -> 3904.8579 | BP9: =BO81 -> 6503.7059 | BQ9: =BP81 -> 9494.5493 | ... BT9: =BS81 -> 13635.093 | BV9: =BT81 -> 19821.24 | BW9: =BV81 -> 49702.374 | BX9: =BW81 -> 53862.226 | BY9: =BX81 -> 55689.263 | BZ9: =BY81 -> 56521.391 | CA9: =BZ81 -> 59253.945 | CB9: =CA81 -> 60782.235 | CC9: =CB81 -> 62325.598 | CD9: =CC81 -> 64911.193 | ... CG9: =CF81 -> 65912.312 | CI9: =CG81 -> 71103.487 | CJ9: =CI81 -> 21164.558 | CK9: =CJ81 -> 29647.983 | CL9: =CK81 -> 36036.712 | CM9: =CL81 -> 35934.444 | CN9: =CM81 -> 35505.592 | CO9: =CN81 -> 36510.341 | CP9: =CO81 -> 37439.989 | CQ9: =CP81 -> 37743.369 | ... CT9: =CS81 -> 37824.268 | CV9: =CT81 -> 41368.087 | CW9: =CV81 -> 30880.049 | CX9: =CW81 -> 39363.474 | CY9: =CX81 -> 45752.204 | CZ9: =CY81 -> 45649.936 | DA9: =CZ81 -> 45221.084 | DB9: =DA81 -> 46225.833 | DC9: =DB81 -> 47155.481 | DD9: =DC81 -> 47458.861 | ... DG9: =DF81 -> 47539.76 | DI9: =DG81 -> 51083.579 | DJ9: =DI81 -> 40595.541 | DK9: =DJ81 -> 49078.966 | DL9: =DK81 -> 55467.696 | DM9: =DL81 -> 55365.427 | DN9: =DM81 -> 54936.575 | DO9: =DN81 -> 55941.324 | DP9: =DO81 -> 56870.973 | DQ9: =DP81 -> 57174.353 | ... DT9: =DS81 -> 57255.251 | DV9: =DT81 -> 60799.07 | DW9: =DV81 -> 50311.033 | DX9: =DW81 -> 58794.458 | DY9: =DX81 -> 65183.187 | DZ9: =DY81 -> 65080.919 | EA9: =DZ81 -> 64652.067 | EB9: =EA81 -> 65656.816 | EC9: =EB81 -> 66586.465 | ED9: =EC81 -> 66889.844 | ... EG9: =EF81 -> 66970.743
D10: =D9+1 -> 2 | F10: Sales | I10: =+'Sales-AR Schedule'!D22 -> 0 | J10: =+'Sales-AR Schedule'!E22 -> 0 | K10: =+'Sales-AR Schedule'!F22 -> 0 | L10: =+'Sales-AR Schedule'!G22 -> 0 | M10: =+'Sales-AR Schedule'!H22 -> 0 | N10: =+'Sales-AR Schedule'!I22 -> 0 | O10: =+'Sales-AR Schedule'!J22 -> 320 | P10: =+'Sales-AR Schedule'!K22 -> 400 | ... T10: =+'Sales-AR Schedule'!O22 -> 400 | U10: =SUM(I10:T10) -> 2000 | V10: =+'Sales-AR Schedule'!D24 -> 15730 | W10: =+'Sales-AR Schedule'!E24 -> 12584 | X10: =+'Sales-AR Schedule'!F24 -> 9438 | Y10: =+'Sales-AR Schedule'!G24 -> 12584 | Z10: =+'Sales-AR Schedule'!H24 -> 15730 | AA10: =+'Sales-AR Schedule'!I24 -> 12584 | AB10: =+'Sales-AR Schedule'!J24 -> 12584 | AC10: =+'Sales-AR Schedule'!K24 -> 15730 | ... AG10: =+'Sales-AR Schedule'!O24 -> 15730 | AH10: =SUM(V10:AG10) -> 157300 | AI10: ='Sales-AR Schedule'!D26 -> 17303 | AJ10: ='Sales-AR Schedule'!E26 -> 13842.4 | AK10: ='Sales-AR Schedule'!F26 -> 10381.8 | AL10: ='Sales-AR Schedule'!G26 -> 13842.4 | AM10: ='Sales-AR Schedule'!H26 -> 17303 | AN10: ='Sales-AR Schedule'!I26 -> 13842.4 | AO10: ='Sales-AR Schedule'!J26 -> 13842.4 | AP10: ='Sales-AR Schedule'!K26 -> 17303 | ... AT10: ='Sales-AR Schedule'!O26 -> 17303 | AU10: =SUM(AI10:AT10) -> 173030 | AV10: ='Sales-AR Schedule'!D28 -> 19033.3 | AW10: ='Sales-AR Schedule'!E28 -> 15226.64 | AX10: ='Sales-AR Schedule'!F28 -> 11419.98 | AY10: ='Sales-AR Schedule'!G28 -> 15226.64 | AZ10: ='Sales-AR Schedule'!H28 -> 19033.3 | BA10: ='Sales-AR Schedule'!I28 -> 15226.64 | BB10: ='Sales-AR Schedule'!J28 -> 15226.64 | BC10: ='Sales-AR Schedule'!K28 -> 19033.3 | ... BG10: ='Sales-AR Schedule'!O28 -> 19033.3 | BH10: =SUM(AV10:BG10) -> 190333 | BI10: =+'Sales-AR Schedule'!D30 -> 20936.63 | BJ10: =+'Sales-AR Schedule'!E30 -> 16749.304 | BK10: =+'Sales-AR Schedule'!F30 -> 12561.978 | BL10: =+'Sales-AR Schedule'!G30 -> 16749.304 | BM10: =+'Sales-AR Schedule'!H30 -> 20936.63 | BN10: =+'Sales-AR Schedule'!I30 -> 16749.304 | BO10: =+'Sales-AR Schedule'!J30 -> 16749.304 | BP10: =+'Sales-AR Schedule'!K30 -> 20936.63 | ... BT10: =+'Sales-AR Schedule'!O30 -> 20936.63 | BU10: =SUM(BI10:BT10) -> 209366.3 | BV10: =+'Sales-AR Schedule'!D32 -> 20936.63 | BW10: =+'Sales-AR Schedule'!E32 -> 16749.304 | BX10: =+'Sales-AR Schedule'!F32 -> 12561.978 | BY10: =+'Sales-AR Schedule'!G32 -> 16749.304 | BZ10: =+'Sales-AR Schedule'!H32 -> 20936.63 | CA10: =+'Sales-AR Schedule'!I32 -> 16749.304 | CB10: =+'Sales-AR Schedule'!J32 -> 16749.304 | CC10: =+'Sales-AR Schedule'!K32 -> 20936.63 | ... CG10: =+'Sales-AR Schedule'!O32 -> 20936.63 | CH10: =SUM(BV10:CG10) -> 209366.3 | CI10: =+'Sales-AR Schedule'!D34 -> 20936.63 | CJ10: =+'Sales-AR Schedule'!E34 -> 16749.304 | CK10: =+'Sales-AR Schedule'!F34 -> 12561.978 | CL10: =+'Sales-AR Schedule'!G34 -> 16749.304 | CM10: =+'Sales-AR Schedule'!H34 -> 20936.63 | CN10: =+'Sales-AR Schedule'!I34 -> 16749.304 | CO10: =+'Sales-AR Schedule'!J34 -> 16749.304 | CP10: =+'Sales-AR Schedule'!K34 -> 20936.63 | ... CT10: =+'Sales-AR Schedule'!O34 -> 20936.63 | CU10: =SUM(CI10:CT10) -> 209366.3 | CV10: =+'Sales-AR Schedule'!D36 -> 20936.63 | CW10: =+'Sales-AR Schedule'!E36 -> 16749.304 | CX10: =+'Sales-AR Schedule'!F36 -> 12561.978 | CY10: =+'Sales-AR Schedule'!G36 -> 16749.304 | CZ10: =+'Sales-AR Schedule'!H36 -> 20936.63 | DA10: =+'Sales-AR Schedule'!I36 -> 16749.304 | DB10: =+'Sales-AR Schedule'!J36 -> 16749.304 | DC10: =+'Sales-AR Schedule'!K36 -> 20936.63 | ... DG10: =+'Sales-AR Schedule'!O36 -> 20936.63 | DH10: =SUM(CV10:DG10) -> 209366.3 | DI10: =+'Sales-AR Schedule'!D38 -> 20936.63 | DJ10: =+'Sales-AR Schedule'!E38 -> 16749.304 | DK10: =+'Sales-AR Schedule'!F38 -> 12561.978 | DL10: =+'Sales-AR Schedule'!G38 -> 16749.304 | DM10: =+'Sales-AR Schedule'!H38 -> 20936.63 | DN10: =+'Sales-AR Schedule'!I38 -> 16749.304 | DO10: =+'Sales-AR Schedule'!J38 -> 16749.304 | DP10: =+'Sales-AR Schedule'!K38 -> 20936.63 | ... DT10: =+'Sales-AR Schedule'!O38 -> 20936.63 | DU10: =SUM(DI10:DT10) -> 209366.3 | DV10: =+'Sales-AR Schedule'!D40 -> 20936.63 | DW10: =+'Sales-AR Schedule'!E40 -> 16749.304 | DX10: =+'Sales-AR Schedule'!F40 -> 12561.978 | DY10: =+'Sales-AR Schedule'!G40 -> 16749.304 | DZ10: =+'Sales-AR Schedule'!H40 -> 20936.63 | EA10: =+'Sales-AR Schedule'!I40 -> 16749.304 | EB10: =+'Sales-AR Schedule'!J40 -> 16749.304 | EC10: =+'Sales-AR Schedule'!K40 -> 20936.63 | ... EG10: =+'Sales-AR Schedule'!O40 -> 20936.63 | EH10: =SUM(DV10:EG10) -> 209366.3
D11: =D10+1 -> 3 | F11: (Account Receivables) | H11: =Historical!K19 -> 403 | I11: =+'Sales-AR Schedule'!D57 -> 0 | J11: =+'Sales-AR Schedule'!E57 -> 0 | K11: =+'Sales-AR Schedule'!F57 -> 0 | L11: =+'Sales-AR Schedule'!G57 -> 0 | M11: =+'Sales-AR Schedule'!H57 -> 0 | N11: =+'Sales-AR Schedule'!I57 -> 0 | O11: =+'Sales-AR Schedule'!J57 -> 27925.714 | P11: =+'Sales-AR Schedule'!K57 -> 24510 | ... T11: =+'Sales-AR Schedule'!O57 -> 16500 | U11: =T11 -> 16500 | V11: =+'Sales-AR Schedule'!D58 -> 23595 | W11: =+'Sales-AR Schedule'!E58 -> 21235.5 | X11: =+'Sales-AR Schedule'!F58 -> 18876 | Y11: =+'Sales-AR Schedule'!G58 -> 18876 | Z11: =+'Sales-AR Schedule'!H58 -> 19819.8 | AA11: =+'Sales-AR Schedule'!I58 -> 19662.5 | AB11: =+'Sales-AR Schedule'!J58 -> 19550.143 | AC11: =+'Sales-AR Schedule'!K58 -> 20055.75 | ... AG11: =+'Sales-AR Schedule'!O58 -> 19662.5 | AH11: =AG11 -> 19662.5 | AI11: ='Sales-AR Schedule'!D59 -> 25954.5 | AJ11: ='Sales-AR Schedule'!E59 -> 23359.05 | AK11: ='Sales-AR Schedule'!F59 -> 20763.6 | AL11: ='Sales-AR Schedule'!G59 -> 20763.6 | AM11: ='Sales-AR Schedule'!H59 -> 21801.78 | AN11: ='Sales-AR Schedule'!I59 -> 21628.75 | AO11: ='Sales-AR Schedule'!J59 -> 21505.157 | AP11: ='Sales-AR Schedule'!K59 -> 22061.325 | ... AT11: ='Sales-AR Schedule'!O59 -> 21628.75 | AU11: =AT11 -> 21628.75 | AV11: ='Sales-AR Schedule'!D60 -> 28549.95 | AW11: ='Sales-AR Schedule'!E60 -> 25694.955 | AX11: ='Sales-AR Schedule'!F60 -> 22839.96 | AY11: ='Sales-AR Schedule'!G60 -> 22839.96 | AZ11: ='Sales-AR Schedule'!H60 -> 23981.958 | BA11: ='Sales-AR Schedule'!I60 -> 23791.625 | BB11: ='Sales-AR Schedule'!J60 -> 23655.673 | BC11: ='Sales-AR Schedule'!K60 -> 24267.458 | ... BG11: ='Sales-AR Schedule'!O60 -> 23791.625 | BH11: =BG11 -> 23791.625 | BI11: =+'Sales-AR Schedule'!D61 -> 31404.945 | BJ11: =+'Sales-AR Schedule'!E61 -> 28264.451 | BK11: =+'Sales-AR Schedule'!F61 -> 25123.956 | BL11: =+'Sales-AR Schedule'!G61 -> 25123.956 | BM11: =+'Sales-AR Schedule'!H61 -> 26380.154 | BN11: =+'Sales-AR Schedule'!I61 -> 26170.788 | BO11: =+'Sales-AR Schedule'!J61 -> 26021.24 | BP11: =+'Sales-AR Schedule'!K61 -> 26694.203 | ... BT11: =+'Sales-AR Schedule'!O61 -> 26170.788 | BU11: =BT11 -> 26170.788 | BV11: =+'Sales-AR Schedule'!D62 -> 31404.945 | BW11: =+'Sales-AR Schedule'!E62 -> 28264.451 | BX11: =+'Sales-AR Schedule'!F62 -> 25123.956 | BY11: =+'Sales-AR Schedule'!G62 -> 25123.956 | BZ11: =+'Sales-AR Schedule'!H62 -> 26380.154 | CA11: =+'Sales-AR Schedule'!I62 -> 26170.788 | CB11: =+'Sales-AR Schedule'!J62 -> 26021.24 | CC11: =+'Sales-AR Schedule'!K62 -> 26694.203 | ... CG11: =+'Sales-AR Schedule'!O62 -> 26170.788 | CH11: =CG11 -> 26170.788 | CI11: =+'Sales-AR Schedule'!D63 -> 83746.52 | CJ11: =+'Sales-AR Schedule'!E63 -> 75371.868 | CK11: =+'Sales-AR Schedule'!F63 -> 66997.216 | CL11: =+'Sales-AR Schedule'!G63 -> 66997.216 | CM11: =+'Sales-AR Schedule'!H63 -> 70347.077 | CN11: =+'Sales-AR Schedule'!I63 -> 69788.767 | CO11: =+'Sales-AR Schedule'!J63 -> 69389.974 | CP11: =+'Sales-AR Schedule'!K63 -> 71184.542 | ... CT11: =+'Sales-AR Schedule'!O63 -> 69788.767 | CU11: =CT11 -> 69788.767 | CV11: =+'Sales-AR Schedule'!D64 -> 83746.52 | CW11: =+'Sales-AR Schedule'!E64 -> 75371.868 | CX11: =+'Sales-AR Schedule'!F64 -> 66997.216 | CY11: =+'Sales-AR Schedule'!G64 -> 66997.216 | CZ11: =+'Sales-AR Schedule'!H64 -> 70347.077 | DA11: =+'Sales-AR Schedule'!I64 -> 69788.767 | DB11: =+'Sales-AR Schedule'!J64 -> 69389.974 | DC11: =+'Sales-AR Schedule'!K64 -> 71184.542 | ... DG11: =+'Sales-AR Schedule'!O64 -> 69788.767 | DH11: =DG11 -> 69788.767 | DI11: =+'Sales-AR Schedule'!D65 -> 83746.52 | DJ11: =+'Sales-AR Schedule'!E65 -> 75371.868 | DK11: =+'Sales-AR Schedule'!F65 -> 66997.216 | DL11: =+'Sales-AR Schedule'!G65 -> 66997.216 | DM11: =+'Sales-AR Schedule'!H65 -> 70347.077 | DN11: =+'Sales-AR Schedule'!I65 -> 69788.767 | DO11: =+'Sales-AR Schedule'!J65 -> 69389.974 | DP11: =+'Sales-AR Schedule'!K65 -> 71184.542 | ... DT11: =+'Sales-AR Schedule'!O65 -> 69788.767 | DU11: =DT11 -> 69788.767 | DV11: =+'Sales-AR Schedule'!D66 -> 83746.52 | DW11: =+'Sales-AR Schedule'!E66 -> 75371.868 | DX11: =+'Sales-AR Schedule'!F66 -> 66997.216 | DY11: =+'Sales-AR Schedule'!G66 -> 66997.216 | DZ11: =+'Sales-AR Schedule'!H66 -> 70347.077 | EA11: =+'Sales-AR Schedule'!I66 -> 69788.767 | EB11: =+'Sales-AR Schedule'!J66 -> 69389.974 | EC11: =+'Sales-AR Schedule'!K66 -> 71184.542 | ... EG11: =+'Sales-AR Schedule'!O66 -> 69788.767 | EH11: =EG11 -> 69788.767
D12: =D11+1 -> 4 | F12: Collected Account Receivables | I12: =+H11+I10-I11 -> 403 | J12: =+I11+J10-J11 -> 0 | K12: =+J11+K10-K11 -> 0 | L12: =+K11+L10-L11 -> 0 | M12: =+L11+M10-M11 -> 0 | N12: =+M11+N10-N11 -> 0 | O12: =+N11+O10-O11 -> -27605.714 | P12: =+O11+P10-P11 -> 3815.7143 | ... T12: =+S11+T10-T11 -> 1845.4545 | U12: =SUM(I12:T12) -> -14097 | V12: =U11+V10-V11 -> 8635 | W12: =V11+W10-W11 -> 14943.5 | X12: =W11+X10-X11 -> 11797.5 | Y12: =X11+Y10-Y11 -> 12584 | Z12: =Y11+Z10-Z11 -> 14786.2 | AA12: =Z11+AA10-AA11 -> 12741.3 | AB12: =AA11+AB10-AB11 -> 12696.357 | AC12: =AB11+AC10-AC11 -> 15224.393 | ... AG12: =AF11+AG10-AG11 -> 15372.5 | AH12: =SUM(V12:AG12) -> 154137.5 | AI12: =AH11+AI10-AI11 -> 11011 | AJ12: =AI11+AJ10-AJ11 -> 16437.85 | AK12: =AJ11+AK10-AK11 -> 12977.25 | AL12: =AK11+AL10-AL11 -> 13842.4 | AM12: =AL11+AM10-AM11 -> 16264.82 | AN12: =AM11+AN10-AN11 -> 14015.43 | AO12: =AN11+AO10-AO11 -> 13965.993 | AP12: =AO11+AP10-AP11 -> 16746.832 | ... AT12: =AS11+AT10-AT11 -> 16909.75 | AU12: =SUM(AI12:AT12) -> 171063.75 | AV12: =AU11+AV10-AV11 -> 12112.1 | AW12: =AV11+AW10-AW11 -> 18081.635 | AX12: =AW11+AX10-AX11 -> 14274.975 | AY12: =AX11+AY10-AY11 -> 15226.64 | AZ12: =AY11+AZ10-AZ11 -> 17891.302 | BA12: =AZ11+BA10-BA11 -> 15416.973 | BB12: =BA11+BB10-BB11 -> 15362.592 | BC12: =BB11+BC10-BC11 -> 18421.515 | ... BG12: =BF11+BG10-BG11 -> 18600.725 | BH12: =SUM(AV12:BG12) -> 188170.12 | BI12: =BH11+BI10-BI11 -> 13323.31 | BJ12: =BI11+BJ10-BJ11 -> 19889.799 | BK12: =BJ11+BK10-BK11 -> 15702.473 | BL12: =BK11+BL10-BL11 -> 16749.304 | BM12: =BL11+BM10-BM11 -> 19680.432 | BN12: =BM11+BN10-BN11 -> 16958.67 | BO12: =BN11+BO10-BO11 -> 16898.851 | BP12: =BO11+BP10-BP11 -> 20263.667 | ... BT12: =BS11+BT10-BT11 -> 20460.798 | BU12: =SUM(BI12:BT12) -> 206987.14 | BV12: =BU11+BV10-BV11 -> 15702.473 | BW12: =BV11+BW10-BW11 -> 19889.799 | BX12: =BW11+BX10-BX11 -> 15702.473 | BY12: =BX11+BY10-BY11 -> 16749.304 | BZ12: =BY11+BZ10-BZ11 -> 19680.432 | CA12: =BZ11+CA10-CA11 -> 16958.67 | CB12: =CA11+CB10-CB11 -> 16898.851 | CC12: =CB11+CC10-CC11 -> 20263.667 | ... CG12: =CF11+CG10-CG11 -> 20460.798 | CH12: =SUM(BV12:CG12) -> 209366.3 | CI12: =CH11+CI10-CI11 -> -36639.103 | CJ12: =CI11+CJ10-CJ11 -> 25123.956 | CK12: =CJ11+CK10-CK11 -> 20936.63 | CL12: =CK11+CL10-CL11 -> 16749.304 | CM12: =CL11+CM10-CM11 -> 17586.769 | CN12: =CM11+CN10-CN11 -> 17307.614 | CO12: =CN11+CO10-CO11 -> 17148.097 | CP12: =CO11+CP10-CP11 -> 19142.062 | ... CT12: =CS11+CT10-CT11 -> 19667.743 | CU12: =SUM(CI12:CT12) -> 165748.32 | CV12: =CU11+CV10-CV11 -> 6978.8767 | CW12: =CV11+CW10-CW11 -> 25123.956 | CX12: =CW11+CX10-CX11 -> 20936.63 | CY12: =CX11+CY10-CY11 -> 16749.304 | CZ12: =CY11+CZ10-CZ11 -> 17586.769 | DA12: =CZ11+DA10-DA11 -> 17307.614 | DB12: =DA11+DB10-DB11 -> 17148.097 | DC12: =DB11+DC10-DC11 -> 19142.062 | ... DG12: =DF11+DG10-DG11 -> 19667.743 | DH12: =SUM(CV12:DG12) -> 209366.3 | DI12: =DH11+DI10-DI11 -> 6978.8767 | DJ12: =DI11+DJ10-DJ11 -> 25123.956 | DK12: =DJ11+DK10-DK11 -> 20936.63 | DL12: =DK11+DL10-DL11 -> 16749.304 | DM12: =DL11+DM10-DM11 -> 17586.769 | DN12: =DM11+DN10-DN11 -> 17307.614 | DO12: =DN11+DO10-DO11 -> 17148.097 | DP12: =DO11+DP10-DP11 -> 19142.062 | ... DT12: =DS11+DT10-DT11 -> 19667.743 | DU12: =SUM(DI12:DT12) -> 209366.3 | DV12: =DU11+DV10-DV11 -> 6978.8767 | DW12: =DV11+DW10-DW11 -> 25123.956 | DX12: =DW11+DX10-DX11 -> 20936.63 | DY12: =DX11+DY10-DY11 -> 16749.304 | DZ12: =DY11+DZ10-DZ11 -> 17586.769 | EA12: =DZ11+EA10-EA11 -> 17307.614 | EB12: =EA11+EB10-EB11 -> 17148.097 | EC12: =EB11+EC10-EC11 -> 19142.062 | ... EG12: =EF11+EG10-EG11 -> 19667.743 | EH12: =SUM(DV12:EG12) -> 209366.3
D13: =D12+1 -> 5 | F13: Other Income / (Expense) | I13: =+I10*Assumption!$M$84*-1 -> 0 | J13: =+J10*Assumption!$M$84*-1 -> 0 | K13: =+K10*Assumption!$M$84*-1 -> 0 | L13: =+L10*Assumption!$M$84*-1 -> 0 | M13: =+M10*Assumption!$M$84*-1 -> 0 | N13: =+N10*Assumption!$M$84*-1 -> 0 | O13: =+O10*Assumption!$M$84*-1 -> 1.6 | P13: =+P10*Assumption!$M$84*-1 -> 2 | ... T13: =+T10*Assumption!$M$84*-1 -> 2 | U13: =SUM(I13:T13) -> 10 | V13: =+V10*Assumption!$M$85*-1 -> 78.65 | W13: =+W10*Assumption!$M$85*-1 -> 62.92 | X13: =+X10*Assumption!$M$85*-1 -> 47.19 | Y13: =+Y10*Assumption!$M$85*-1 -> 62.92 | Z13: =+Z10*Assumption!$M$85*-1 -> 78.65 | AA13: =+AA10*Assumption!$M$85*-1 -> 62.92 | AB13: =+AB10*Assumption!$M$85*-1 -> 62.92 | AC13: =+AC10*Assumption!$M$85*-1 -> 78.65 | ... AG13: =+AG10*Assumption!$M$85*-1 -> 78.65 | AH13: =SUM(V13:AG13) -> 786.5 | AI13: =+AI10*Assumption!$M$86*-1 -> 86.515 | AJ13: =+AJ10*Assumption!$M$86*-1 -> 69.212 | AK13: =+AK10*Assumption!$M$86*-1 -> 51.909 | AL13: =+AL10*Assumption!$M$86*-1 -> 69.212 | AM13: =+AM10*Assumption!$M$86*-1 -> 86.515 | AN13: =+AN10*Assumption!$M$86*-1 -> 69.212 | AO13: =+AO10*Assumption!$M$86*-1 -> 69.212 | AP13: =+AP10*Assumption!$M$86*-1 -> 86.515 | ... AT13: =+AT10*Assumption!$M$86*-1 -> 86.515 | AU13: =SUM(AI13:AT13) -> 865.15 | AV13: =+AV10*Assumption!$M$87*-1 -> 95.1665 | AW13: =+AW10*Assumption!$M$87*-1 -> 76.1332 | AX13: =+AX10*Assumption!$M$87*-1 -> 57.0999 | AY13: =+AY10*Assumption!$M$87*-1 -> 76.1332 | AZ13: =+AZ10*Assumption!$M$87*-1 -> 95.1665 | BA13: =+BA10*Assumption!$M$87*-1 -> 76.1332 | BB13: =+BB10*Assumption!$M$87*-1 -> 76.1332 | BC13: =+BC10*Assumption!$M$87*-1 -> 95.1665 | ... BG13: =+BG10*Assumption!$M$87*-1 -> 95.1665 | BH13: =SUM(AV13:BG13) -> 951.665 | BI13: =+BI10*Assumption!$M$88*-1 -> 104.68315 | BJ13: =+BJ10*Assumption!$M$88*-1 -> 83.74652 | BK13: =+BK10*Assumption!$M$88*-1 -> 62.80989 | BL13: =+BL10*Assumption!$M$88*-1 -> 83.74652 | BM13: =+BM10*Assumption!$M$88*-1 -> 104.68315 | BN13: =+BN10*Assumption!$M$88*-1 -> 83.74652 | BO13: =+BO10*Assumption!$M$88*-1 -> 83.74652 | BP13: =+BP10*Assumption!$M$88*-1 -> 104.68315 | ... BT13: =+BT10*Assumption!$M$88*-1 -> 104.68315 | BU13: =SUM(BI13:BT13) -> 1046.8315 | BV13: =+BV10*Assumption!$M$89*-1 -> 88.909858 | BW13: =+BW10*Assumption!$M$89*-1 -> 71.127887 | BX13: =+BX10*Assumption!$M$89*-1 -> 53.345915 | BY13: =+BY10*Assumption!$M$89*-1 -> 71.127887 | BZ13: =+BZ10*Assumption!$M$89*-1 -> 88.909858 | CA13: =+CA10*Assumption!$M$89*-1 -> 71.127887 | CB13: =+CB10*Assumption!$M$89*-1 -> 71.127887 | CC13: =+CC10*Assumption!$M$89*-1 -> 88.909858 | ... CG13: =+CG10*Assumption!$M$89*-1 -> 88.909858 | CH13: =SUM(BV13:CG13) -> 889.09858 | CI13: =+CI10*Assumption!$M$89*-1 -> 88.909858 | CJ13: =+CJ10*Assumption!$M$89*-1 -> 71.127887 | CK13: =+CK10*Assumption!$M$89*-1 -> 53.345915 | CL13: =+CL10*Assumption!$M$89*-1 -> 71.127887 | CM13: =+CM10*Assumption!$M$89*-1 -> 88.909858 | CN13: =+CN10*Assumption!$M$89*-1 -> 71.127887 | CO13: =+CO10*Assumption!$M$89*-1 -> 71.127887 | CP13: =+CP10*Assumption!$M$89*-1 -> 88.909858 | ... CT13: =+CT10*Assumption!$M$89*-1 -> 88.909858 | CU13: =SUM(CI13:CT13) -> 889.09858 | CV13: =+CV10*Assumption!$M$89*-1 -> 88.909858 | CW13: =+CW10*Assumption!$M$89*-1 -> 71.127887 | CX13: =+CX10*Assumption!$M$89*-1 -> 53.345915 | CY13: =+CY10*Assumption!$M$89*-1 -> 71.127887 | CZ13: =+CZ10*Assumption!$M$89*-1 -> 88.909858 | DA13: =+DA10*Assumption!$M$89*-1 -> 71.127887 | DB13: =+DB10*Assumption!$M$89*-1 -> 71.127887 | DC13: =+DC10*Assumption!$M$89*-1 -> 88.909858 | ... DG13: =+DG10*Assumption!$M$89*-1 -> 88.909858 | DH13: =SUM(CV13:DG13) -> 889.09858 | DI13: =+DI10*Assumption!$M$89*-1 -> 88.909858 | DJ13: =+DJ10*Assumption!$M$89*-1 -> 71.127887 | DK13: =+DK10*Assumption!$M$89*-1 -> 53.345915 | DL13: =+DL10*Assumption!$M$89*-1 -> 71.127887 | DM13: =+DM10*Assumption!$M$89*-1 -> 88.909858 | DN13: =+DN10*Assumption!$M$89*-1 -> 71.127887 | DO13: =+DO10*Assumption!$M$89*-1 -> 71.127887 | DP13: =+DP10*Assumption!$M$89*-1 -> 88.909858 | ... DT13: =+DT10*Assumption!$M$89*-1 -> 88.909858 | DU13: =SUM(DI13:DT13) -> 889.09858 | DV13: =+DV10*Assumption!$M$89*-1 -> 88.909858 | DW13: =+DW10*Assumption!$M$89*-1 -> 71.127887 | DX13: =+DX10*Assumption!$M$89*-1 -> 53.345915 | DY13: =+DY10*Assumption!$M$89*-1 -> 71.127887 | DZ13: =+DZ10*Assumption!$M$89*-1 -> 88.909858 | EA13: =+EA10*Assumption!$M$89*-1 -> 71.127887 | EB13: =+EB10*Assumption!$M$89*-1 -> 71.127887 | EC13: =+EC10*Assumption!$M$89*-1 -> 88.909858 | ... EG13: =+EG10*Assumption!$M$89*-1 -> 88.909858 | EH13: =SUM(DV13:EG13) -> 889.09858
D14: 6 | F14: TOTAL OPERATING CASH INFLOWS | I14: =SUM(I12:I13) -> 403 | J14: =SUM(J12:J13) -> 0 | K14: =SUM(K12:K13) -> 0 | L14: =SUM(L12:L13) -> 0 | M14: =SUM(M12:M13) -> 0 | N14: =SUM(N12:N13) -> 0 | O14: =SUM(O12:O13) -> -27604.114 | P14: =SUM(P12:P13) -> 3817.7143 | ... EH14: =SUM(EH12:EH13) -> 210255.4
D15: =D14+1 -> 7 | F15: Purchase | G15: 1 | I15: =+'Purchase-Expenses-AP Schedule'!F36 -> 0 | J15: =+'Purchase-Expenses-AP Schedule'!G36 -> 0 | K15: =+'Purchase-Expenses-AP Schedule'!H36 -> 0 | L15: =+'Purchase-Expenses-AP Schedule'!I36 -> 0 | M15: =+'Purchase-Expenses-AP Schedule'!J36 -> 0 | N15: =+'Purchase-Expenses-AP Schedule'!K36 -> 0 | O15: =+'Purchase-Expenses-AP Schedule'!L36 -> 3260.32 | P15: =+'Purchase-Expenses-AP Schedule'!M36 -> 4075.4 | ... T15: =+'Purchase-Expenses-AP Schedule'!Q36 -> 3260.32 | U15: =SUM(I15:T15) -> 20377 | V15: =+'Purchase-Expenses-AP Schedule'!F38 -> 9303.36 | W15: =+'Purchase-Expenses-AP Schedule'!G38 -> 6977.52 | X15: =+'Purchase-Expenses-AP Schedule'!H38 -> 9303.36 | Y15: =+'Purchase-Expenses-AP Schedule'!I38 -> 11629.2 | Z15: =+'Purchase-Expenses-AP Schedule'!J38 -> 11629.2 | AA15: =+'Purchase-Expenses-AP Schedule'!K38 -> 9303.36 | AB15: =+'Purchase-Expenses-AP Schedule'!L38 -> 9303.36 | AC15: =+'Purchase-Expenses-AP Schedule'!M38 -> 11629.2 | ... AG15: =+'Purchase-Expenses-AP Schedule'!Q38 -> 9303.36 | AH15: =SUM(V15:AG15) -> 116292 | AI15: =+'Purchase-Expenses-AP Schedule'!F40 -> 10117.536 | AJ15: =+'Purchase-Expenses-AP Schedule'!G40 -> 7588.152 | AK15: =+'Purchase-Expenses-AP Schedule'!H40 -> 10117.536 | AL15: =+'Purchase-Expenses-AP Schedule'!I40 -> 12646.92 | AM15: =+'Purchase-Expenses-AP Schedule'!J40 -> 12646.92 | AN15: =+'Purchase-Expenses-AP Schedule'!K40 -> 10117.536 | AO15: =+'Purchase-Expenses-AP Schedule'!L40 -> 10117.536 | AP15: =+'Purchase-Expenses-AP Schedule'!M40 -> 12646.92 | ... AT15: =+'Purchase-Expenses-AP Schedule'!Q40 -> 10117.536 | AU15: =SUM(AI15:AT15) -> 126469.2 | AV15: =+'Purchase-Expenses-AP Schedule'!F42 -> 11129.29 | AW15: =+'Purchase-Expenses-AP Schedule'!G42 -> 8346.9672 | AX15: =+'Purchase-Expenses-AP Schedule'!H42 -> 11129.29 | AY15: =+'Purchase-Expenses-AP Schedule'!I42 -> 13911.612 | AZ15: =+'Purchase-Expenses-AP Schedule'!J42 -> 13911.612 | BA15: =+'Purchase-Expenses-AP Schedule'!K42 -> 11129.29 | BB15: =+'Purchase-Expenses-AP Schedule'!L42 -> 11129.29 | BC15: =+'Purchase-Expenses-AP Schedule'!M42 -> 13911.612 | ... BG15: =+'Purchase-Expenses-AP Schedule'!Q42 -> 11129.29 | BH15: =SUM(AV15:BG15) -> 139116.12 | BI15: =+'Purchase-Expenses-AP Schedule'!F44 -> 12242.219 | BJ15: =+'Purchase-Expenses-AP Schedule'!G44 -> 9181.6639 | BK15: =+'Purchase-Expenses-AP Schedule'!H44 -> 12242.219 | BL15: =+'Purchase-Expenses-AP Schedule'!I44 -> 15302.773 | BM15: =+'Purchase-Expenses-AP Schedule'!J44 -> 15302.773 | BN15: =+'Purchase-Expenses-AP Schedule'!K44 -> 12242.219 | BO15: =+'Purchase-Expenses-AP Schedule'!L44 -> 12242.219 | BP15: =+'Purchase-Expenses-AP Schedule'!M44 -> 15302.773 | ... BT15: =+'Purchase-Expenses-AP Schedule'!Q44 -> 12242.219 | BU15: =SUM(BI15:BT15) -> 153027.73 | BV15: =+'Purchase-Expenses-AP Schedule'!F46 -> 13480.51 | BW15: =+'Purchase-Expenses-AP Schedule'!G46 -> 10110.382 | BX15: =+'Purchase-Expenses-AP Schedule'!H46 -> 13480.51 | BY15: =+'Purchase-Expenses-AP Schedule'!I46 -> 16850.637 | BZ15: =+'Purchase-Expenses-AP Schedule'!J46 -> 16850.637 | CA15: =+'Purchase-Expenses-AP Schedule'!K46 -> 13480.51 | CB15: =+'Purchase-Expenses-AP Schedule'!L46 -> 13480.51 | CC15: =+'Purchase-Expenses-AP Schedule'!M46 -> 16850.637 | ... CG15: =+'Purchase-Expenses-AP Schedule'!Q46 -> 13480.51 | CH15: =SUM(BV15:CG15) -> 168506.37 | CI15: =+'Purchase-Expenses-AP Schedule'!F48 -> 15194.969 | CJ15: =+'Purchase-Expenses-AP Schedule'!G48 -> 11396.226 | CK15: =+'Purchase-Expenses-AP Schedule'!H48 -> 15194.969 | CL15: =+'Purchase-Expenses-AP Schedule'!I48 -> 18993.711 | CM15: =+'Purchase-Expenses-AP Schedule'!J48 -> 18993.711 | CN15: =+'Purchase-Expenses-AP Schedule'!K48 -> 15194.969 | CO15: =+'Purchase-Expenses-AP Schedule'!L48 -> 15194.969 | CP15: =+'Purchase-Expenses-AP Schedule'!M48 -> 18993.711 | ... CT15: =+'Purchase-Expenses-AP Schedule'!Q48 -> 15194.969 | CU15: =SUM(CI15:CT15) -> 189937.11 | CV15: =+'Purchase-Expenses-AP Schedule'!F50 -> 15194.969 | CW15: =+'Purchase-Expenses-AP Schedule'!G50 -> 11396.226 | CX15: =+'Purchase-Expenses-AP Schedule'!H50 -> 15194.969 | CY15: =+'Purchase-Expenses-AP Schedule'!I50 -> 18993.711 | CZ15: =+'Purchase-Expenses-AP Schedule'!J50 -> 18993.711 | DA15: =+'Purchase-Expenses-AP Schedule'!K50 -> 15194.969 | DB15: =+'Purchase-Expenses-AP Schedule'!L50 -> 15194.969 | DC15: =+'Purchase-Expenses-AP Schedule'!M50 -> 18993.711 | ... DG15: =+'Purchase-Expenses-AP Schedule'!Q50 -> 15194.969 | DH15: =SUM(CV15:DG15) -> 189937.11 | DI15: =+'Purchase-Expenses-AP Schedule'!F52 -> 15194.969 | DJ15: =+'Purchase-Expenses-AP Schedule'!G52 -> 11396.226 | DK15: =+'Purchase-Expenses-AP Schedule'!H52 -> 15194.969 | DL15: =+'Purchase-Expenses-AP Schedule'!I52 -> 18993.711 | DM15: =+'Purchase-Expenses-AP Schedule'!J52 -> 18993.711 | DN15: =+'Purchase-Expenses-AP Schedule'!K52 -> 15194.969 | DO15: =+'Purchase-Expenses-AP Schedule'!L52 -> 15194.969 | DP15: =+'Purchase-Expenses-AP Schedule'!M52 -> 18993.711 | ... DT15: =+'Purchase-Expenses-AP Schedule'!Q52 -> 15194.969 | DU15: =SUM(DI15:DT15) -> 189937.11 | DV15: =+'Purchase-Expenses-AP Schedule'!F54 -> 15194.969 | DW15: =+'Purchase-Expenses-AP Schedule'!G54 -> 11396.226 | DX15: =+'Purchase-Expenses-AP Schedule'!H54 -> 15194.969 | DY15: =+'Purchase-Expenses-AP Schedule'!I54 -> 18993.711 | DZ15: =+'Purchase-Expenses-AP Schedule'!J54 -> 18993.711 | EA15: =+'Purchase-Expenses-AP Schedule'!K54 -> 15194.969 | EB15: =+'Purchase-Expenses-AP Schedule'!L54 -> 15194.969 | EC15: =+'Purchase-Expenses-AP Schedule'!M54 -> 18993.711 | ... EG15: =+'Purchase-Expenses-AP Schedule'!Q54 -> 15194.969 | EH15: =SUM(DV15:EG15) -> 189937.11
D16: =D15+1 -> 8 | F16: Credit Purchase (Non L/C) | G16: =Assumption!G196 -> 1 | I16: =+$G$16*I15 -> 0 | J16: =+$G$16*J15 -> 0 | K16: =+$G$16*K15 -> 0 | L16: =+$G$16*L15 -> 0 | M16: =+$G$16*M15 -> 0 | N16: =+$G$16*N15 -> 0 | O16: =+$G$16*O15 -> 3260.32 | P16: =+$G$16*P15 -> 4075.4 | ... T16: =+$G$16*T15 -> 3260.32 | U16: =SUM(I16:T16) -> 20377 | V16: =+$G$16*V15 -> 9303.36 | W16: =+$G$16*W15 -> 6977.52 | X16: =+$G$16*X15 -> 9303.36 | Y16: =+$G$16*Y15 -> 11629.2 | Z16: =+$G$16*Z15 -> 11629.2 | AA16: =+$G$16*AA15 -> 9303.36 | AB16: =+$G$16*AB15 -> 9303.36 | AC16: =+$G$16*AC15 -> 11629.2 | ... AG16: =+$G$16*AG15 -> 9303.36 | AH16: =SUM(V16:AG16) -> 116292 | AI16: =+$G$16*AI15 -> 10117.536 | AJ16: =+$G$16*AJ15 -> 7588.152 | AK16: =+$G$16*AK15 -> 10117.536 | AL16: =+$G$16*AL15 -> 12646.92 | AM16: =+$G$16*AM15 -> 12646.92 | AN16: =+$G$16*AN15 -> 10117.536 | AO16: =+$G$16*AO15 -> 10117.536 | AP16: =+$G$16*AP15 -> 12646.92 | ... AT16: =+$G$16*AT15 -> 10117.536 | AU16: =SUM(AI16:AT16) -> 126469.2 | AV16: =+$G$16*AV15 -> 11129.29 | AW16: =+$G$16*AW15 -> 8346.9672 | AX16: =+$G$16*AX15 -> 11129.29 | AY16: =+$G$16*AY15 -> 13911.612 | AZ16: =+$G$16*AZ15 -> 13911.612 | BA16: =+$G$16*BA15 -> 11129.29 | BB16: =+$G$16*BB15 -> 11129.29 | BC16: =+$G$16*BC15 -> 13911.612 | ... BG16: =+$G$16*BG15 -> 11129.29 | BH16: =SUM(AV16:BG16) -> 139116.12 | BI16: =+$G$16*BI15 -> 12242.219 | BJ16: =+$G$16*BJ15 -> 9181.6639 | BK16: =+$G$16*BK15 -> 12242.219 | BL16: =+$G$16*BL15 -> 15302.773 | BM16: =+$G$16*BM15 -> 15302.773 | BN16: =+$G$16*BN15 -> 12242.219 | BO16: =+$G$16*BO15 -> 12242.219 | BP16: =+$G$16*BP15 -> 15302.773 | ... BT16: =+$G$16*BT15 -> 12242.219 | BU16: =SUM(BI16:BT16) -> 153027.73 | BV16: =+$G$16*BV15 -> 13480.51 | BW16: =+$G$16*BW15 -> 10110.382 | BX16: =+$G$16*BX15 -> 13480.51 | BY16: =+$G$16*BY15 -> 16850.637 | BZ16: =+$G$16*BZ15 -> 16850.637 | CA16: =+$G$16*CA15 -> 13480.51 | CB16: =+$G$16*CB15 -> 13480.51 | CC16: =+$G$16*CC15 -> 16850.637 | ... CG16: =+$G$16*CG15 -> 13480.51 | CH16: =SUM(BV16:CG16) -> 168506.37 | CI16: =+$G$16*CI15 -> 15194.969 | CJ16: =+$G$16*CJ15 -> 11396.226 | CK16: =+$G$16*CK15 -> 15194.969 | CL16: =+$G$16*CL15 -> 18993.711 | CM16: =+$G$16*CM15 -> 18993.711 | CN16: =+$G$16*CN15 -> 15194.969 | CO16: =+$G$16*CO15 -> 15194.969 | CP16: =+$G$16*CP15 -> 18993.711 | ... CT16: =+$G$16*CT15 -> 15194.969 | CU16: =SUM(CI16:CT16) -> 189937.11 | CV16: =+$G$16*CV15 -> 15194.969 | CW16: =+$G$16*CW15 -> 11396.226 | CX16: =+$G$16*CX15 -> 15194.969 | CY16: =+$G$16*CY15 -> 18993.711 | CZ16: =+$G$16*CZ15 -> 18993.711 | DA16: =+$G$16*DA15 -> 15194.969 | DB16: =+$G$16*DB15 -> 15194.969 | DC16: =+$G$16*DC15 -> 18993.711 | ... DG16: =+$G$16*DG15 -> 15194.969 | DH16: =SUM(CV16:DG16) -> 189937.11 | DI16: =+$G$16*DI15 -> 15194.969 | DJ16: =+$G$16*DJ15 -> 11396.226 | DK16: =+$G$16*DK15 -> 15194.969 | DL16: =+$G$16*DL15 -> 18993.711 | DM16: =+$G$16*DM15 -> 18993.711 | DN16: =+$G$16*DN15 -> 15194.969 | DO16: =+$G$16*DO15 -> 15194.969 | DP16: =+$G$16*DP15 -> 18993.711 | ... DT16: =+$G$16*DT15 -> 15194.969 | DU16: =SUM(DI16:DT16) -> 189937.11 | DV16: =+$G$16*DV15 -> 15194.969 | DW16: =+$G$16*DW15 -> 11396.226 | DX16: =+$G$16*DX15 -> 15194.969 | DY16: =+$G$16*DY15 -> 18993.711 | DZ16: =+$G$16*DZ15 -> 18993.711 | EA16: =+$G$16*EA15 -> 15194.969 | EB16: =+$G$16*EB15 -> 15194.969 | EC16: =+$G$16*EC15 -> 18993.711 | ... EG16: =+$G$16*EG15 -> 15194.969 | EH16: =SUM(DV16:EG16) -> 189937.11
D17: =D16+1 -> 9 | F17: Purchase by L/C (Open L/C) | G17: =Assumption!G195 -> 0 | I17: =+I15-I16 -> 0 | J17: =+J15-J16 -> 0 | K17: =+K15-K16 -> 0 | L17: =+L15-L16 -> 0 | M17: =+M15-M16 -> 0 | N17: =+N15-N16 -> 0 | O17: =+O15-O16 -> 0 | P17: =+P15-P16 -> 0 | ... T17: =+T15-T16 -> 0 | U17: =SUM(I17:T17) -> 0 | V17: =+V15-V16 -> 0 | W17: =+W15-W16 -> 0 | X17: =+X15-X16 -> 0 | Y17: =+Y15-Y16 -> 0 | Z17: =+Z15-Z16 -> 0 | AA17: =+AA15-AA16 -> 0 | AB17: =+AB15-AB16 -> 0 | AC17: =+AC15-AC16 -> 0 | ... AG17: =+AG15-AG16 -> 0 | AH17: =SUM(V17:AG17) -> 0 | AI17: =+AI15-AI16 -> 0 | AJ17: =+AJ15-AJ16 -> 0 | AK17: =+AK15-AK16 -> 0 | AL17: =+AL15-AL16 -> 0 | AM17: =+AM15-AM16 -> 0 | AN17: =+AN15-AN16 -> 0 | AO17: =+AO15-AO16 -> 0 | AP17: =+AP15-AP16 -> 0 | ... AT17: =+AT15-AT16 -> 0 | AU17: =SUM(AI17:AT17) -> 0 | AV17: =+AV15-AV16 -> 0 | AW17: =+AW15-AW16 -> 0 | AX17: =+AX15-AX16 -> 0 | AY17: =+AY15-AY16 -> 0 | AZ17: =+AZ15-AZ16 -> 0 | BA17: =+BA15-BA16 -> 0 | BB17: =+BB15-BB16 -> 0 | BC17: =+BC15-BC16 -> 0 | ... BG17: =+BG15-BG16 -> 0 | BH17: =SUM(AV17:BG17) -> 0 | BI17: =+BI15-BI16 -> 0 | BJ17: =+BJ15-BJ16 -> 0 | BK17: =+BK15-BK16 -> 0 | BL17: =+BL15-BL16 -> 0 | BM17: =+BM15-BM16 -> 0 | BN17: =+BN15-BN16 -> 0 | BO17: =+BO15-BO16 -> 0 | BP17: =+BP15-BP16 -> 0 | ... BT17: =+BT15-BT16 -> 0 | BU17: =SUM(BI17:BT17) -> 0 | BV17: =+BV15-BV16 -> 0 | BW17: =+BW15-BW16 -> 0 | BX17: =+BX15-BX16 -> 0 | BY17: =+BY15-BY16 -> 0 | BZ17: =+BZ15-BZ16 -> 0 | CA17: =+CA15-CA16 -> 0 | CB17: =+CB15-CB16 -> 0 | CC17: =+CC15-CC16 -> 0 | ... CG17: =+CG15-CG16 -> 0 | CH17: =SUM(BV17:CG17) -> 0 | CI17: =+CI15-CI16 -> 0 | CJ17: =+CJ15-CJ16 -> 0 | CK17: =+CK15-CK16 -> 0 | CL17: =+CL15-CL16 -> 0 | CM17: =+CM15-CM16 -> 0 | CN17: =+CN15-CN16 -> 0 | CO17: =+CO15-CO16 -> 0 | CP17: =+CP15-CP16 -> 0 | ... CT17: =+CT15-CT16 -> 0 | CU17: =SUM(CI17:CT17) -> 0 | CV17: =+CV15-CV16 -> 0 | CW17: =+CW15-CW16 -> 0 | CX17: =+CX15-CX16 -> 0 | CY17: =+CY15-CY16 -> 0 | CZ17: =+CZ15-CZ16 -> 0 | DA17: =+DA15-DA16 -> 0 | DB17: =+DB15-DB16 -> 0 | DC17: =+DC15-DC16 -> 0 | ... DG17: =+DG15-DG16 -> 0 | DH17: =SUM(CV17:DG17) -> 0 | DI17: =+DI15-DI16 -> 0 | DJ17: =+DJ15-DJ16 -> 0 | DK17: =+DK15-DK16 -> 0 | DL17: =+DL15-DL16 -> 0 | DM17: =+DM15-DM16 -> 0 | DN17: =+DN15-DN16 -> 0 | DO17: =+DO15-DO16 -> 0 | DP17: =+DP15-DP16 -> 0 | ... DT17: =+DT15-DT16 -> 0 | DU17: =SUM(DI17:DT17) -> 0 | DV17: =+DV15-DV16 -> 0 | DW17: =+DW15-DW16 -> 0 | DX17: =+DX15-DX16 -> 0 | DY17: =+DY15-DY16 -> 0 | DZ17: =+DZ15-DZ16 -> 0 | EA17: =+EA15-EA16 -> 0 | EB17: =+EB15-EB16 -> 0 | EC17: =+EC15-EC16 -> 0 | ... EG17: =+EG15-EG16 -> 0 | EH17: =SUM(DV17:EG17) -> 0
D18: =D17+1 -> 10 | F18: (Account Payables) | H18: =Historical!K39 -> 2403 | I18: =+'Purchase-Expenses-AP Schedule'!F71 -> 0 | J18: =+'Purchase-Expenses-AP Schedule'!G71 -> 0 | K18: =+'Purchase-Expenses-AP Schedule'!H71 -> 0 | L18: =+'Purchase-Expenses-AP Schedule'!I71 -> 0 | M18: =+'Purchase-Expenses-AP Schedule'!J71 -> 0 | N18: =+'Purchase-Expenses-AP Schedule'!K71 -> 0 | O18: =+'Purchase-Expenses-AP Schedule'!L71 -> 2220.5076 | P18: =+'Purchase-Expenses-AP Schedule'!M71 -> 2027.8483 | ... T18: =+'Purchase-Expenses-AP Schedule'!Q71 -> 1533.0278 | U18: =T18 -> 1533.0278 | V18: =+'Purchase-Expenses-AP Schedule'!F72 -> 1550.56 | W18: =+'Purchase-Expenses-AP Schedule'!G72 -> 1356.74 | X18: =+'Purchase-Expenses-AP Schedule'!H72 -> 1421.3467 | Y18: =+'Purchase-Expenses-AP Schedule'!I72 -> 1550.56 | Z18: =+'Purchase-Expenses-AP Schedule'!J72 -> 1628.088 | AA18: =+'Purchase-Expenses-AP Schedule'!K72 -> 1615.1667 | AB18: =+'Purchase-Expenses-AP Schedule'!L72 -> 1605.9371 | AC18: =+'Purchase-Expenses-AP Schedule'!M72 -> 1647.47 | ... AG18: =+'Purchase-Expenses-AP Schedule'!Q72 -> 1615.1667 | AH18: =AG18 -> 1615.1667 | AI18: =+'Purchase-Expenses-AP Schedule'!F73 -> 1686.256 | AJ18: =+'Purchase-Expenses-AP Schedule'!G73 -> 1475.474 | AK18: =+'Purchase-Expenses-AP Schedule'!H73 -> 1545.7347 | AL18: =+'Purchase-Expenses-AP Schedule'!I73 -> 1686.256 | AM18: =+'Purchase-Expenses-AP Schedule'!J73 -> 1770.5688 | AN18: =+'Purchase-Expenses-AP Schedule'!K73 -> 1756.5167 | AO18: =+'Purchase-Expenses-AP Schedule'!L73 -> 1746.4794 | AP18: =+'Purchase-Expenses-AP Schedule'!M73 -> 1791.647 | ... AT18: =+'Purchase-Expenses-AP Schedule'!Q73 -> 1756.5167 | AU18: =AT18 -> 1756.5167 | AV18: =+'Purchase-Expenses-AP Schedule'!F74 -> 1854.8816 | AW18: =+'Purchase-Expenses-AP Schedule'!G74 -> 1623.0214 | AX18: =+'Purchase-Expenses-AP Schedule'!H74 -> 1700.3081 | AY18: =+'Purchase-Expenses-AP Schedule'!I74 -> 1854.8816 | AZ18: =+'Purchase-Expenses-AP Schedule'!J74 -> 1947.6257 | BA18: =+'Purchase-Expenses-AP Schedule'!K74 -> 1932.1683 | BB18: =+'Purchase-Expenses-AP Schedule'!L74 -> 1921.1274 | BC18: =+'Purchase-Expenses-AP Schedule'!M74 -> 1970.8117 | ... BG18: =+'Purchase-Expenses-AP Schedule'!Q74 -> 1932.1683 | BH18: =BG18 -> 1932.1683 | BI18: =+'Purchase-Expenses-AP Schedule'!F75 -> 2040.3698 | BJ18: =+'Purchase-Expenses-AP Schedule'!G75 -> 1785.3235 | BK18: =+'Purchase-Expenses-AP Schedule'!H75 -> 1870.3389 | BL18: =+'Purchase-Expenses-AP Schedule'!I75 -> 2040.3698 | BM18: =+'Purchase-Expenses-AP Schedule'!J75 -> 2142.3882 | BN18: =+'Purchase-Expenses-AP Schedule'!K75 -> 2125.3852 | BO18: =+'Purchase-Expenses-AP Schedule'!L75 -> 2113.2401 | BP18: =+'Purchase-Expenses-AP Schedule'!M75 -> 2167.8929 | ... BT18: =+'Purchase-Expenses-AP Schedule'!Q75 -> 2125.3852 | BU18: =BT18 -> 2125.3852 | BV18: =+'Purchase-Expenses-AP Schedule'!F76 -> 31454.523 | BW18: =+'Purchase-Expenses-AP Schedule'!G76 -> 27522.708 | BX18: =+'Purchase-Expenses-AP Schedule'!H76 -> 28833.313 | BY18: =+'Purchase-Expenses-AP Schedule'!I76 -> 31454.523 | BZ18: =+'Purchase-Expenses-AP Schedule'!J76 -> 33027.249 | CA18: =+'Purchase-Expenses-AP Schedule'!K76 -> 32765.128 | CB18: =+'Purchase-Expenses-AP Schedule'!L76 -> 32577.899 | CC18: =+'Purchase-Expenses-AP Schedule'!M76 -> 33420.431 | ... CG18: =+'Purchase-Expenses-AP Schedule'!Q76 -> 32765.128 | CH18: =CG18 -> 32765.128 | CI18: =+'Purchase-Expenses-AP Schedule'!F77 -> 35454.927 | CJ18: =+'Purchase-Expenses-AP Schedule'!G77 -> 31023.061 | CK18: =+'Purchase-Expenses-AP Schedule'!H77 -> 32500.349 | CL18: =+'Purchase-Expenses-AP Schedule'!I77 -> 35454.927 | CM18: =+'Purchase-Expenses-AP Schedule'!J77 -> 37227.673 | CN18: =+'Purchase-Expenses-AP Schedule'!K77 -> 36932.215 | CO18: =+'Purchase-Expenses-AP Schedule'!L77 -> 36721.174 | CP18: =+'Purchase-Expenses-AP Schedule'!M77 -> 37670.86 | ... CT18: =+'Purchase-Expenses-AP Schedule'!Q77 -> 36932.215 | CU18: =CT18 -> 36932.215 | CV18: =+'Purchase-Expenses-AP Schedule'!F78 -> 35454.927 | CW18: =+'Purchase-Expenses-AP Schedule'!G78 -> 31023.061 | CX18: =+'Purchase-Expenses-AP Schedule'!H78 -> 32500.349 | CY18: =+'Purchase-Expenses-AP Schedule'!I78 -> 35454.927 | CZ18: =+'Purchase-Expenses-AP Schedule'!J78 -> 37227.673 | DA18: =+'Purchase-Expenses-AP Schedule'!K78 -> 36932.215 | DB18: =+'Purchase-Expenses-AP Schedule'!L78 -> 36721.174 | DC18: =+'Purchase-Expenses-AP Schedule'!M78 -> 37670.86 | ... DG18: =+'Purchase-Expenses-AP Schedule'!Q78 -> 36932.215 | DH18: =DG18 -> 36932.215 | DI18: =+'Purchase-Expenses-AP Schedule'!F79 -> 35454.927 | DJ18: =+'Purchase-Expenses-AP Schedule'!G79 -> 31023.061 | DK18: =+'Purchase-Expenses-AP Schedule'!H79 -> 32500.349 | DL18: =+'Purchase-Expenses-AP Schedule'!I79 -> 35454.927 | DM18: =+'Purchase-Expenses-AP Schedule'!J79 -> 37227.673 | DN18: =+'Purchase-Expenses-AP Schedule'!K79 -> 36932.215 | DO18: =+'Purchase-Expenses-AP Schedule'!L79 -> 36721.174 | DP18: =+'Purchase-Expenses-AP Schedule'!M79 -> 37670.86 | ... DT18: =+'Purchase-Expenses-AP Schedule'!Q79 -> 36932.215 | DU18: =DT18 -> 36932.215 | DV18: =+'Purchase-Expenses-AP Schedule'!F80 -> 35454.927 | DW18: =+'Purchase-Expenses-AP Schedule'!G80 -> 31023.061 | DX18: =+'Purchase-Expenses-AP Schedule'!H80 -> 32500.349 | DY18: =+'Purchase-Expenses-AP Schedule'!I80 -> 35454.927 | DZ18: =+'Purchase-Expenses-AP Schedule'!J80 -> 37227.673 | EA18: =+'Purchase-Expenses-AP Schedule'!K80 -> 36932.215 | EB18: =+'Purchase-Expenses-AP Schedule'!L80 -> 36721.174 | EC18: =+'Purchase-Expenses-AP Schedule'!M80 -> 37670.86 | ... EG18: =+'Purchase-Expenses-AP Schedule'!Q80 -> 36932.215 | EH18: =EG18 -> 36932.215
D19: =D18+1 -> 11 | F19: (LC + TR) | G19: =+Assumption!K199 -> 4 | H19: =Historical!K37 -> 2203 | I19: =+H19+I17-I21 -> 2203 | J19: =+I19+J17-J21 -> 2203 | K19: =+J19+K17-K21 -> 2203 | L19: =+K19+L17-L21 -> 2203 | M19: =+L19+M17-M21 -> 2203 | N19: =+M19+N17-N21 -> 2203 | O19: =+N19+O17-O21 -> 1652.25 | P19: =+O19+P17-P21 -> 1101.5 | ... T19: =+S19+T17-T21 -> 0 | U19: =+T19 -> 0 | V19: =+U19+V17-V21 -> 0 | W19: =+V19+W17-W21 -> 0 | X19: =+W19+X17-X21 -> 0 | Y19: =+X19+Y17-Y21 -> 0 | Z19: =+Y19+Z17-Z21 -> 0 | AA19: =+Z19+AA17-AA21 -> 0 | AB19: =+AA19+AB17-AB21 -> 0 | AC19: =+AB19+AC17-AC21 -> 0 | ... AG19: =+AF19+AG17-AG21 -> 0 | AH19: =+AG19 -> 0 | AI19: =+AH19+AI17-AI21 -> 0 | AJ19: =+AI19+AJ17-AJ21 -> 0 | AK19: =+AJ19+AK17-AK21 -> 0 | AL19: =+AK19+AL17-AL21 -> 0 | AM19: =+AL19+AM17-AM21 -> 0 | AN19: =+AM19+AN17-AN21 -> 0 | AO19: =+AN19+AO17-AO21 -> 0 | AP19: =+AO19+AP17-AP21 -> 0 | ... AT19: =+AS19+AT17-AT21 -> 0 | AU19: =+AT19 -> 0 | AV19: =+AU19+AV17-AV21 -> 0 | AW19: =+AV19+AW17-AW21 -> 0 | AX19: =+AW19+AX17-AX21 -> 0 | AY19: =+AX19+AY17-AY21 -> 0 | AZ19: =+AY19+AZ17-AZ21 -> 0 | BA19: =+AZ19+BA17-BA21 -> 0 | BB19: =+BA19+BB17-BB21 -> 0 | BC19: =+BB19+BC17-BC21 -> 0 | ... BG19: =+BF19+BG17-BG21 -> 0 | BH19: =+BG19 -> 0 | BI19: =+BH19+BI17-BI21 -> 0 | BJ19: =+BI19+BJ17-BJ21 -> 0 | BK19: =+BJ19+BK17-BK21 -> 0 | BL19: =+BK19+BL17-BL21 -> 0 | BM19: =+BL19+BM17-BM21 -> 0 | BN19: =+BM19+BN17-BN21 -> 0 | BO19: =+BN19+BO17-BO21 -> 0 | BP19: =+BO19+BP17-BP21 -> 0 | ... BT19: =+BS19+BT17-BT21 -> 0 | BU19: =+BT19 -> 0 | BV19: =+BU19+BV17-BV21 -> 0 | BW19: =+BV19+BW17-BW21 -> 0 | BX19: =+BW19+BX17-BX21 -> 0 | BY19: =+BX19+BY17-BY21 -> 0 | BZ19: =+BY19+BZ17-BZ21 -> 0 | CA19: =+BZ19+CA17-CA21 -> 0 | CB19: =+CA19+CB17-CB21 -> 0 | CC19: =+CB19+CC17-CC21 -> 0 | ... CG19: =+CF19+CG17-CG21 -> 0 | CH19: =+CG19 -> 0 | CI19: =+CH19+CI17-CI21 -> 0 | CJ19: =+CI19+CJ17-CJ21 -> 0 | CK19: =+CJ19+CK17-CK21 -> 0 | CL19: =+CK19+CL17-CL21 -> 0 | CM19: =+CL19+CM17-CM21 -> 0 | CN19: =+CM19+CN17-CN21 -> 0 | CO19: =+CN19+CO17-CO21 -> 0 | CP19: =+CO19+CP17-CP21 -> 0 | ... CT19: =+CS19+CT17-CT21 -> 0 | CU19: =+CT19 -> 0 | CV19: =+CU19+CV17-CV21 -> 0 | CW19: =+CV19+CW17-CW21 -> 0 | CX19: =+CW19+CX17-CX21 -> 0 | CY19: =+CX19+CY17-CY21 -> 0 | CZ19: =+CY19+CZ17-CZ21 -> 0 | DA19: =+CZ19+DA17-DA21 -> 0 | DB19: =+DA19+DB17-DB21 -> 0 | DC19: =+DB19+DC17-DC21 -> 0 | ... DG19: =+DF19+DG17-DG21 -> 0 | DH19: =+DG19 -> 0 | DI19: =+DH19+DI17-DI21 -> 0 | DJ19: =+DI19+DJ17-DJ21 -> 0 | DK19: =+DJ19+DK17-DK21 -> 0 | DL19: =+DK19+DL17-DL21 -> 0 | DM19: =+DL19+DM17-DM21 -> 0 | DN19: =+DM19+DN17-DN21 -> 0 | DO19: =+DN19+DO17-DO21 -> 0 | DP19: =+DO19+DP17-DP21 -> 0 | ... DT19: =+DS19+DT17-DT21 -> 0 | DU19: =+DT19 -> 0 | DV19: =+DU19+DV17-DV21 -> 0 | DW19: =+DV19+DW17-DW21 -> 0 | DX19: =+DW19+DX17-DX21 -> 0 | DY19: =+DX19+DY17-DY21 -> 0 | DZ19: =+DY19+DZ17-DZ21 -> 0 | EA19: =+DZ19+EA17-EA21 -> 0 | EB19: =+EA19+EB17-EB21 -> 0 | EC19: =+EB19+EC17-EC21 -> 0 | ... EG19: =+EF19+EG17-EG21 -> 0 | EH19: =+EG19 -> 0
D20: =D19+1 -> 12 | F20: Payments of Account Payables | I20: =+H18+I16-I18 -> 2403 | J20: =+I18+J16-J18 -> 0 | K20: =+J18+K16-K18 -> 0 | L20: =+K18+L16-L18 -> 0 | M20: =+L18+M16-M18 -> 0 | N20: =+M18+N16-N18 -> 0 | O20: =+N18+O16-O18 -> 1039.8124 | P20: =+O18+P16-P18 -> 4268.0593 | ... T20: =+S18+T16-T18 -> 3350.2874 | U20: =SUM(L20:T20) -> 18843.972 | V20: =+U18+V16-V18 -> 9285.8278 | W20: =+V18+W16-W18 -> 7171.34 | X20: =+W18+X16-X18 -> 9238.7533 | Y20: =+X18+Y16-Y18 -> 11499.987 | Z20: =+Y18+Z16-Z18 -> 11551.672 | AA20: =+Z18+AA16-AA18 -> 9316.2813 | AB20: =+AA18+AB16-AB18 -> 9312.5895 | AC20: =+AB18+AC16-AC18 -> 11587.667 | ... AG20: =+AF18+AG16-AG18 -> 9309.2333 | AH20: =SUM(Y20:AG20) -> 90513.94 | AI20: =+AH18+AI16-AI18 -> 10046.447 | AJ20: =+AI18+AJ16-AJ18 -> 7798.934 | AK20: =+AJ18+AK16-AK18 -> 10047.275 | AL20: =+AK18+AL16-AL18 -> 12506.399 | AM20: =+AL18+AM16-AM18 -> 12562.607 | AN20: =+AM18+AN16-AN18 -> 10131.588 | AO20: =+AN18+AO16-AO18 -> 10127.573 | AP20: =+AO18+AP16-AP18 -> 12601.752 | ... AT20: =+AS18+AT16-AT18 -> 10123.923 | AU20: =SUM(AL20:AT20) -> 98435.194 | AV20: =+AU18+AV16-AV18 -> 11030.925 | AW20: =+AV18+AW16-AW18 -> 8578.8274 | AX20: =+AW18+AX16-AX18 -> 11052.003 | AY20: =+AX18+AY16-AY18 -> 13757.039 | AZ20: =+AY18+AZ16-AZ18 -> 13818.868 | BA20: =+AZ18+BA16-BA18 -> 11144.747 | BB20: =+BA18+BB16-BB18 -> 11140.331 | BC20: =+BB18+BC16-BC18 -> 13861.928 | ... BG20: =+BF18+BG16-BG18 -> 11136.316 | BH20: =SUM(AY20:BG20) -> 108278.71 | BI20: =+BH18+BI16-BI18 -> 12134.017 | BJ20: =+BI18+BJ16-BJ18 -> 9436.7101 | BK20: =+BJ18+BK16-BK18 -> 12157.203 | BL20: =+BK18+BL16-BL18 -> 15132.742 | BM20: =+BL18+BM16-BM18 -> 15200.755 | BN20: =+BM18+BN16-BN18 -> 12259.222 | BO20: =+BN18+BO16-BO18 -> 12254.364 | BP20: =+BO18+BP16-BP18 -> 15248.12 | ... BT20: =+BS18+BT16-BT18 -> 12249.947 | BU20: =SUM(BL20:BT20) -> 119106.58 | BV20: =+BU18+BV16-BV18 -> -15848.628 | BW20: =+BV18+BW16-BW18 -> 14042.198 | BX20: =+BW18+BX16-BX18 -> 12169.905 | BY20: =+BX18+BY16-BY18 -> 14229.427 | BZ20: =+BY18+BZ16-BZ18 -> 15277.911 | CA20: =+BZ18+CA16-CA18 -> 13742.631 | CB20: =+CA18+CB16-CB18 -> 13667.739 | CC20: =+CB18+CC16-CC18 -> 16008.105 | ... CG20: =+CF18+CG16-CG18 -> 13599.656 | CH20: =SUM(BY20:CG20) -> 127503.16 | CI20: =+CH18+CI16-CI18 -> 12505.17 | CJ20: =+CI18+CJ16-CJ18 -> 15828.092 | CK20: =+CJ18+CK16-CK18 -> 13717.68 | CL20: =+CK18+CL16-CL18 -> 16039.134 | CM20: =+CL18+CM16-CM18 -> 17220.964 | CN20: =+CM18+CN16-CN18 -> 15490.426 | CO20: =+CN18+CO16-CO18 -> 15406.01 | CP20: =+CO18+CP16-CP18 -> 18044.025 | ... CT20: =+CS18+CT16-CT18 -> 15329.268 | CU20: =SUM(CL20:CT20) -> 143719.08 | CV20: =+CU18+CV16-CV18 -> 16672.257 | CW20: =+CV18+CW16-CW18 -> 15828.092 | CX20: =+CW18+CX16-CX18 -> 13717.68 | CY20: =+CX18+CY16-CY18 -> 16039.134 | CZ20: =+CY18+CZ16-CZ18 -> 17220.964 | DA20: =+CZ18+DA16-DA18 -> 15490.426 | DB20: =+DA18+DB16-DB18 -> 15406.01 | DC20: =+DB18+DC16-DC18 -> 18044.025 | ... DG20: =+DF18+DG16-DG18 -> 15329.268 | DH20: =SUM(CY20:DG20) -> 143719.08 | DI20: =+DH18+DI16-DI18 -> 16672.257 | DJ20: =+DI18+DJ16-DJ18 -> 15828.092 | DK20: =+DJ18+DK16-DK18 -> 13717.68 | DL20: =+DK18+DL16-DL18 -> 16039.134 | DM20: =+DL18+DM16-DM18 -> 17220.964 | DN20: =+DM18+DN16-DN18 -> 15490.426 | DO20: =+DN18+DO16-DO18 -> 15406.01 | DP20: =+DO18+DP16-DP18 -> 18044.025 | ... DT20: =+DS18+DT16-DT18 -> 15329.268 | DU20: =SUM(DL20:DT20) -> 143719.08 | DV20: =+DU18+DV16-DV18 -> 16672.257 | DW20: =+DV18+DW16-DW18 -> 15828.092 | DX20: =+DW18+DX16-DX18 -> 13717.68 | DY20: =+DX18+DY16-DY18 -> 16039.134 | DZ20: =+DY18+DZ16-DZ18 -> 17220.964 | EA20: =+DZ18+EA16-EA18 -> 15490.426 | EB20: =+EA18+EB16-EB18 -> 15406.01 | EC20: =+EB18+EC16-EC18 -> 18044.025 | ... EG20: =+EF18+EG16-EG18 -> 15329.268 | EH20: =SUM(DY20:EG20) -> 143719.08
D21: =D20+1 -> 13 | F21: Payments of L/C + TR | I21: =+IF(I5-$I$3<1,H19*I4/$I$3,HLOOKUP(I5-$I$3,I5:T17,13,FALSE)) -> 0 | J21: =+IF(J5-$I$3<1,H19*J4/$I$3,HLOOKUP(J5-$I$3,I5:T17,13,FALSE)) -> 0 | K21: =+IF(K5-$I$3<1,H19*K4/$I$3,HLOOKUP(K5-$I$3,I5:T17,13,FALSE)) -> 0 | L21: =+IF(L5-$I$3<1,H19*L4/$I$3,HLOOKUP(L5-$I$3,I5:T17,13,FALSE)) -> 0 | M21: =+IF(M5-$I$3<1,H19*M4/$I$3,HLOOKUP(M5-$I$3,I5:T17,13,FALSE)) -> 0 | N21: =+IF(N5-$I$3<1,H19*N4/$I$3,HLOOKUP(N5-$I$3,I5:T17,13,FALSE)) -> 0 | O21: =+IF(O5-$I$3<1,H19*O4/$I$3,HLOOKUP(O5-$I$3,I5:T17,13,FALSE)) -> 550.75 | P21: =+IF(P5-$I$3<1,H19*P4/$I$3,HLOOKUP(P5-$I$3,I5:T17,13,FALSE)) -> 550.75 | Q21: =+IF(Q5-$I$3<1,H19*Q4/$I$3,HLOOKUP(Q5-$I$3,I5:T17,13,FALSE)) -> 550.75 | R21: =+IF(R5-$I$3<1,H19*R4/$I$3,HLOOKUP(R5-$I$3,I5:T17,13,FALSE)) -> 550.75 | S21: =+IF(S5-$I$3<1,H19*S4/$I$3,HLOOKUP(S5-$I$3,I5:T17,13,FALSE)) -> 0 | T21: =+IF(T5-$I$3<1,H19*T4/$I$3,HLOOKUP(T5-$I$3,I5:T17,13,FALSE)) -> 0 | U21: =SUM(I21:T21) -> 2203 | V21: =+IF(V5-$I$3<1,U19*V4/$I$3,HLOOKUP(V5-$I$3,V5:AG17,13,FALSE)) -> 0 | W21: =+IF(W5-$I$3<1,U19*W4/$I$3,HLOOKUP(W5-$I$3,V5:AG17,13,FALSE)) -> 0 | X21: =+IF(X5-$I$3<1,U19*X4/$I$3,HLOOKUP(X5-$I$3,V5:AG17,13,FALSE)) -> 0 | Y21: =+IF(Y5-$I$3<1,U19*Y4/$I$3,HLOOKUP(Y5-$I$3,V5:AG17,13,FALSE)) -> 0 | Z21: =+IF(Z5-$I$3<1,U19*Z4/$I$3,HLOOKUP(Z5-$I$3,V5:AG17,13,FALSE)) -> 0 | AA21: =+IF(AA5-$I$3<1,U19*AA4/$I$3,HLOOKUP(AA5-$I$3,V5:AG17,13,FALSE)) -> 0 | AB21: =+IF(AB5-$I$3<1,U19*AB4/$I$3,HLOOKUP(AB5-$I$3,V5:AG17,13,FALSE)) -> 0 | AC21: =+IF(AC5-$I$3<1,U19*AC4/$I$3,HLOOKUP(AC5-$I$3,V5:AG17,13,FALSE)) -> 0 | AD21: =+IF(AD5-$I$3<1,U19*AD4/$I$3,HLOOKUP(AD5-$I$3,V5:AG17,13,FALSE)) -> 0 | AE21: =+IF(AE5-$I$3<1,U19*AE4/$I$3,HLOOKUP(AE5-$I$3,V5:AG17,13,FALSE)) -> 0 | AF21: =+IF(AF5-$I$3<1,U19*AF4/$I$3,HLOOKUP(AF5-$I$3,V5:AG17,13,FALSE)) -> 0 | AG21: =+IF(AG5-$I$3<1,U19*AG4/$I$3,HLOOKUP(AG5-$I$3,V5:AG17,13,FALSE)) -> 0 | AH21: =SUM(V21:AG21) -> 0 | AI21: =+IF(AI5-$I$3<1,AH19*AI4/$I$3,HLOOKUP(AI5-$I$3,AI5:AT17,13,FALSE)) -> 0 | AJ21: =+IF(AJ5-$I$3<1,AH19*AJ4/$I$3,HLOOKUP(AJ5-$I$3,AI5:AT17,13,FALSE)) -> 0 | AK21: =+IF(AK5-$I$3<1,AH19*AK4/$I$3,HLOOKUP(AK5-$I$3,AI5:AT17,13,FALSE)) -> 0 | AL21: =+IF(AL5-$I$3<1,AH19*AL4/$I$3,HLOOKUP(AL5-$I$3,AI5:AT17,13,FALSE)) -> 0 | AM21: =+IF(AM5-$I$3<1,AH19*AM4/$I$3,HLOOKUP(AM5-$I$3,AI5:AT17,13,FALSE)) -> 0 | AN21: =+IF(AN5-$I$3<1,AH19*AN4/$I$3,HLOOKUP(AN5-$I$3,AI5:AT17,13,FALSE)) -> 0 | AO21: =+IF(AO5-$I$3<1,AH19*AO4/$I$3,HLOOKUP(AO5-$I$3,AI5:AT17,13,FALSE)) -> 0 | AP21: =+IF(AP5-$I$3<1,AH19*AP4/$I$3,HLOOKUP(AP5-$I$3,AI5:AT17,13,FALSE)) -> 0 | AQ21: =+IF(AQ5-$I$3<1,AH19*AQ4/$I$3,HLOOKUP(AQ5-$I$3,AI5:AT17,13,FALSE)) -> 0 | AR21: =+IF(AR5-$I$3<1,AH19*AR4/$I$3,HLOOKUP(AR5-$I$3,AI5:AT17,13,FALSE)) -> 0 | AS21: =+IF(AS5-$I$3<1,AH19*AS4/$I$3,HLOOKUP(AS5-$I$3,AI5:AT17,13,FALSE)) -> 0 | AT21: =+IF(AT5-$I$3<1,AH19*AT4/$I$3,HLOOKUP(AT5-$I$3,AI5:AT17,13,FALSE)) -> 0 | AU21: =SUM(AI21:AT21) -> 0 | AV21: =+IF(AV5-$I$3<1,AU19*AV4/$I$3,HLOOKUP(AV5-$I$3,AV5:BG17,13,FALSE)) -> 0 | AW21: =+IF(AW5-$I$3<1,AU19*AW4/$I$3,HLOOKUP(AW5-$I$3,AV5:BG17,13,FALSE)) -> 0 | AX21: =+IF(AX5-$I$3<1,AU19*AX4/$I$3,HLOOKUP(AX5-$I$3,AV5:BG17,13,FALSE)) -> 0 | AY21: =+IF(AY5-$I$3<1,AU19*AY4/$I$3,HLOOKUP(AY5-$I$3,AV5:BG17,13,FALSE)) -> 0 | AZ21: =+IF(AZ5-$I$3<1,AU19*AZ4/$I$3,HLOOKUP(AZ5-$I$3,AV5:BG17,13,FALSE)) -> 0 | BA21: =+IF(BA5-$I$3<1,AU19*BA4/$I$3,HLOOKUP(BA5-$I$3,AV5:BG17,13,FALSE)) -> 0 | BB21: =+IF(BB5-$I$3<1,AU19*BB4/$I$3,HLOOKUP(BB5-$I$3,AV5:BG17,13,FALSE)) -> 0 | BC21: =+IF(BC5-$I$3<1,AU19*BC4/$I$3,HLOOKUP(BC5-$I$3,AV5:BG17,13,FALSE)) -> 0 | BD21: =+IF(BD5-$I$3<1,AU19*BD4/$I$3,HLOOKUP(BD5-$I$3,AV5:BG17,13,FALSE)) -> 0 | BE21: =+IF(BE5-$I$3<1,AU19*BE4/$I$3,HLOOKUP(BE5-$I$3,AV5:BG17,13,FALSE)) -> 0 | BF21: =+IF(BF5-$I$3<1,AU19*BF4/$I$3,HLOOKUP(BF5-$I$3,AV5:BG17,13,FALSE)) -> 0 | BG21: =+IF(BG5-$I$3<1,AU19*BG4/$I$3,HLOOKUP(BG5-$I$3,AV5:BG17,13,FALSE)) -> 0 | BH21: =SUM(AV21:BG21) -> 0 | BI21: =+IF(BI5-$I$3<1,BH19*BI4/$I$3,HLOOKUP(BI5-$I$3,BI5:BT17,13,FALSE)) -> 0 | BJ21: =+IF(BJ5-$I$3<1,BH19*BJ4/$I$3,HLOOKUP(BJ5-$I$3,BI5:BT17,13,FALSE)) -> 0 | BK21: =+IF(BK5-$I$3<1,BH19*BK4/$I$3,HLOOKUP(BK5-$I$3,BI5:BT17,13,FALSE)) -> 0 | BL21: =+IF(BL5-$I$3<1,BH19*BL4/$I$3,HLOOKUP(BL5-$I$3,BI5:BT17,13,FALSE)) -> 0 | BM21: =+IF(BM5-$I$3<1,BH19*BM4/$I$3,HLOOKUP(BM5-$I$3,BI5:BT17,13,FALSE)) -> 0 | BN21: =+IF(BN5-$I$3<1,BH19*BN4/$I$3,HLOOKUP(BN5-$I$3,BI5:BT17,13,FALSE)) -> 0 | BO21: =+IF(BO5-$I$3<1,BH19*BO4/$I$3,HLOOKUP(BO5-$I$3,BI5:BT17,13,FALSE)) -> 0 | BP21: =+IF(BP5-$I$3<1,BH19*BP4/$I$3,HLOOKUP(BP5-$I$3,BI5:BT17,13,FALSE)) -> 0 | BQ21: =+IF(BQ5-$I$3<1,BH19*BQ4/$I$3,HLOOKUP(BQ5-$I$3,BI5:BT17,13,FALSE)) -> 0 | BR21: =+IF(BR5-$I$3<1,BH19*BR4/$I$3,HLOOKUP(BR5-$I$3,BI5:BT17,13,FALSE)) -> 0 | BS21: =+IF(BS5-$I$3<1,BH19*BS4/$I$3,HLOOKUP(BS5-$I$3,BI5:BT17,13,FALSE)) -> 0 | BT21: =+IF(BT5-$I$3<1,BH19*BT4/$I$3,HLOOKUP(BT5-$I$3,BI5:BT17,13,FALSE)) -> 0 | BU21: =SUM(BI21:BT21) -> 0 | BV21: =+IF(BV5-$I$3<1,$BU$19*BV4/$I$3,HLOOKUP(BV5-$I$3,$BV$5:$CG$17,13,FALSE)) -> 0 | BW21: =+IF(BW5-$I$3<1,$BU$19*BW4/$I$3,HLOOKUP(BW5-$I$3,$BV$5:$CG$17,13,FALSE)) -> 0 | BX21: =+IF(BX5-$I$3<1,$BU$19*BX4/$I$3,HLOOKUP(BX5-$I$3,$BV$5:$CG$17,13,FALSE)) -> 0 | BY21: =+IF(BY5-$I$3<1,$BU$19*BY4/$I$3,HLOOKUP(BY5-$I$3,$BV$5:$CG$17,13,FALSE)) -> 0 | BZ21: =+IF(BZ5-$I$3<1,$BU$19*BZ4/$I$3,HLOOKUP(BZ5-$I$3,$BV$5:$CG$17,13,FALSE)) -> 0 | CA21: =+IF(CA5-$I$3<1,$BU$19*CA4/$I$3,HLOOKUP(CA5-$I$3,$BV$5:$CG$17,13,FALSE)) -> 0 | CB21: =+IF(CB5-$I$3<1,$BU$19*CB4/$I$3,HLOOKUP(CB5-$I$3,$BV$5:$CG$17,13,FALSE)) -> 0 | CC21: =+IF(CC5-$I$3<1,$BU$19*CC4/$I$3,HLOOKUP(CC5-$I$3,$BV$5:$CG$17,13,FALSE)) -> 0 | ... CG21: =+IF(CG5-$I$3<1,$BU$19*CG4/$I$3,HLOOKUP(CG5-$I$3,$BV$5:$CG$17,13,FALSE)) -> 0 | CH21: =SUM(BV21:CG21) -> 0 | CI21: =+IF(CI5-$I$3<1,$CH$19*CI4/$I$3,HLOOKUP(CI5-$I$3,$CI$5:$CT$17,13,FALSE)) -> 0 | CJ21: =+IF(CJ5-$I$3<1,$CH$19*CJ4/$I$3,HLOOKUP(CJ5-$I$3,$CI$5:$CT$17,13,FALSE)) -> 0 | CK21: =+IF(CK5-$I$3<1,$CH$19*CK4/$I$3,HLOOKUP(CK5-$I$3,$CI$5:$CT$17,13,FALSE)) -> 0 | CL21: =+IF(CL5-$I$3<1,$CH$19*CL4/$I$3,HLOOKUP(CL5-$I$3,$CI$5:$CT$17,13,FALSE)) -> 0 | CM21: =+IF(CM5-$I$3<1,$CH$19*CM4/$I$3,HLOOKUP(CM5-$I$3,$CI$5:$CT$17,13,FALSE)) -> 0 | CN21: =+IF(CN5-$I$3<1,$CH$19*CN4/$I$3,HLOOKUP(CN5-$I$3,$CI$5:$CT$17,13,FALSE)) -> 0 | CO21: =+IF(CO5-$I$3<1,$CH$19*CO4/$I$3,HLOOKUP(CO5-$I$3,$CI$5:$CT$17,13,FALSE)) -> 0 | CP21: =+IF(CP5-$I$3<1,$CH$19*CP4/$I$3,HLOOKUP(CP5-$I$3,$CI$5:$CT$17,13,FALSE)) -> 0 | ... CT21: =+IF(CT5-$I$3<1,$CH$19*CT4/$I$3,HLOOKUP(CT5-$I$3,$CI$5:$CT$17,13,FALSE)) -> 0 | CU21: =SUM(CI21:CT21) -> 0 | CV21: =+IF(CV5-$I$3<1,$CU$19*CV4/$I$3,HLOOKUP(CV5-$I$3,$CV$5:$DG$17,13,FALSE)) -> 0 | CW21: =+IF(CW5-$I$3<1,$CU$19*CW4/$I$3,HLOOKUP(CW5-$I$3,$CV$5:$DG$17,13,FALSE)) -> 0 | CX21: =+IF(CX5-$I$3<1,$CU$19*CX4/$I$3,HLOOKUP(CX5-$I$3,$CV$5:$DG$17,13,FALSE)) -> 0 | CY21: =+IF(CY5-$I$3<1,$CU$19*CY4/$I$3,HLOOKUP(CY5-$I$3,$CV$5:$DG$17,13,FALSE)) -> 0 | CZ21: =+IF(CZ5-$I$3<1,$CU$19*CZ4/$I$3,HLOOKUP(CZ5-$I$3,$CV$5:$DG$17,13,FALSE)) -> 0 | DA21: =+IF(DA5-$I$3<1,$CU$19*DA4/$I$3,HLOOKUP(DA5-$I$3,$CV$5:$DG$17,13,FALSE)) -> 0 | DB21: =+IF(DB5-$I$3<1,$CU$19*DB4/$I$3,HLOOKUP(DB5-$I$3,$CV$5:$DG$17,13,FALSE)) -> 0 | DC21: =+IF(DC5-$I$3<1,$CU$19*DC4/$I$3,HLOOKUP(DC5-$I$3,$CV$5:$DG$17,13,FALSE)) -> 0 | ... DG21: =+IF(DG5-$I$3<1,$CU$19*DG4/$I$3,HLOOKUP(DG5-$I$3,$CV$5:$DG$17,13,FALSE)) -> 0 | DH21: =SUM(CV21:DG21) -> 0 | DI21: =+IF(DI5-$I$3<1,$DH$19*DI4/$I$3,HLOOKUP(DI5-$I$3,$DI$5:$DT$17,13,FALSE)) -> 0 | DJ21: =+IF(DJ5-$I$3<1,$DH$19*DJ4/$I$3,HLOOKUP(DJ5-$I$3,$DI$5:$DT$17,13,FALSE)) -> 0 | DK21: =+IF(DK5-$I$3<1,$DH$19*DK4/$I$3,HLOOKUP(DK5-$I$3,$DI$5:$DT$17,13,FALSE)) -> 0 | DL21: =+IF(DL5-$I$3<1,$DH$19*DL4/$I$3,HLOOKUP(DL5-$I$3,$DI$5:$DT$17,13,FALSE)) -> 0 | DM21: =+IF(DM5-$I$3<1,$DH$19*DM4/$I$3,HLOOKUP(DM5-$I$3,$DI$5:$DT$17,13,FALSE)) -> 0 | DN21: =+IF(DN5-$I$3<1,$DH$19*DN4/$I$3,HLOOKUP(DN5-$I$3,$DI$5:$DT$17,13,FALSE)) -> 0 | DO21: =+IF(DO5-$I$3<1,$DH$19*DO4/$I$3,HLOOKUP(DO5-$I$3,$DI$5:$DT$17,13,FALSE)) -> 0 | DP21: =+IF(DP5-$I$3<1,$DH$19*DP4/$I$3,HLOOKUP(DP5-$I$3,$DI$5:$DT$17,13,FALSE)) -> 0 | ... DT21: =+IF(DT5-$I$3<1,$DH$19*DT4/$I$3,HLOOKUP(DT5-$I$3,$DI$5:$DT$17,13,FALSE)) -> 0 | DU21: =SUM(DI21:DT21) -> 0 | DV21: =+IF(DV5-$I$3<1,$DU$19*DV4/$I$3,HLOOKUP(DV5-$I$3,$DV$5:$EG$17,13,FALSE)) -> 0 | DW21: =+IF(DW5-$I$3<1,$DU$19*DW4/$I$3,HLOOKUP(DW5-$I$3,$DV$5:$EG$17,13,FALSE)) -> 0 | DX21: =+IF(DX5-$I$3<1,$DU$19*DX4/$I$3,HLOOKUP(DX5-$I$3,$DV$5:$EG$17,13,FALSE)) -> 0 | DY21: =+IF(DY5-$I$3<1,$DU$19*DY4/$I$3,HLOOKUP(DY5-$I$3,$DV$5:$EG$17,13,FALSE)) -> 0 | DZ21: =+IF(DZ5-$I$3<1,$DU$19*DZ4/$I$3,HLOOKUP(DZ5-$I$3,$DV$5:$EG$17,13,FALSE)) -> 0 | EA21: =+IF(EA5-$I$3<1,$DU$19*EA4/$I$3,HLOOKUP(EA5-$I$3,$DV$5:$EG$17,13,FALSE)) -> 0 | EB21: =+IF(EB5-$I$3<1,$DU$19*EB4/$I$3,HLOOKUP(EB5-$I$3,$DV$5:$EG$17,13,FALSE)) -> 0 | EC21: =+IF(EC5-$I$3<1,$DU$19*EC4/$I$3,HLOOKUP(EC5-$I$3,$DV$5:$EG$17,13,FALSE)) -> 0 | ... EG21: =+IF(EG5-$I$3<1,$DU$19*EG4/$I$3,HLOOKUP(EG5-$I$3,$DV$5:$EG$17,13,FALSE)) -> 0 | EH21: =SUM(DV21:EG21) -> 0
D22: =D21+1 -> 14 | F22: Payments of Labor Cost | I22: =+'Purchase-Expenses-AP Schedule'!F84 -> 0 | J22: =+'Purchase-Expenses-AP Schedule'!G84 -> 0 | K22: =+'Purchase-Expenses-AP Schedule'!H84 -> 0 | L22: =+'Purchase-Expenses-AP Schedule'!I84 -> 0 | M22: =+'Purchase-Expenses-AP Schedule'!J84 -> 0 | N22: =+'Purchase-Expenses-AP Schedule'!K84 -> 0 | O22: =+'Purchase-Expenses-AP Schedule'!L84 -> 0 | P22: =+'Purchase-Expenses-AP Schedule'!M84 -> 0 | ... T22: =+'Purchase-Expenses-AP Schedule'!Q84 -> 0 | U22: =SUM(I22:T22) -> 0 | V22: =+'Purchase-Expenses-AP Schedule'!F86 -> 0 | W22: =+'Purchase-Expenses-AP Schedule'!G86 -> 0 | X22: =+'Purchase-Expenses-AP Schedule'!H86 -> 0 | Y22: =+'Purchase-Expenses-AP Schedule'!I86 -> 0 | Z22: =+'Purchase-Expenses-AP Schedule'!J86 -> 0 | AA22: =+'Purchase-Expenses-AP Schedule'!K86 -> 0 | AB22: =+'Purchase-Expenses-AP Schedule'!L86 -> 0 | AC22: =+'Purchase-Expenses-AP Schedule'!M86 -> 0 | ... AG22: =+'Purchase-Expenses-AP Schedule'!Q86 -> 0 | AH22: =SUM(V22:AG22) -> 0 | AI22: =+'Purchase-Expenses-AP Schedule'!F88 -> 0 | AJ22: =+'Purchase-Expenses-AP Schedule'!G88 -> 0 | AK22: =+'Purchase-Expenses-AP Schedule'!H88 -> 0 | AL22: =+'Purchase-Expenses-AP Schedule'!I88 -> 0 | AM22: =+'Purchase-Expenses-AP Schedule'!J88 -> 0 | AN22: =+'Purchase-Expenses-AP Schedule'!K88 -> 0 | AO22: =+'Purchase-Expenses-AP Schedule'!L88 -> 0 | AP22: =+'Purchase-Expenses-AP Schedule'!M88 -> 0 | ... AT22: =+'Purchase-Expenses-AP Schedule'!Q88 -> 0 | AU22: =SUM(AI22:AT22) -> 0 | AV22: =+'Purchase-Expenses-AP Schedule'!F90 -> 0 | AW22: =+'Purchase-Expenses-AP Schedule'!G90 -> 0 | AX22: =+'Purchase-Expenses-AP Schedule'!H90 -> 0 | AY22: =+'Purchase-Expenses-AP Schedule'!I90 -> 0 | AZ22: =+'Purchase-Expenses-AP Schedule'!J90 -> 0 | BA22: =+'Purchase-Expenses-AP Schedule'!K90 -> 0 | BB22: =+'Purchase-Expenses-AP Schedule'!L90 -> 0 | BC22: =+'Purchase-Expenses-AP Schedule'!M90 -> 0 | ... BG22: =+'Purchase-Expenses-AP Schedule'!Q90 -> 0 | BH22: =SUM(AV22:BG22) -> 0 | BI22: =+'Purchase-Expenses-AP Schedule'!F92 -> 0 | BJ22: =+'Purchase-Expenses-AP Schedule'!G92 -> 0 | BK22: =+'Purchase-Expenses-AP Schedule'!H92 -> 0 | BL22: =+'Purchase-Expenses-AP Schedule'!I92 -> 0 | BM22: =+'Purchase-Expenses-AP Schedule'!J92 -> 0 | BN22: =+'Purchase-Expenses-AP Schedule'!K92 -> 0 | BO22: =+'Purchase-Expenses-AP Schedule'!L92 -> 0 | BP22: =+'Purchase-Expenses-AP Schedule'!M92 -> 0 | ... BT22: =+'Purchase-Expenses-AP Schedule'!Q92 -> 0 | BU22: =SUM(BI22:BT22) -> 0 | BV22: =+'Purchase-Expenses-AP Schedule'!F94 -> 0 | BW22: =+'Purchase-Expenses-AP Schedule'!G94 -> 0 | BX22: =+'Purchase-Expenses-AP Schedule'!H94 -> 0 | BY22: =+'Purchase-Expenses-AP Schedule'!I94 -> 0 | BZ22: =+'Purchase-Expenses-AP Schedule'!J94 -> 0 | CA22: =+'Purchase-Expenses-AP Schedule'!K94 -> 0 | CB22: =+'Purchase-Expenses-AP Schedule'!L94 -> 0 | CC22: =+'Purchase-Expenses-AP Schedule'!M94 -> 0 | ... CG22: =+'Purchase-Expenses-AP Schedule'!Q94 -> 0 | CH22: =SUM(BV22:CG22) -> 0 | CI22: =+'Purchase-Expenses-AP Schedule'!F96 -> 0 | CJ22: =+'Purchase-Expenses-AP Schedule'!G96 -> 0 | CK22: =+'Purchase-Expenses-AP Schedule'!H96 -> 0 | CL22: =+'Purchase-Expenses-AP Schedule'!I96 -> 0 | CM22: =+'Purchase-Expenses-AP Schedule'!J96 -> 0 | CN22: =+'Purchase-Expenses-AP Schedule'!K96 -> 0 | CO22: =+'Purchase-Expenses-AP Schedule'!L96 -> 0 | CP22: =+'Purchase-Expenses-AP Schedule'!M96 -> 0 | ... CT22: =+'Purchase-Expenses-AP Schedule'!Q96 -> 0 | CU22: =SUM(CI22:CT22) -> 0 | CV22: =+'Purchase-Expenses-AP Schedule'!F98 -> 0 | CW22: =+'Purchase-Expenses-AP Schedule'!G98 -> 0 | CX22: =+'Purchase-Expenses-AP Schedule'!H98 -> 0 | CY22: =+'Purchase-Expenses-AP Schedule'!I98 -> 0 | CZ22: =+'Purchase-Expenses-AP Schedule'!J98 -> 0 | DA22: =+'Purchase-Expenses-AP Schedule'!K98 -> 0 | DB22: =+'Purchase-Expenses-AP Schedule'!L98 -> 0 | DC22: =+'Purchase-Expenses-AP Schedule'!M98 -> 0 | ... DG22: =+'Purchase-Expenses-AP Schedule'!Q98 -> 0 | DH22: =SUM(CV22:DG22) -> 0 | DI22: =+'Purchase-Expenses-AP Schedule'!F100 -> 0 | DJ22: =+'Purchase-Expenses-AP Schedule'!G100 -> 0 | DK22: =+'Purchase-Expenses-AP Schedule'!H100 -> 0 | DL22: =+'Purchase-Expenses-AP Schedule'!I100 -> 0 | DM22: =+'Purchase-Expenses-AP Schedule'!J100 -> 0 | DN22: =+'Purchase-Expenses-AP Schedule'!K100 -> 0 | DO22: =+'Purchase-Expenses-AP Schedule'!L100 -> 0 | DP22: =+'Purchase-Expenses-AP Schedule'!M100 -> 0 | ... DT22: =+'Purchase-Expenses-AP Schedule'!Q100 -> 0 | DU22: =SUM(DI22:DT22) -> 0 | DV22: =+'Purchase-Expenses-AP Schedule'!F102 -> 0 | DW22: =+'Purchase-Expenses-AP Schedule'!G102 -> 0 | DX22: =+'Purchase-Expenses-AP Schedule'!H102 -> 0 | DY22: =+'Purchase-Expenses-AP Schedule'!I102 -> 0 | DZ22: =+'Purchase-Expenses-AP Schedule'!J102 -> 0 | EA22: =+'Purchase-Expenses-AP Schedule'!K102 -> 0 | EB22: =+'Purchase-Expenses-AP Schedule'!L102 -> 0 | EC22: =+'Purchase-Expenses-AP Schedule'!M102 -> 0 | ... EG22: =+'Purchase-Expenses-AP Schedule'!Q102 -> 0 | EH22: =SUM(DV22:EG22) -> 0
D23: =D22+1 -> 15 | F23: Payments of Overhead Cost | I23: =+'Purchase-Expenses-AP Schedule'!F107 -> 0 | J23: =+'Purchase-Expenses-AP Schedule'!G107 -> 0 | K23: =+'Purchase-Expenses-AP Schedule'!H107 -> 0 | L23: =+'Purchase-Expenses-AP Schedule'!I107 -> 0 | M23: =+'Purchase-Expenses-AP Schedule'!J107 -> 0 | N23: =+'Purchase-Expenses-AP Schedule'!K107 -> 0 | O23: =+'Purchase-Expenses-AP Schedule'!L107 -> 0 | P23: =+'Purchase-Expenses-AP Schedule'!M107 -> 0 | ... T23: =+'Purchase-Expenses-AP Schedule'!Q107 -> 0 | U23: =SUM(I23:T23) -> 0 | V23: =+'Purchase-Expenses-AP Schedule'!F109 -> 0 | W23: =+'Purchase-Expenses-AP Schedule'!G109 -> 0 | X23: =+'Purchase-Expenses-AP Schedule'!H109 -> 0 | Y23: =+'Purchase-Expenses-AP Schedule'!I109 -> 0 | Z23: =+'Purchase-Expenses-AP Schedule'!J109 -> 0 | AA23: =+'Purchase-Expenses-AP Schedule'!K109 -> 0 | AB23: =+'Purchase-Expenses-AP Schedule'!L109 -> 0 | AC23: =+'Purchase-Expenses-AP Schedule'!M109 -> 0 | ... AG23: =+'Purchase-Expenses-AP Schedule'!Q109 -> 0 | AH23: =SUM(V23:AG23) -> 0 | AI23: =+'Purchase-Expenses-AP Schedule'!F111 -> 0 | AJ23: =+'Purchase-Expenses-AP Schedule'!G111 -> 0 | AK23: =+'Purchase-Expenses-AP Schedule'!H111 -> 0 | AL23: =+'Purchase-Expenses-AP Schedule'!I111 -> 0 | AM23: =+'Purchase-Expenses-AP Schedule'!J111 -> 0 | AN23: =+'Purchase-Expenses-AP Schedule'!K111 -> 0 | AO23: =+'Purchase-Expenses-AP Schedule'!L111 -> 0 | AP23: =+'Purchase-Expenses-AP Schedule'!M111 -> 0 | ... AT23: =+'Purchase-Expenses-AP Schedule'!Q111 -> 0 | AU23: =SUM(AI23:AT23) -> 0 | AV23: =+'Purchase-Expenses-AP Schedule'!F113 -> 0 | AW23: =+'Purchase-Expenses-AP Schedule'!G113 -> 0 | AX23: =+'Purchase-Expenses-AP Schedule'!H113 -> 0 | AY23: =+'Purchase-Expenses-AP Schedule'!I113 -> 0 | AZ23: =+'Purchase-Expenses-AP Schedule'!J113 -> 0 | BA23: =+'Purchase-Expenses-AP Schedule'!K113 -> 0 | BB23: =+'Purchase-Expenses-AP Schedule'!L113 -> 0 | BC23: =+'Purchase-Expenses-AP Schedule'!M113 -> 0 | ... BG23: =+'Purchase-Expenses-AP Schedule'!Q113 -> 0 | BH23: =SUM(AV23:BG23) -> 0 | BI23: =+'Purchase-Expenses-AP Schedule'!F115 -> 0 | BJ23: =+'Purchase-Expenses-AP Schedule'!G115 -> 0 | BK23: =+'Purchase-Expenses-AP Schedule'!H115 -> 0 | BL23: =+'Purchase-Expenses-AP Schedule'!I115 -> 0 | BM23: =+'Purchase-Expenses-AP Schedule'!J115 -> 0 | BN23: =+'Purchase-Expenses-AP Schedule'!K115 -> 0 | BO23: =+'Purchase-Expenses-AP Schedule'!L115 -> 0 | BP23: =+'Purchase-Expenses-AP Schedule'!M115 -> 0 | ... BT23: =+'Purchase-Expenses-AP Schedule'!Q115 -> 0 | BU23: =SUM(BI23:BT23) -> 0 | BV23: =+'Purchase-Expenses-AP Schedule'!F117 -> 0 | BW23: =+'Purchase-Expenses-AP Schedule'!G117 -> 0 | BX23: =+'Purchase-Expenses-AP Schedule'!H117 -> 0 | BY23: =+'Purchase-Expenses-AP Schedule'!I117 -> 0 | BZ23: =+'Purchase-Expenses-AP Schedule'!J117 -> 0 | CA23: =+'Purchase-Expenses-AP Schedule'!K117 -> 0 | CB23: =+'Purchase-Expenses-AP Schedule'!L117 -> 0 | CC23: =+'Purchase-Expenses-AP Schedule'!M117 -> 0 | ... CG23: =+'Purchase-Expenses-AP Schedule'!Q117 -> 0 | CH23: =SUM(BV23:CG23) -> 0 | CI23: =+'Purchase-Expenses-AP Schedule'!F119 -> 0 | CJ23: =+'Purchase-Expenses-AP Schedule'!G119 -> 0 | CK23: =+'Purchase-Expenses-AP Schedule'!H119 -> 0 | CL23: =+'Purchase-Expenses-AP Schedule'!I119 -> 0 | CM23: =+'Purchase-Expenses-AP Schedule'!J119 -> 0 | CN23: =+'Purchase-Expenses-AP Schedule'!K119 -> 0 | CO23: =+'Purchase-Expenses-AP Schedule'!L119 -> 0 | CP23: =+'Purchase-Expenses-AP Schedule'!M119 -> 0 | ... CT23: =+'Purchase-Expenses-AP Schedule'!Q119 -> 0 | CU23: =SUM(CI23:CT23) -> 0 | CV23: =+'Purchase-Expenses-AP Schedule'!F121 -> 0 | CW23: =+'Purchase-Expenses-AP Schedule'!G121 -> 0 | CX23: =+'Purchase-Expenses-AP Schedule'!H121 -> 0 | CY23: =+'Purchase-Expenses-AP Schedule'!I121 -> 0 | CZ23: =+'Purchase-Expenses-AP Schedule'!J121 -> 0 | DA23: =+'Purchase-Expenses-AP Schedule'!K121 -> 0 | DB23: =+'Purchase-Expenses-AP Schedule'!L121 -> 0 | DC23: =+'Purchase-Expenses-AP Schedule'!M121 -> 0 | ... DG23: =+'Purchase-Expenses-AP Schedule'!Q121 -> 0 | DH23: =SUM(CV23:DG23) -> 0 | DI23: =+'Purchase-Expenses-AP Schedule'!F123 -> 0 | DJ23: =+'Purchase-Expenses-AP Schedule'!G123 -> 0 | DK23: =+'Purchase-Expenses-AP Schedule'!H123 -> 0 | DL23: =+'Purchase-Expenses-AP Schedule'!I123 -> 0 | DM23: =+'Purchase-Expenses-AP Schedule'!J123 -> 0 | DN23: =+'Purchase-Expenses-AP Schedule'!K123 -> 0 | DO23: =+'Purchase-Expenses-AP Schedule'!L123 -> 0 | DP23: =+'Purchase-Expenses-AP Schedule'!M123 -> 0 | ... DT23: =+'Purchase-Expenses-AP Schedule'!Q123 -> 0 | DU23: =SUM(DI23:DT23) -> 0 | DV23: =+'Purchase-Expenses-AP Schedule'!F125 -> 0 | DW23: =+'Purchase-Expenses-AP Schedule'!G125 -> 0 | DX23: =+'Purchase-Expenses-AP Schedule'!H125 -> 0 | DY23: =+'Purchase-Expenses-AP Schedule'!I125 -> 0 | DZ23: =+'Purchase-Expenses-AP Schedule'!J125 -> 0 | EA23: =+'Purchase-Expenses-AP Schedule'!K125 -> 0 | EB23: =+'Purchase-Expenses-AP Schedule'!L125 -> 0 | EC23: =+'Purchase-Expenses-AP Schedule'!M125 -> 0 | ... EG23: =+'Purchase-Expenses-AP Schedule'!Q125 -> 0 | EH23: =SUM(DV23:EG23) -> 0
D24: =D23+1 -> 16 | F24: Payments of Selling, General & Administrative Expenses | I24: =+'Purchase-Expenses-AP Schedule'!F130 -> 0 | J24: =+'Purchase-Expenses-AP Schedule'!G130 -> 0 | K24: =+'Purchase-Expenses-AP Schedule'!H130 -> 0 | L24: =+'Purchase-Expenses-AP Schedule'!I130 -> 0 | M24: =+'Purchase-Expenses-AP Schedule'!J130 -> 0 | N24: =+'Purchase-Expenses-AP Schedule'!K130 -> 0 | O24: =+'Purchase-Expenses-AP Schedule'!L130 -> -66.666667 | P24: =+'Purchase-Expenses-AP Schedule'!M130 -> -66.666667 | ... T24: =+'Purchase-Expenses-AP Schedule'!Q130 -> -66.666667 | U24: =SUM(I24:T24) -> -400 | V24: =+'Purchase-Expenses-AP Schedule'!F132 -> 655.41667 | W24: =+'Purchase-Expenses-AP Schedule'!G132 -> 655.41667 | X24: =+'Purchase-Expenses-AP Schedule'!H132 -> 655.41667 | Y24: =+'Purchase-Expenses-AP Schedule'!I132 -> 655.41667 | Z24: =+'Purchase-Expenses-AP Schedule'!J132 -> 655.41667 | AA24: =+'Purchase-Expenses-AP Schedule'!K132 -> 655.41667 | AB24: =+'Purchase-Expenses-AP Schedule'!L132 -> 655.41667 | AC24: =+'Purchase-Expenses-AP Schedule'!M132 -> 655.41667 | ... AG24: =+'Purchase-Expenses-AP Schedule'!Q132 -> 655.41667 | AH24: =SUM(V24:AG24) -> 7865 | AI24: =+'Purchase-Expenses-AP Schedule'!F134 -> 720.95833 | AJ24: =+'Purchase-Expenses-AP Schedule'!G134 -> 720.95833 | AK24: =+'Purchase-Expenses-AP Schedule'!H134 -> 720.95833 | AL24: =+'Purchase-Expenses-AP Schedule'!I134 -> 720.95833 | AM24: =+'Purchase-Expenses-AP Schedule'!J134 -> 720.95833 | AN24: =+'Purchase-Expenses-AP Schedule'!K134 -> 720.95833 | AO24: =+'Purchase-Expenses-AP Schedule'!L134 -> 720.95833 | AP24: =+'Purchase-Expenses-AP Schedule'!M134 -> 720.95833 | ... AT24: =+'Purchase-Expenses-AP Schedule'!Q134 -> 720.95833 | AU24: =SUM(AI24:AT24) -> 8651.5 | AV24: =+'Purchase-Expenses-AP Schedule'!F136 -> 793.05417 | AW24: =+'Purchase-Expenses-AP Schedule'!G136 -> 793.05417 | AX24: =+'Purchase-Expenses-AP Schedule'!H136 -> 793.05417 | AY24: =+'Purchase-Expenses-AP Schedule'!I136 -> 793.05417 | AZ24: =+'Purchase-Expenses-AP Schedule'!J136 -> 793.05417 | BA24: =+'Purchase-Expenses-AP Schedule'!K136 -> 793.05417 | BB24: =+'Purchase-Expenses-AP Schedule'!L136 -> 793.05417 | BC24: =+'Purchase-Expenses-AP Schedule'!M136 -> 793.05417 | ... BG24: =+'Purchase-Expenses-AP Schedule'!Q136 -> 793.05417 | BH24: =SUM(AV24:BG24) -> 9516.65 | BI24: =+'Purchase-Expenses-AP Schedule'!F138 -> 872.35958 | BJ24: =+'Purchase-Expenses-AP Schedule'!G138 -> 872.35958 | BK24: =+'Purchase-Expenses-AP Schedule'!H138 -> 872.35958 | BL24: =+'Purchase-Expenses-AP Schedule'!I138 -> 872.35958 | BM24: =+'Purchase-Expenses-AP Schedule'!J138 -> 872.35958 | BN24: =+'Purchase-Expenses-AP Schedule'!K138 -> 872.35958 | BO24: =+'Purchase-Expenses-AP Schedule'!L138 -> 872.35958 | BP24: =+'Purchase-Expenses-AP Schedule'!M138 -> 872.35958 | ... BT24: =+'Purchase-Expenses-AP Schedule'!Q138 -> 872.35958 | BU24: =SUM(BI24:BT24) -> 10468.315 | BV24: =+'Purchase-Expenses-AP Schedule'!F140 -> 304.24507 | BW24: =+'Purchase-Expenses-AP Schedule'!G140 -> 304.24507 | BX24: =+'Purchase-Expenses-AP Schedule'!H140 -> 304.24507 | BY24: =+'Purchase-Expenses-AP Schedule'!I140 -> 304.24507 | BZ24: =+'Purchase-Expenses-AP Schedule'!J140 -> 304.24507 | CA24: =+'Purchase-Expenses-AP Schedule'!K140 -> 304.24507 | CB24: =+'Purchase-Expenses-AP Schedule'!L140 -> 304.24507 | CC24: =+'Purchase-Expenses-AP Schedule'!M140 -> 304.24507 | ... CG24: =+'Purchase-Expenses-AP Schedule'!Q140 -> 304.24507 | CH24: =SUM(BV24:CG24) -> 3650.9408 | CI24: =+'Purchase-Expenses-AP Schedule'!F142 -> 304.24507 | CJ24: =+'Purchase-Expenses-AP Schedule'!G142 -> 304.24507 | CK24: =+'Purchase-Expenses-AP Schedule'!H142 -> 304.24507 | CL24: =+'Purchase-Expenses-AP Schedule'!I142 -> 304.24507 | CM24: =+'Purchase-Expenses-AP Schedule'!J142 -> 304.24507 | CN24: =+'Purchase-Expenses-AP Schedule'!K142 -> 304.24507 | CO24: =+'Purchase-Expenses-AP Schedule'!L142 -> 304.24507 | CP24: =+'Purchase-Expenses-AP Schedule'!M142 -> 304.24507 | ... CT24: =+'Purchase-Expenses-AP Schedule'!Q142 -> 304.24507 | CU24: =SUM(CI24:CT24) -> 3650.9408 | CV24: =+'Purchase-Expenses-AP Schedule'!F144 -> 304.24507 | CW24: =+'Purchase-Expenses-AP Schedule'!G144 -> 304.24507 | CX24: =+'Purchase-Expenses-AP Schedule'!H144 -> 304.24507 | CY24: =+'Purchase-Expenses-AP Schedule'!I144 -> 304.24507 | CZ24: =+'Purchase-Expenses-AP Schedule'!J144 -> 304.24507 | DA24: =+'Purchase-Expenses-AP Schedule'!K144 -> 304.24507 | DB24: =+'Purchase-Expenses-AP Schedule'!L144 -> 304.24507 | DC24: =+'Purchase-Expenses-AP Schedule'!M144 -> 304.24507 | ... DG24: =+'Purchase-Expenses-AP Schedule'!Q144 -> 304.24507 | DH24: =SUM(CV24:DG24) -> 3650.9408 | DI24: =+'Purchase-Expenses-AP Schedule'!F146 -> 304.24507 | DJ24: =+'Purchase-Expenses-AP Schedule'!G146 -> 304.24507 | DK24: =+'Purchase-Expenses-AP Schedule'!H146 -> 304.24507 | DL24: =+'Purchase-Expenses-AP Schedule'!I146 -> 304.24507 | DM24: =+'Purchase-Expenses-AP Schedule'!J146 -> 304.24507 | DN24: =+'Purchase-Expenses-AP Schedule'!K146 -> 304.24507 | DO24: =+'Purchase-Expenses-AP Schedule'!L146 -> 304.24507 | DP24: =+'Purchase-Expenses-AP Schedule'!M146 -> 304.24507 | ... DT24: =+'Purchase-Expenses-AP Schedule'!Q146 -> 304.24507 | DU24: =SUM(DI24:DT24) -> 3650.9408 | DV24: =+'Purchase-Expenses-AP Schedule'!F148 -> 304.24507 | DW24: =+'Purchase-Expenses-AP Schedule'!G148 -> 304.24507 | DX24: =+'Purchase-Expenses-AP Schedule'!H148 -> 304.24507 | DY24: =+'Purchase-Expenses-AP Schedule'!I148 -> 304.24507 | DZ24: =+'Purchase-Expenses-AP Schedule'!J148 -> 304.24507 | EA24: =+'Purchase-Expenses-AP Schedule'!K148 -> 304.24507 | EB24: =+'Purchase-Expenses-AP Schedule'!L148 -> 304.24507 | EC24: =+'Purchase-Expenses-AP Schedule'!M148 -> 304.24507 | ... EG24: =+'Purchase-Expenses-AP Schedule'!Q148 -> 304.24507 | EH24: =SUM(DV24:EG24) -> 3650.9408
D25: =D24+1 -> 17 | F25: Payments of Provision for LC | G25: =Assumption!G198 -> 0.01 | I25: =+$G$25*I17 -> 0 | J25: =+$G$25*J17 -> 0 | K25: =+$G$25*K17 -> 0 | L25: =+$G$25*L17 -> 0 | M25: =+$G$25*M17 -> 0 | N25: =+$G$25*N17 -> 0 | O25: =+$G$25*O17 -> 0 | P25: =+$G$25*P17 -> 0 | ... T25: =+$G$25*T17 -> 0 | U25: =SUM(I25:T25) -> 0 | V25: =+$G$25*V17 -> 0 | W25: =+$G$25*W17 -> 0 | X25: =+$G$25*X17 -> 0 | Y25: =+$G$25*Y17 -> 0 | Z25: =+$G$25*Z17 -> 0 | AA25: =+$G$25*AA17 -> 0 | AB25: =+$G$25*AB17 -> 0 | AC25: =+$G$25*AC17 -> 0 | ... AG25: =+$G$25*AG17 -> 0 | AH25: =SUM(V25:AG25) -> 0 | AI25: =+$G$25*AI17 -> 0 | AJ25: =+$G$25*AJ17 -> 0 | AK25: =+$G$25*AK17 -> 0 | AL25: =+$G$25*AL17 -> 0 | AM25: =+$G$25*AM17 -> 0 | AN25: =+$G$25*AN17 -> 0 | AO25: =+$G$25*AO17 -> 0 | AP25: =+$G$25*AP17 -> 0 | ... AT25: =+$G$25*AT17 -> 0 | AU25: =SUM(AI25:AT25) -> 0 | AV25: =+$G$25*AV17 -> 0 | AW25: =+$G$25*AW17 -> 0 | AX25: =+$G$25*AX17 -> 0 | AY25: =+$G$25*AY17 -> 0 | AZ25: =+$G$25*AZ17 -> 0 | BA25: =+$G$25*BA17 -> 0 | BB25: =+$G$25*BB17 -> 0 | BC25: =+$G$25*BC17 -> 0 | ... BG25: =+$G$25*BG17 -> 0 | BH25: =SUM(AV25:BG25) -> 0 | BI25: =+$G$25*BI17 -> 0 | BJ25: =+$G$25*BJ17 -> 0 | BK25: =+$G$25*BK17 -> 0 | BL25: =+$G$25*BL17 -> 0 | BM25: =+$G$25*BM17 -> 0 | BN25: =+$G$25*BN17 -> 0 | BO25: =+$G$25*BO17 -> 0 | BP25: =+$G$25*BP17 -> 0 | ... BT25: =+$G$25*BT17 -> 0 | BU25: =SUM(BI25:BT25) -> 0 | BV25: =+$G$25*BV17 -> 0 | BW25: =+$G$25*BW17 -> 0 | BX25: =+$G$25*BX17 -> 0 | BY25: =+$G$25*BY17 -> 0 | BZ25: =+$G$25*BZ17 -> 0 | CA25: =+$G$25*CA17 -> 0 | CB25: =+$G$25*CB17 -> 0 | CC25: =+$G$25*CC17 -> 0 | ... CG25: =+$G$25*CG17 -> 0 | CH25: =SUM(BV25:CG25) -> 0 | CI25: =+$G$25*CI17 -> 0 | CJ25: =+$G$25*CJ17 -> 0 | CK25: =+$G$25*CK17 -> 0 | CL25: =+$G$25*CL17 -> 0 | CM25: =+$G$25*CM17 -> 0 | CN25: =+$G$25*CN17 -> 0 | CO25: =+$G$25*CO17 -> 0 | CP25: =+$G$25*CP17 -> 0 | ... CT25: =+$G$25*CT17 -> 0 | CU25: =SUM(CI25:CT25) -> 0 | CV25: =+$G$25*CV17 -> 0 | CW25: =+$G$25*CW17 -> 0 | CX25: =+$G$25*CX17 -> 0 | CY25: =+$G$25*CY17 -> 0 | CZ25: =+$G$25*CZ17 -> 0 | DA25: =+$G$25*DA17 -> 0 | DB25: =+$G$25*DB17 -> 0 | DC25: =+$G$25*DC17 -> 0 | ... DG25: =+$G$25*DG17 -> 0 | DH25: =SUM(CV25:DG25) -> 0 | DI25: =+$G$25*DI17 -> 0 | DJ25: =+$G$25*DJ17 -> 0 | DK25: =+$G$25*DK17 -> 0 | DL25: =+$G$25*DL17 -> 0 | DM25: =+$G$25*DM17 -> 0 | DN25: =+$G$25*DN17 -> 0 | DO25: =+$G$25*DO17 -> 0 | DP25: =+$G$25*DP17 -> 0 | ... DT25: =+$G$25*DT17 -> 0 | DU25: =SUM(DI25:DT25) -> 0 | DV25: =+$G$25*DV17 -> 0 | DW25: =+$G$25*DW17 -> 0 | DX25: =+$G$25*DX17 -> 0 | DY25: =+$G$25*DY17 -> 0 | DZ25: =+$G$25*DZ17 -> 0 | EA25: =+$G$25*EA17 -> 0 | EB25: =+$G$25*EB17 -> 0 | EC25: =+$G$25*EC17 -> 0 | ... EG25: =+$G$25*EG17 -> 0 | EH25: =SUM(DV25:EG25) -> 0
F26: Payments of TR Interest | G26: =Assumption!G199 -> 0.1 | I26: =(Assumption!$K$198/Assumption!$K$199)*(CF!$G$26/12)*CF!H19 -> 13.76875 | J26: =(Assumption!$K$198/Assumption!$K$199)*(CF!$G$26/12)*CF!I19 -> 13.76875 | K26: =(Assumption!$K$198/Assumption!$K$199)*(CF!$G$26/12)*CF!J19 -> 13.76875 | L26: =(Assumption!$K$198/Assumption!$K$199)*(CF!$G$26/12)*CF!K19 -> 13.76875 | M26: =(Assumption!$K$198/Assumption!$K$199)*(CF!$G$26/12)*CF!L19 -> 13.76875 | N26: =(Assumption!$K$198/Assumption!$K$199)*(CF!$G$26/12)*CF!M19 -> 13.76875 | O26: =(Assumption!$K$198/Assumption!$K$199)*(CF!$G$26/12)*CF!N19 -> 13.76875 | P26: =(Assumption!$K$198/Assumption!$K$199)*(CF!$G$26/12)*CF!O19 -> 10.326563 | ... T26: =(Assumption!$K$198/Assumption!$K$199)*(CF!$G$26/12)*CF!S19 -> 0 | U26: =SUM(I26:T26) -> 117.03437 | V26: =(Assumption!$K$198/Assumption!$K$199)*(CF!$G$26/12)*CF!U19 -> 0 | W26: =(Assumption!$K$198/Assumption!$K$199)*(CF!$G$26/12)*CF!V19 -> 0 | X26: =(Assumption!$K$198/Assumption!$K$199)*(CF!$G$26/12)*CF!W19 -> 0 | Y26: =(Assumption!$K$198/Assumption!$K$199)*(CF!$G$26/12)*CF!X19 -> 0 | Z26: =(Assumption!$K$198/Assumption!$K$199)*(CF!$G$26/12)*CF!Y19 -> 0 | AA26: =(Assumption!$K$198/Assumption!$K$199)*(CF!$G$26/12)*CF!Z19 -> 0 | AB26: =(Assumption!$K$198/Assumption!$K$199)*(CF!$G$26/12)*CF!AA19 -> 0 | AC26: =(Assumption!$K$198/Assumption!$K$199)*(CF!$G$26/12)*CF!AB19 -> 0 | ... AG26: =(Assumption!$K$198/Assumption!$K$199)*(CF!$G$26/12)*CF!AF19 -> 0 | AH26: =SUM(V26:AG26) -> 0 | AI26: =(Assumption!$K$198/Assumption!$K$199)*(CF!$G$26/12)*CF!AH19 -> 0 | AJ26: =(Assumption!$K$198/Assumption!$K$199)*(CF!$G$26/12)*CF!AI19 -> 0 | AK26: =(Assumption!$K$198/Assumption!$K$199)*(CF!$G$26/12)*CF!AJ19 -> 0 | AL26: =(Assumption!$K$198/Assumption!$K$199)*(CF!$G$26/12)*CF!AK19 -> 0 | AM26: =(Assumption!$K$198/Assumption!$K$199)*(CF!$G$26/12)*CF!AL19 -> 0 | AN26: =(Assumption!$K$198/Assumption!$K$199)*(CF!$G$26/12)*CF!AM19 -> 0 | AO26: =(Assumption!$K$198/Assumption!$K$199)*(CF!$G$26/12)*CF!AN19 -> 0 | AP26: =(Assumption!$K$198/Assumption!$K$199)*(CF!$G$26/12)*CF!AO19 -> 0 | ... AT26: =(Assumption!$K$198/Assumption!$K$199)*(CF!$G$26/12)*CF!AS19 -> 0 | AU26: =SUM(AI26:AT26) -> 0 | AV26: =(Assumption!$K$198/Assumption!$K$199)*(CF!$G$26/12)*CF!AU19 -> 0 | AW26: =(Assumption!$K$198/Assumption!$K$199)*(CF!$G$26/12)*CF!AV19 -> 0 | AX26: =(Assumption!$K$198/Assumption!$K$199)*(CF!$G$26/12)*CF!AW19 -> 0 | AY26: =(Assumption!$K$198/Assumption!$K$199)*(CF!$G$26/12)*CF!AX19 -> 0 | AZ26: =(Assumption!$K$198/Assumption!$K$199)*(CF!$G$26/12)*CF!AY19 -> 0 | BA26: =(Assumption!$K$198/Assumption!$K$199)*(CF!$G$26/12)*CF!AZ19 -> 0 | BB26: =(Assumption!$K$198/Assumption!$K$199)*(CF!$G$26/12)*CF!BA19 -> 0 | BC26: =(Assumption!$K$198/Assumption!$K$199)*(CF!$G$26/12)*CF!BB19 -> 0 | ... BG26: =(Assumption!$K$198/Assumption!$K$199)*(CF!$G$26/12)*CF!BF19 -> 0 | BH26: =SUM(AV26:BG26) -> 0 | BI26: =(Assumption!$K$198/Assumption!$K$199)*(CF!$G$26/12)*CF!BH19 -> 0 | BJ26: =(Assumption!$K$198/Assumption!$K$199)*(CF!$G$26/12)*CF!BI19 -> 0 | BK26: =(Assumption!$K$198/Assumption!$K$199)*(CF!$G$26/12)*CF!BJ19 -> 0 | BL26: =(Assumption!$K$198/Assumption!$K$199)*(CF!$G$26/12)*CF!BK19 -> 0 | BM26: =(Assumption!$K$198/Assumption!$K$199)*(CF!$G$26/12)*CF!BL19 -> 0 | BN26: =(Assumption!$K$198/Assumption!$K$199)*(CF!$G$26/12)*CF!BM19 -> 0 | BO26: =(Assumption!$K$198/Assumption!$K$199)*(CF!$G$26/12)*CF!BN19 -> 0 | BP26: =(Assumption!$K$198/Assumption!$K$199)*(CF!$G$26/12)*CF!BO19 -> 0 | ... BT26: =(Assumption!$K$198/Assumption!$K$199)*(CF!$G$26/12)*CF!BS19 -> 0 | BU26: =SUM(BI26:BT26) -> 0
B27: =IF(Assumption!K199=0,0,+Assumption!K198/Assumption!K199) -> 0.75 | D27: =D25+1 -> 18 | F27: Payments of Short Term Bank Loan Interest | I27: =+I218 -> 0 | J27: =+J218 -> 0 | K27: =+K218 -> 0 | L27: =+L218 -> 0 | M27: =+M218 -> 0 | N27: =+N218 -> 0 | O27: =+O218 -> 37.721667 | P27: =+P218 -> 433.55697 | ... T27: =+T218 -> 549.15406 | U27: =SUM(I27:T27) -> 2500.5846 | V27: =+V218 -> 586.01443 | W27: =+W218 -> 610.21539 | X27: =+X218 -> 564.55755 | Y27: =+Y218 -> 562.09541 | Z27: =+Z218 -> 571.77113 | AA27: =+AA218 -> 563.47543 | AB27: =+AB218 -> 553.65426 | AC27: =+AC218 -> 544.09501 | ... AG27: =+AG218 -> 526.15272 | AH27: =SUM(V27:AG27) -> 6709.813 | AI27: =+AI218 -> 493.90404 | AJ27: =+AJ218 -> 502.72645 | AK27: =+AK218 -> 447.81355 | AL27: =+AL218 -> 437.32419 | AM27: =+AM218 -> 442.7239 | AN27: =+AN218 -> 428.30598 | AO27: =+AO218 -> 412.39853 | AP27: =+AP218 -> 396.73703 | ... AT27: =+AT218 -> 355.73623 | AU27: =SUM(AI27:AT27) -> 5070.425 | AV27: =+AV218 -> 314.89663 | AW27: =+AW218 -> 323.16386 | AX27: =+AX218 -> 261.47832 | AY27: =+AY218 -> 251.76931 | AZ27: =+AZ218 -> 256.4322 | BA27: =+BA218 -> 239.28507 | BB27: =+BB218 -> 220.48872 | BC27: =+BC218 -> 201.95211 | ... BG27: =+BG218 -> 151.50536 | BH27: =SUM(AV27:BG27) -> 2777.6629 | BI27: =+BI218 -> 105.21738 | BJ27: =+BJ218 -> 112.88069 | BK27: =+BK218 -> 43.584041 | BL27: =+BL218 -> 31.44955 | BM27: =+BM218 -> 35.11203 | BN27: =+BN218 -> 21.03 | BO27: =+BO218 -> 21.03 | BP27: =+BP218 -> 21.03 | ... BT27: =+BT218 -> 21.03 | BU27: =SUM(BI27:BT27) -> 475.45369 | BV27: =+BV218 -> 21.03 | BW27: =+BW218 -> 21.03 | BX27: =+BX218 -> 21.03 | BY27: =+BY218 -> 21.03 | BZ27: =+BZ218 -> 21.03 | CA27: =+CA218 -> 21.03 | CB27: =+CB218 -> 21.03 | CC27: =+CC218 -> 21.03 | ... CG27: =+CG218 -> 21.03 | CH27: =SUM(BV27:CG27) -> 252.36 | CI27: =+CI218 -> 21.03 | CJ27: =+CJ218 -> 21.03 | CK27: =+CK218 -> 21.03 | CL27: =+CL218 -> 21.03 | CM27: =+CM218 -> 21.03 | CN27: =+CN218 -> 21.03 | CO27: =+CO218 -> 21.03 | CP27: =+CP218 -> 21.03 | ... CT27: =+CT218 -> 21.03 | CU27: =SUM(CI27:CT27) -> 252.36 | CV27: =+CV218 -> 21.03 | CW27: =+CW218 -> 21.03 | CX27: =+CX218 -> 21.03 | CY27: =+CY218 -> 21.03 | CZ27: =+CZ218 -> 21.03 | DA27: =+DA218 -> 21.03 | DB27: =+DB218 -> 21.03 | DC27: =+DC218 -> 21.03 | ... DG27: =+DG218 -> 21.03 | DH27: =SUM(CV27:DG27) -> 252.36 | DI27: =+DI218 -> 21.03 | DJ27: =+DJ218 -> 21.03 | DK27: =+DK218 -> 21.03 | DL27: =+DL218 -> 21.03 | DM27: =+DM218 -> 21.03 | DN27: =+DN218 -> 21.03 | DO27: =+DO218 -> 21.03 | DP27: =+DP218 -> 21.03 | ... DT27: =+DT218 -> 21.03 | DU27: =SUM(DI27:DT27) -> 252.36 | DV27: =+DV218 -> 21.03 | DW27: =+DW218 -> 21.03 | DX27: =+DX218 -> 21.03 | DY27: =+DY218 -> 21.03 | DZ27: =+DZ218 -> 21.03 | EA27: =+EA218 -> 21.03 | EB27: =+EB218 -> 21.03 | EC27: =+EC218 -> 21.03 | ... EG27: =+EG218 -> 21.03 | EH27: =SUM(DV27:EG27) -> 252.36
D28: =D27+1 -> 19 | F28: Payments of Long Term Bank Loan Interest | I28: =+I257 -> 0 | J28: =+J257 -> 0 | K28: =+K257 -> 0 | L28: =+L257 -> 0 | M28: =+M257 -> 0 | N28: =+N257 -> 0 | O28: =+O257 -> 341.12333 | P28: =+P257 -> 341.12333 | ... T28: =+T257 -> 341.12333 | U28: =SUM(I28:T28) -> 2046.74 | V28: =+V257 -> 340.50667 | W28: =+W257 -> 340.50667 | X28: =+X257 -> 340.50667 | Y28: =+Y257 -> 340.50667 | Z28: =+Z257 -> 340.50667 | AA28: =+AA257 -> 340.50667 | AB28: =+AB257 -> 340.50667 | AC28: =+AC257 -> 340.50667 | ... AG28: =+AG257 -> 340.50667 | AH28: =SUM(V28:AG28) -> 4086.08 | AI28: =+AI257 -> 340.50667 | AJ28: =+AJ257 -> 340.50667 | AL28: =+AL257 -> 340.50667 | AM28: =+AM257 -> 340.50667 | AN28: =+AN257 -> 340.50667 | AO28: =+AO257 -> 340.50667 | AP28: =+AP257 -> 340.50667 | AQ28: =+AQ257 -> 340.50667 | AR28: =+AR257 -> 340.50667 | AS28: =+AS257 -> 340.50667 | AT28: =+AT257 -> 340.50667 | AU28: =SUM(AI28:AT28) -> 3745.5733 | AV28: =+AV257 -> 340.50667 | AW28: =+AW257 -> 340.50667 | AX28: =+AX257 -> 340.50667 | AY28: =+AY257 -> 340.50667 | AZ28: =+AZ257 -> 340.50667 | BA28: =+BA257 -> 340.50667 | BB28: =+BB257 -> 340.50667 | BC28: =+BC257 -> 340.50667 | ... BG28: =+BG257 -> 340.50667 | BH28: =SUM(AV28:BG28) -> 4086.08 | BI28: =+BI257 -> 340.50667 | BJ28: =+BJ257 -> 340.50667 | BK28: =+BK257 -> 340.50667 | BL28: =+BL257 -> 340.50667 | BM28: =+BM257 -> 340.50667 | BN28: =+BN257 -> 340.50667 | BO28: =+BO257 -> 340.50667 | BP28: =+BP257 -> 340.50667 | ... BT28: =+BT257 -> 340.50667 | BU28: =SUM(BI28:BT28) -> 4086.08 | BV28: =+BV257 -> 340.50667 | BW28: =+BW257 -> 340.50667 | BX28: =+BX257 -> 340.50667 | BY28: =+BY257 -> 340.50667 | BZ28: =+BZ257 -> 340.50667 | CA28: =+CA257 -> 340.50667 | CB28: =+CB257 -> 340.50667 | CC28: =+CC257 -> 340.50667 | ... CG28: =+CG257 -> 340.50667 | CH28: =SUM(BV28:CG28) -> 4086.08 | CI28: =+CI257 -> 340.50667 | CJ28: =+CJ257 -> 340.50667 | CK28: =+CK257 -> 340.50667 | CL28: =+CL257 -> 340.50667 | CM28: =+CM257 -> 340.50667 | CN28: =+CN257 -> 340.50667 | CO28: =+CO257 -> 340.50667 | CP28: =+CP257 -> 340.50667 | ... CT28: =+CT257 -> 340.50667 | CU28: =SUM(CI28:CT28) -> 4086.08 | CV28: =+CV257 -> 340.50667 | CW28: =+CW257 -> 340.50667 | CX28: =+CX257 -> 340.50667 | CY28: =+CY257 -> 340.50667 | CZ28: =+CZ257 -> 340.50667 | DA28: =+DA257 -> 340.50667 | DB28: =+DB257 -> 340.50667 | DC28: =+DC257 -> 340.50667 | ... DG28: =+DG257 -> 340.50667 | DH28: =SUM(CV28:DG28) -> 4086.08 | DI28: =+DI257 -> 340.50667 | DJ28: =+DJ257 -> 340.50667 | DK28: =+DK257 -> 340.50667 | DL28: =+DL257 -> 340.50667 | DM28: =+DM257 -> 340.50667 | DN28: =+DN257 -> 340.50667 | DO28: =+DO257 -> 340.50667 | DP28: =+DP257 -> 340.50667 | ... DT28: =+DT257 -> 340.50667 | DU28: =SUM(DI28:DT28) -> 4086.08 | DV28: =+DV257 -> 340.50667 | DW28: =+DW257 -> 340.50667 | DX28: =+DX257 -> 340.50667 | DY28: =+DY257 -> 340.50667 | DZ28: =+DZ257 -> 340.50667 | EA28: =+EA257 -> 340.50667 | EB28: =+EB257 -> 340.50667 | EC28: =+EC257 -> 340.50667 | ... EG28: =+EG257 -> 340.50667 | EH28: =SUM(DV28:EG28) -> 4086.08
D29: =D28+1 -> 20 | F29: Payments of all in fee (Provision, Commitment Fee, Service Fee) | T29: 10 | U29: =SUM(I29:T29) -> 10 | AH29: =SUM(V29:AG29) -> 0 | AP29: 0 | AU29: =SUM(AI29:AT29) -> 0 | BH29: =SUM(AV29:BG29) -> 0 | BU29: =SUM(BI29:BT29) -> 0 | CH29: =SUM(BV29:CG29) -> 0 | CU29: =SUM(CI29:CT29) -> 0 | DH29: =SUM(CV29:DG29) -> 0 | DU29: =SUM(DI29:DT29) -> 0 | EH29: =SUM(DV29:EG29) -> 0
D30: =D29+1 -> 21 | F30: Payments of Tax | H30: =25%*(Historical!K105-Historical!K105) -> 0 | I30: =+IF(I10=0,0,Historical!$K$120/SUM($I$4:$T$4)) -> 0 | J30: =+IF(J10=0,0,Historical!$K$120/SUM($I$4:$T$4)) -> 0 | K30: =+IF(K10=0,0,Historical!$K$120/SUM($I$4:$T$4)) -> 0 | L30: =+IF(L10=0,0,Historical!$K$120/SUM($I$4:$T$4)) -> 0 | M30: =+IF(M10=0,0,Historical!$K$120/SUM($I$4:$T$4)) -> 0 | N30: =+IF(N10=0,0,Historical!$K$120/SUM($I$4:$T$4)) -> 0 | O30: =+IF(O10=0,0,Historical!$K$120/SUM($I$4:$T$4)) -> 1500 | P30: =+IF(P10=0,0,Historical!$K$120/SUM($I$4:$T$4)) -> 1500 | ... T30: =+IF(T10=0,0,Historical!$K$120/SUM($I$4:$T$4)) -> 1500 | U30: =SUM(I30:T30) -> 9000 | V30: =+Projection!L89/12 -> 750 | W30: =+Projection!L89/12 -> 750 | X30: =+Projection!L89/12 -> 750 | Y30: =+Projection!L89/12 -> 750 | Z30: =+Projection!L89/12 -> 750 | AA30: =+Projection!L89/12 -> 750 | AB30: =+Projection!L89/12 -> 750 | AC30: =+Projection!L89/12 -> 750 | AD30: =+Projection!L89/12 -> 750 | AE30: =+Projection!L89/12 -> 750 | AF30: =+Projection!L89/12 -> 750 | AG30: =+Projection!L89/12 -> 750 | AH30: =SUM(V30:AG30) -> 9000 | AI30: =+Projection!N89/12 -> 554.38854 | AJ30: =+Projection!N89/12 -> 554.38854 | AK30: =+Projection!N89/12 -> 554.38854 | AL30: =+Projection!N89/12 -> 554.38854 | AM30: =+Projection!N89/12 -> 554.38854 | AN30: =+Projection!N89/12 -> 554.38854 | AO30: =+Projection!N89/12 -> 554.38854 | AP30: =+Projection!N89/12 -> 554.38854 | AQ30: =+Projection!N89/12 -> 554.38854 | AR30: =+Projection!N89/12 -> 554.38854 | AS30: =+Projection!N89/12 -> 554.38854 | AT30: =+Projection!N89/12 -> 554.38854 | AU30: =SUM(AI30:AT30) -> 6652.6624 | AV30: =+Projection!P89/12 -> 719.95151 | AW30: =+Projection!P89/12 -> 719.95151 | AX30: =+Projection!P89/12 -> 719.95151 | AY30: =+Projection!P89/12 -> 719.95151 | AZ30: =+Projection!P89/12 -> 719.95151 | BA30: =+Projection!P89/12 -> 719.95151 | BB30: =+Projection!P89/12 -> 719.95151 | BC30: =+Projection!P89/12 -> 719.95151 | BD30: =+Projection!P89/12 -> 719.95151 | BE30: =+Projection!P89/12 -> 719.95151 | BF30: =+Projection!P89/12 -> 719.95151 | BG30: =+Projection!P89/12 -> 719.95151 | BH30: =SUM(AV30:BG30) -> 8639.4181 | BI30: =+Projection!R89/12 -> 895.48994 | BJ30: =+Projection!R89/12 -> 895.48994 | BK30: =+Projection!R89/12 -> 895.48994 | BL30: =+Projection!R89/12 -> 895.48994 | BM30: =+Projection!R89/12 -> 895.48994 | BN30: =+Projection!R89/12 -> 895.48994 | BO30: =+Projection!R89/12 -> 895.48994 | BP30: =+Projection!R89/12 -> 895.48994 | BQ30: =+Projection!R89/12 -> 895.48994 | BR30: =+Projection!R89/12 -> 895.48994 | BS30: =+Projection!R89/12 -> 895.48994 | BT30: =+Projection!R89/12 -> 895.48994 | BU30: =SUM(BI30:BT30) -> 10745.879 | BV30: =+Projection!T89/12 -> 1093.0951 | BW30: =+BV30 -> 1093.0951 | BX30: =+BW30 -> 1093.0951 | BY30: =+BX30 -> 1093.0951 | BZ30: =+BY30 -> 1093.0951 | CA30: =+BZ30 -> 1093.0951 | CB30: =+CA30 -> 1093.0951 | CC30: =+CB30 -> 1093.0951 | CD30: =+CC30 -> 1093.0951 | ... CG30: =+CF30 -> 1093.0951 | CH30: =SUM(BV30:CG30) -> 13117.141 | CI30: =Projection!Z89/12 -> 217.78489 | CJ30: =+CI30 -> 217.78489 | CK30: =+CJ30 -> 217.78489 | CL30: =+CK30 -> 217.78489 | CM30: =+CL30 -> 217.78489 | CN30: =+CM30 -> 217.78489 | CO30: =+CN30 -> 217.78489 | CP30: =+CO30 -> 217.78489 | CQ30: =+CP30 -> 217.78489 | ... CT30: =+CS30 -> 217.78489 | CU30: =SUM(CI30:CT30) -> 2613.4187 | CV30: =Projection!AB89/12 -> 217.78489 | CW30: =+CV30 -> 217.78489 | CX30: =+CW30 -> 217.78489 | CY30: =+CX30 -> 217.78489 | CZ30: =+CY30 -> 217.78489 | DA30: =+CZ30 -> 217.78489 | DB30: =+DA30 -> 217.78489 | DC30: =+DB30 -> 217.78489 | DD30: =+DC30 -> 217.78489 | ... DG30: =+DF30 -> 217.78489 | DH30: =SUM(CV30:DG30) -> 2613.4187 | DI30: =Projection!AD89/12 -> 217.78489 | DJ30: =+DI30 -> 217.78489 | DK30: =+DJ30 -> 217.78489 | DL30: =+DK30 -> 217.78489 | DM30: =+DL30 -> 217.78489 | DN30: =+DM30 -> 217.78489 | DO30: =+DN30 -> 217.78489 | DP30: =+DO30 -> 217.78489 | DQ30: =+DP30 -> 217.78489 | ... DT30: =+DS30 -> 217.78489 | DU30: =SUM(DI30:DT30) -> 2613.4187 | DV30: =Projection!AF89/12 -> 217.78489 | DW30: =+DV30 -> 217.78489 | DX30: =+DW30 -> 217.78489 | DY30: =+DX30 -> 217.78489 | DZ30: =+DY30 -> 217.78489 | EA30: =+DZ30 -> 217.78489 | EB30: =+EA30 -> 217.78489 | EC30: =+EB30 -> 217.78489 | ED30: =+EC30 -> 217.78489 | ... EG30: =+EF30 -> 217.78489 | EH30: =SUM(DV30:EG30) -> 2613.4187
D31: =D30+1 -> 22 | F31: =+" (Payments of) / Additions to "&Historical!C21 -> (Payments of) / Additions to Prepaid Taxes | H31: =Historical!K21 -> 603 | T31: 20 | U31: =(SUM(I31:T31)) -> 20 | AH31: =(SUM(V31:AG31)) -> 0 | AU31: =(SUM(AI31:AT31)) -> 0 | BH31: =(SUM(AV31:BG31)) -> 0 | BU31: =(SUM(BI31:BT31)) -> 0 | CH31: =(SUM(BV31:CG31)) -> 0 | CU31: =(SUM(CI31:CT31)) -> 0 | DH31: =(SUM(CV31:DG31)) -> 0 | DU31: =(SUM(DI31:DT31)) -> 0 | EH31: =(SUM(DV31:EG31)) -> 0
D32: =D31+1 -> 23 | F32: =+" (Payments of) / Additions to "&Historical!C22 -> (Payments of) / Additions to Prepaid Expenses | T32: 30 | U32: =(SUM(I32:T32)) -> 30 | AH32: =(SUM(V32:AG32)) -> 0 | AU32: =(SUM(AI32:AT32)) -> 0 | BH32: =(SUM(AV32:BG32)) -> 0 | BU32: =(SUM(BI32:BT32)) -> 0 | CH32: =(SUM(BV32:CG32)) -> 0 | CU32: =(SUM(CI32:CT32)) -> 0 | DH32: =(SUM(CV32:DG32)) -> 0 | DU32: =(SUM(DI32:DT32)) -> 0 | EH32: =(SUM(DV32:EG32)) -> 0
D33: =D32+1 -> 24 | F33: =+" (Payments of) / Additions to "&Historical!C23 -> (Payments of) / Additions to Advance Payments | H33: =Historical!K23 -> 803 | T33: 40 | U33: =(SUM(I33:T33)) -> 40 | AH33: =(SUM(V33:AG33)) -> 0 | AU33: =(SUM(AI33:AT33)) -> 0 | BH33: =(SUM(AV33:BG33)) -> 0 | BU33: =(SUM(BI33:BT33)) -> 0 | CH33: =(SUM(BV33:CG33)) -> 0 | CU33: =(SUM(CI33:CT33)) -> 0 | DH33: =(SUM(CV33:DG33)) -> 0 | DU33: =(SUM(DI33:DT33)) -> 0 | EH33: =(SUM(DV33:EG33)) -> 0
D34: =D33+1 -> 25 | F34: =+" (Payments of) / Additions to "&Historical!C24 -> (Payments of) / Additions to Other Current Assets | H34: =Historical!K24 -> 903 | T34: 50 | U34: =(SUM(I34:T34)) -> 50 | AH34: =(SUM(V34:AG34)) -> 0 | AU34: =(SUM(AI34:AT34)) -> 0 | BH34: =(SUM(AV34:BG34)) -> 0 | BU34: =(SUM(BI34:BT34)) -> 0 | CH34: =(SUM(BV34:CG34)) -> 0 | CU34: =(SUM(CI34:CT34)) -> 0 | DH34: =(SUM(CV34:DG34)) -> 0 | DU34: =(SUM(DI34:DT34)) -> 0 | EH34: =(SUM(DV34:EG34)) -> 0
D35: =D34+1 -> 26 | F35: =+" (Payments of) / Additions to "&Historical!C41 -> (Payments of) / Additions to Shareholder & Related Parties Loans- Short Term | H35: =+Historical!K41 -> 2603 | T35: 10 | U35: =-1*(SUM(I35:T35)) -> -10 | AH35: =-1*(SUM(V35:AG35)) -> 0 | AU35: =-1*(SUM(AI35:AT35)) -> 0 | BH35: =-1*(SUM(AV35:BG35)) -> 0 | BU35: =-1*(SUM(BI35:BT35)) -> 0 | CH35: =-1*(SUM(BV35:CG35)) -> 0 | CU35: =-1*(SUM(CI35:CT35)) -> 0 | DH35: =-1*(SUM(CV35:DG35)) -> 0 | DU35: =-1*(SUM(DI35:DT35)) -> 0 | EH35: =-1*(SUM(DV35:EG35)) -> 0
D36: =D35+1 -> 27 | F36: =+" (Payments of) / Additions to "&Historical!C42 -> (Payments of) / Additions to Accrued Expenses | H36: =+Historical!K42 -> 2703 | T36: 20 | U36: =-1*(SUM(I36:T36)) -> -20 | AH36: =-1*(SUM(V36:AG36)) -> 0 | AU36: =-1*(SUM(AI36:AT36)) -> 0 | BH36: =-1*(SUM(AV36:BG36)) -> 0 | BU36: =-1*(SUM(BI36:BT36)) -> 0 | CH36: =-1*(SUM(BV36:CG36)) -> 0 | CU36: =-1*(SUM(CI36:CT36)) -> 0 | DH36: =-1*(SUM(CV36:DG36)) -> 0 | DU36: =-1*(SUM(DI36:DT36)) -> 0 | EH36: =-1*(SUM(DV36:EG36)) -> 0
D37: =D36+1 -> 28 | F37: =+" (Payments of) / Additions to "&Historical!C43 -> (Payments of) / Additions to Customer Advances | T37: 30 | U37: =-1*(SUM(I37:T37)) -> -30 | AH37: =-1*(SUM(V37:AG37)) -> 0 | AU37: =-1*(SUM(AI37:AT37)) -> 0 | BH37: =-1*(SUM(AV37:BG37)) -> 0 | BU37: =-1*(SUM(BI37:BT37)) -> 0 | CH37: =-1*(SUM(BV37:CG37)) -> 0 | CU37: =-1*(SUM(CI37:CT37)) -> 0 | DH37: =-1*(SUM(CV37:DG37)) -> 0 | DU37: =-1*(SUM(DI37:DT37)) -> 0 | EH37: =-1*(SUM(DV37:EG37)) -> 0
D38: =D37+1 -> 29 | F38: =+" (Payments of) / Additions to "&Historical!C44 -> (Payments of) / Additions to Deferred Liabilities | T38: 40 | U38: =-1*(SUM(I38:T38)) -> -40 | AH38: =-1*(SUM(V38:AG38)) -> 0 | AU38: =-1*(SUM(AI38:AT38)) -> 0 | BH38: =-1*(SUM(AV38:BG38)) -> 0 | BU38: =-1*(SUM(BI38:BT38)) -> 0 | CH38: =-1*(SUM(BV38:CG38)) -> 0 | CU38: =-1*(SUM(CI38:CT38)) -> 0 | DH38: =-1*(SUM(CV38:DG38)) -> 0 | DU38: =-1*(SUM(DI38:DT38)) -> 0 | EH38: =-1*(SUM(DV38:EG38)) -> 0
D39: =D38+1 -> 30 | F39: TOTAL OPERATING CASH OUTFLOWS | I39: =SUM(I20:I38) -> 2416.7688 | J39: =SUM(J20:J38) -> 13.76875 | K39: =SUM(K20:K38) -> 13.76875 | L39: =SUM(L20:L38) -> 13.76875 | M39: =SUM(M20:M38) -> 13.76875 | N39: =SUM(N20:N38) -> 13.76875 | O39: =SUM(O20:O38) -> 3416.5095 | P39: =SUM(P20:P38) -> 7037.1495 | ... EH39: =SUM(EH20:EH38) -> 154321.88
D40: =D39+1 -> 31 | E40: Arus Kas Masuk Non Operasional | F40: =+" Sales of "&Historical!C18 -> Sales of Short Term Investments | T40: 10 | U40: =SUM(I40:T40) -> 10 | AH40: =SUM(V40:AG40) -> 0 | AU40: =SUM(AI40:AT40) -> 0 | BH40: =SUM(AV40:BG40) -> 0 | BU40: =SUM(BI40:BT40) -> 0 | CH40: =SUM(BV40:CG40) -> 0 | CU40: =SUM(CI40:CT40) -> 0 | DH40: =SUM(CV40:DG40) -> 0 | DU40: =SUM(DI40:DT40) -> 0 | EH40: =SUM(DV40:EG40) -> 0
D41: =D40+1 -> 32 | F41: =+" Sales of "&Historical!C26 -> Sales of Fixed Assets | T41: 20 | U41: =SUM(I41:T41) -> 20 | AH41: =SUM(V41:AG41) -> 0 | AU41: =SUM(AI41:AT41) -> 0 | BH41: =SUM(AV41:BG41) -> 0 | BU41: =SUM(BI41:BT41) -> 0 | CH41: =SUM(BV41:CG41) -> 0 | CU41: =SUM(CI41:CT41) -> 0 | DH41: =SUM(CV41:DG41) -> 0 | DU41: =SUM(DI41:DT41) -> 0 | EH41: =SUM(DV41:EG41) -> 0
D42: =D41+1 -> 33 | F42: =+" Sales of "&Historical!C27 -> Sales of Investment in Associates | T42: 30 | U42: =SUM(I42:T42) -> 30 | AH42: =SUM(V42:AG42) -> 0 | AU42: =SUM(AI42:AT42) -> 0 | BH42: =SUM(AV42:BG42) -> 0 | BU42: =SUM(BI42:BT42) -> 0 | CH42: =SUM(BV42:CG42) -> 0 | CU42: =SUM(CI42:CT42) -> 0 | DH42: =SUM(CV42:DG42) -> 0 | DU42: =SUM(DI42:DT42) -> 0 | EH42: =SUM(DV42:EG42) -> 0
D43: =D42+1 -> 34 | F43: =+" Sales of "&Historical!C28 -> Sales of Investment in Joint Venture | T43: 40 | U43: =SUM(I43:T43) -> 40 | AH43: =SUM(V43:AG43) -> 0 | AU43: =SUM(AI43:AT43) -> 0 | BH43: =SUM(AV43:BG43) -> 0 | BU43: =SUM(BI43:BT43) -> 0
D44: =D43+1 -> 35 | F44: =+" Sales of "&Historical!C30 -> Sales of Deferred Taxes | T44: 50 | U44: =SUM(I44:T44) -> 50 | AH44: =SUM(V44:AG44) -> 0 | AU44: =SUM(AI44:AT44) -> 0 | BH44: =SUM(AV44:BG44) -> 0 | BU44: =SUM(BI44:BT44) -> 0 | CH44: =SUM(BV44:CG44) -> 0 | CU44: =SUM(CI44:CT44) -> 0 | DH44: =SUM(CV44:DG44) -> 0 | DU44: =SUM(DI44:DT44) -> 0 | EH44: =SUM(DV44:EG44) -> 0
D45: =D44+1 -> 36 | F45: =+" Sales of "&Historical!C31 -> Sales of Other Non-Current Assets | T45: 10 | U45: =SUM(I45:T45) -> 10 | AH45: =SUM(V45:AG45) -> 0 | AU45: =SUM(AI45:AT45) -> 0 | BH45: =SUM(AV45:BG45) -> 0 | BU45: =SUM(BI45:BT45) -> 0 | CH45: =SUM(BV45:CG45) -> 0 | CU45: =SUM(CI45:CT45) -> 0 | DH45: =SUM(CV45:DG45) -> 0 | DU45: =SUM(DI45:DT45) -> 0 | EH45: =SUM(DV45:EG45) -> 0
D46: =D45+1 -> 37 | F46: =+" Sales of "&Historical!C32 -> Sales of Investments | T46: 20 | U46: =SUM(I46:T46) -> 20 | AH46: =SUM(V46:AG46) -> 0 | AU46: =SUM(AI46:AT46) -> 0 | BH46: =SUM(AV46:BG46) -> 0 | BU46: =SUM(BI46:BT46) -> 0 | CH46: =SUM(BV46:CG46) -> 0 | CU46: =SUM(CI46:CT46) -> 0 | DH46: =SUM(CV46:DG46) -> 0 | DU46: =SUM(DI46:DT46) -> 0 | EH46: =SUM(DV46:EG46) -> 0
D47: =D46+1 -> 38 | F47: =+" Additions to "&Historical!C55 -> Additions to Employee Benefit Liabilities | T47: 30 | U47: =SUM(I47:T47) -> 30 | AH47: =SUM(V47:AG47) -> 0 | AU47: =SUM(AI47:AT47) -> 0 | BH47: =SUM(AV47:BG47) -> 0 | BU47: =SUM(BI47:BT47) -> 0 | CH47: =SUM(BV47:CG47) -> 0 | CU47: =SUM(CI47:CT47) -> 0 | DH47: =SUM(CV47:DG47) -> 0 | DU47: =SUM(DI47:DT47) -> 0 | EH47: =SUM(DV47:EG47) -> 0
D48: =D47+1 -> 39 | F48: =+" Additions to "&Historical!C56 -> Additions to Long Term Tax Payables | T48: 40 | U48: =SUM(I48:T48) -> 40 | AH48: =SUM(V48:AG48) -> 0 | AU48: =SUM(AI48:AT48) -> 0 | BH48: =SUM(AV48:BG48) -> 0 | BU48: =SUM(BI48:BT48) -> 0 | CH48: =SUM(BV48:CG48) -> 0 | CU48: =SUM(CI48:CT48) -> 0 | DH48: =SUM(CV48:DG48) -> 0 | DU48: =SUM(DI48:DT48) -> 0 | EH48: =SUM(DV48:EG48) -> 0
D49: =D48+1 -> 40 | F49: =+" Additions to "&Historical!C57 -> Additions to Shareholders & Related Parties Loan- Long Term | T49: 50 | U49: =SUM(I49:T49) -> 50 | AH49: =SUM(V49:AG49) -> 0 | AU49: =SUM(AI49:AT49) -> 0 | BH49: =SUM(AV49:BG49) -> 0 | BU49: =SUM(BI49:BT49) -> 0 | CH49: =SUM(BV49:CG49) -> 0 | CU49: =SUM(CI49:CT49) -> 0 | DH49: =SUM(CV49:DG49) -> 0 | DU49: =SUM(DI49:DT49) -> 0 | EH49: =SUM(DV49:EG49) -> 0
D50: =D49+1 -> 41 | F50: =+" Additions to "&Historical!C58 -> Additions to Other Non-Current Liabilities | K50: 0 | T50: 10 | U50: =SUM(I50:T50) -> 10 | AH50: =SUM(V50:AG50) -> 0 | AU50: =SUM(AI50:AT50) -> 0 | BH50: =SUM(AV50:BG50) -> 0 | BU50: =SUM(BI50:BT50) -> 0 | CH50: =SUM(BV50:CG50) -> 0 | CU50: =SUM(CI50:CT50) -> 0 | DH50: =SUM(CV50:DG50) -> 0 | DU50: =SUM(DI50:DT50) -> 0 | EH50: =SUM(DV50:EG50) -> 0
D51: =D50+1 -> 42 | F51: Long Term Bank Loan - Other Banks Disbursement | I51: =SUM(I140:I149) -> 0 | J51: =SUM(J140:J149) -> 0 | K51: =SUM(K140:K149) -> 0 | L51: =SUM(L140:L149) -> 0 | M51: =SUM(M140:M149) -> 0 | N51: =SUM(N140:N149) -> 0 | O51: =SUM(O140:O149) -> 0 | P51: =SUM(P140:P149) -> 0 | ... T51: =SUM(T140:T149) -> 300 | U51: =SUM(I51:T51) -> 300 | V51: =SUM(V140:V149) -> 0 | W51: =SUM(W140:W149) -> 0 | X51: =SUM(X140:X149) -> 0 | Y51: =SUM(Y140:Y149) -> 0 | Z51: =SUM(Z140:Z149) -> 0 | AA51: =SUM(AA140:AA149) -> 0 | AB51: =SUM(AB140:AB149) -> 0 | AC51: =SUM(AC140:AC149) -> 0 | ... AG51: =SUM(AG140:AG149) -> 0 | AH51: =SUM(V51:AG51) -> 0 | AI51: =SUM(AI140:AI149) -> 0 | AJ51: =SUM(AJ140:AJ149) -> 0 | AK51: =SUM(AK140:AK149) -> 0 | AL51: =SUM(AL140:AL149) -> 0 | AM51: =SUM(AM140:AM149) -> 0 | AN51: =SUM(AN140:AN149) -> 0 | AO51: =SUM(AO140:AO149) -> 0 | AP51: =SUM(AP140:AP149) -> 0 | ... AT51: =SUM(AT140:AT149) -> 0 | AU51: =SUM(AI51:AT51) -> 0 | AV51: =SUM(AV140:AV149) -> 0 | AW51: =SUM(AW140:AW149) -> 0 | AX51: =SUM(AX140:AX149) -> 0 | AY51: =SUM(AY140:AY149) -> 0 | AZ51: =SUM(AZ140:AZ149) -> 0 | BA51: =SUM(BA140:BA149) -> 0 | BB51: =SUM(BB140:BB149) -> 0 | BC51: =SUM(BC140:BC149) -> 0 | ... BG51: =SUM(BG140:BG149) -> 0 | BH51: =SUM(AV51:BG51) -> 0 | BI51: =SUM(BI140:BI149) -> 0 | BJ51: =SUM(BJ140:BJ149) -> 0 | BK51: =SUM(BK140:BK149) -> 0 | BL51: =SUM(BL140:BL149) -> 0 | BM51: =SUM(BM140:BM149) -> 0 | BN51: =SUM(BN140:BN149) -> 0 | BO51: =SUM(BO140:BO149) -> 0 | BP51: =SUM(BP140:BP149) -> 0 | ... BT51: =SUM(BT140:BT149) -> 0 | BU51: =SUM(BI51:BT51) -> 0 | CH51: =SUM(BV51:CG51) -> 0 | CU51: =SUM(CI51:CT51) -> 0 | DH51: =SUM(CV51:DG51) -> 0 | DU51: =SUM(DI51:DT51) -> 0 | EH51: =SUM(DV51:EG51) -> 0
D52: =D51+1 -> 43 | F52: =+" Additions to "&Historical!C66 -> Additions to Subordinated Shareholders & Related Parties Loan | G52: =+Assumption!H258 -> 0.25 | I52: =+I211 -> 10000 | J52: =+J211 -> 0 | K52: =+K211 -> 0 | L52: =+L211 -> 0 | M52: =+M211 -> 0 | N52: =+N211 -> 0 | O52: =+O211 -> 0 | P52: =+P211 -> 0 | ... T52: =+T211 -> 2 | U52: =SUM(I52:T52) -> 10002 | V52: =+$G$52*V61 -> 0 | W52: =+$G$52*W61 -> 0 | X52: =+$G$52*X61 -> 0 | Y52: =+$G$52*Y61 -> 0 | Z52: =+$G$52*Z61 -> 0 | AA52: =+$G$52*AA61 -> 0 | AB52: =+$G$52*AB61 -> 0 | AC52: =+$G$52*AC61 -> 0 | ... AG52: =+$G$52*AG61 -> 0 | AH52: =SUM(V52:AG52) -> 0 | AI52: =+$G$52*AI61 -> 0 | AJ52: =+$G$52*AJ61 -> 0 | AK52: =+$G$52*AK61 -> 0 | AL52: =+$G$52*AL61 -> 0 | AM52: =+$G$52*AM61 -> 0 | AN52: =+$G$52*AN61 -> 0 | AO52: =+$G$52*AO61 -> 0 | AP52: =+$G$52*AP61 -> 0 | ... AT52: =+$G$52*AT61 -> 0 | AU52: =SUM(AI52:AT52) -> 0 | AV52: =+$G$52*AV61 -> 0 | AW52: =+$G$52*AW61 -> 0 | AX52: =+$G$52*AX61 -> 0 | AY52: =+$G$52*AY61 -> 0 | AZ52: =+$G$52*AZ61 -> 0 | BA52: =+$G$52*BA61 -> 0 | BB52: =+$G$52*BB61 -> 0 | BC52: =+$G$52*BC61 -> 0 | ... BG52: =+$G$52*BG61 -> 0 | BH52: =SUM(AV52:BG52) -> 0 | BI52: =+$G$52*BI61 -> 0 | BJ52: =+$G$52*BJ61 -> 0 | BK52: =+$G$52*BK61 -> 0 | BL52: =+$G$52*BL61 -> 0 | BM52: =+$G$52*BM61 -> 0 | BN52: =+$G$52*BN61 -> 0 | BO52: =+$G$52*BO61 -> 0 | BP52: =+$G$52*BP61 -> 0 | ... BT52: =+$G$52*BT61 -> 0 | BU52: =SUM(BI52:BT52) -> 0 | BV52: =+BT52*$I$61 -> 0 | BW52: =+BU52*$I$61 -> 0 | BX52: =+BV52*$I$61 -> 0 | BY52: =+BW52*$I$61 -> 0 | BZ52: =+BX52*$I$61 -> 0 | CA52: =+BY52*$I$61 -> 0 | CB52: =+BZ52*$I$61 -> 0 | CC52: =+CA52*$I$61 -> 0 | ... CG52: =+CE52*$I$61 -> 0 | CH52: =SUM(BV52:CG52) -> 0 | CI52: =+$G$52*CI61 -> 0 | CJ52: =+$G$52*CJ61 -> 0 | CK52: =+$G$52*CK61 -> 0 | CL52: =+$G$52*CL61 -> 0 | CM52: =+$G$52*CM61 -> 0 | CN52: =+$G$52*CN61 -> 0 | CO52: =+$G$52*CO61 -> 0 | CP52: =+$G$52*CP61 -> 0 | ... CT52: =+$G$52*CT61 -> 0 | CU52: =SUM(CI52:CT52) -> 0 | CV52: =+$G$52*CV61 -> 0 | CW52: =+$G$52*CW61 -> 0 | CX52: =+$G$52*CX61 -> 0 | CY52: =+$G$52*CY61 -> 0 | CZ52: =+$G$52*CZ61 -> 0 | DA52: =+$G$52*DA61 -> 0 | DB52: =+$G$52*DB61 -> 0 | DC52: =+$G$52*DC61 -> 0 | ... DG52: =+$G$52*DG61 -> 0 | DH52: =SUM(CV52:DG52) -> 0 | DI52: =+$G$52*DI61 -> 0 | DJ52: =+$G$52*DJ61 -> 0 | DK52: =+$G$52*DK61 -> 0 | DL52: =+$G$52*DL61 -> 0 | DM52: =+$G$52*DM61 -> 0 | DN52: =+$G$52*DN61 -> 0 | DO52: =+$G$52*DO61 -> 0 | DP52: =+$G$52*DP61 -> 0 | ... DT52: =+$G$52*DT61 -> 0 | DU52: =SUM(DI52:DT52) -> 0 | DV52: =+$G$52*DV61 -> 0 | DW52: =+$G$52*DW61 -> 0 | DX52: =+$G$52*DX61 -> 0 | DY52: =+$G$52*DY61 -> 0 | DZ52: =+$G$52*DZ61 -> 0 | EA52: =+$G$52*EA61 -> 0 | EB52: =+$G$52*EB61 -> 0 | EC52: =+$G$52*EC61 -> 0 | ... EG52: =+$G$52*EG61 -> 0 | EH52: =SUM(DV52:EG52) -> 0
D53: =D52+1 -> 44 | F53: =+" Additions to "&Historical!C65 -> Additions to Additional Paid-In Capital | G53: =+Assumption!H260*Assumption!H253 -> 0.16 | I53: =+I212 -> 16000 | J53: =+J212 -> 0 | K53: =+K212 -> 0 | L53: =+L212 -> 0 | M53: =+M212 -> 0 | N53: =+N212 -> 0 | O53: =+O212 -> 0 | P53: =+P212 -> 0 | ... T53: =+T212 -> 3.2 | U53: =SUM(I53:T53) -> 16003.2 | V53: =+$G$53*V61 -> 0 | W53: =+$G$53*W61 -> 0 | X53: =+$G$53*X61 -> 0 | Y53: =+$G$53*Y61 -> 0 | Z53: =+$G$53*Z61 -> 0 | AA53: =+$G$53*AA61 -> 0 | AB53: =+$G$53*AB61 -> 0 | AC53: =+$G$53*AC61 -> 0 | ... AG53: =+$G$53*AG61 -> 0 | AH53: =SUM(V53:AG53) -> 0 | AI53: =+$G$53*AI61 -> 0 | AJ53: =+$G$53*AJ61 -> 0 | AK53: =+$G$53*AK61 -> 0 | AL53: =+$G$53*AL61 -> 0 | AM53: =+$G$53*AM61 -> 0 | AN53: =+$G$53*AN61 -> 0 | AO53: =+$G$53*AO61 -> 0 | AP53: =+$G$53*AP61 -> 0 | ... AT53: =+$G$53*AT61 -> 0 | AU53: =SUM(AI53:AT53) -> 0 | AV53: =+$G$53*AV61 -> 0 | AW53: =+$G$53*AW61 -> 0 | AX53: =+$G$53*AX61 -> 0 | AY53: =+$G$53*AY61 -> 0 | AZ53: =+$G$53*AZ61 -> 0 | BA53: =+$G$53*BA61 -> 0 | BB53: =+$G$53*BB61 -> 0 | BC53: =+$G$53*BC61 -> 0 | ... BG53: =+$G$53*BG61 -> 0 | BH53: =SUM(AV53:BG53) -> 0 | BI53: =+$G$53*BI61 -> 0 | BJ53: =+$G$53*BJ61 -> 0 | BK53: =+$G$53*BK61 -> 0 | BL53: =+$G$53*BL61 -> 0 | BM53: =+$G$53*BM61 -> 0 | BN53: =+$G$53*BN61 -> 0 | BO53: =+$G$53*BO61 -> 0 | BP53: =+$G$53*BP61 -> 0 | ... BT53: =+$G$53*BT61 -> 0 | BU53: =SUM(BI53:BT53) -> 0 | BV53: =+$G$53*BV61 -> 0 | BW53: =+$G$53*BW61 -> 0 | BX53: =+$G$53*BX61 -> 0 | BY53: =+$G$53*BY61 -> 0 | BZ53: =+$G$53*BZ61 -> 0 | CA53: =+$G$53*CA61 -> 0 | CB53: =+$G$53*CB61 -> 0 | CC53: =+$G$53*CC61 -> 0 | ... CG53: =+$G$53*CG61 -> 0 | CH53: =SUM(BV53:CG53) -> 0 | CI53: =+$G$53*CI61 -> 0 | CJ53: =+$G$53*CJ61 -> 0 | CK53: =+$G$53*CK61 -> 0 | CL53: =+$G$53*CL61 -> 0 | CM53: =+$G$53*CM61 -> 0 | CN53: =+$G$53*CN61 -> 0 | CO53: =+$G$53*CO61 -> 0 | CP53: =+$G$53*CP61 -> 0 | ... CT53: =+$G$53*CT61 -> 0 | CU53: =SUM(CI53:CT53) -> 0 | CV53: =+$G$53*CV61 -> 0 | CW53: =+$G$53*CW61 -> 0 | CX53: =+$G$53*CX61 -> 0 | CY53: =+$G$53*CY61 -> 0 | CZ53: =+$G$53*CZ61 -> 0 | DA53: =+$G$53*DA61 -> 0 | DB53: =+$G$53*DB61 -> 0 | DC53: =+$G$53*DC61 -> 0 | ... DG53: =+$G$53*DG61 -> 0 | DH53: =SUM(CV53:DG53) -> 0 | DI53: =+$G$53*DI61 -> 0 | DJ53: =+$G$53*DJ61 -> 0 | DK53: =+$G$53*DK61 -> 0 | DL53: =+$G$53*DL61 -> 0 | DM53: =+$G$53*DM61 -> 0 | DN53: =+$G$53*DN61 -> 0 | DO53: =+$G$53*DO61 -> 0 | DP53: =+$G$53*DP61 -> 0 | ... DT53: =+$G$53*DT61 -> 0 | DU53: =SUM(DI53:DT53) -> 0 | DV53: =+$G$53*DV61 -> 0 | DW53: =+$G$53*DW61 -> 0 | DX53: =+$G$53*DX61 -> 0 | DY53: =+$G$53*DY61 -> 0 | DZ53: =+$G$53*DZ61 -> 0 | EA53: =+$G$53*EA61 -> 0 | EB53: =+$G$53*EB61 -> 0 | EC53: =+$G$53*EC61 -> 0 | ... EG53: =+$G$53*EG61 -> 0 | EH53: =SUM(DV53:EG53) -> 0
